Workbook

Sheet Dashboard
C2: DEBT PAYOFF TRACKER | L2: StackedSheets
C4: ━━ PAYOFF METHOD ━━ | F4: ━━ EXTRA / MONTH ━━
C5: Snowball | F5: 200
I6: 🟢 = your input | K6: ■ = auto-calculated
C8: ━━ YOUR DEBT-FREE DATE ━━ | I8: ━━ PROGRESS ━━
C9: =IF(C5="Snowball",Snowball!CJ3,Avalanche!CJ3) | I9: =IF(Debts!I8>0,1-(IF(C5="Snowball",Snowball!CJ5,Avalanche!CJ5)/Debts!I8),0) | L9: paid off
C10: =IF(C5="Snowball",Snowball!CJ4,Avalanche!CJ4)&" months to freedom" | I10: ="$"&TEXT(Debts!I8-IF(C5="Snowball",Snowball!CJ5,Avalanche!CJ5),"#,##0")&" conquered so far"
C12: =Debts!I8 | F12: =Debts!I9+Dashboard!F5 | I12: =IF(C5="Snowball",Snowball!CJ2,Avalanche!CJ2) | L12: =Debts!I11
C13: ━━ TOTAL DEBT ━━ | F13: ━━ MONTHLY PAYMENT ━━ | I13: ━━ TOTAL INTEREST ━━ | L13: ━━ ACTIVE DEBTS ━━
C15: ● YOUR DEBTS
C16: DEBT NAME | E16: BALANCE | F16: APR | G16: MIN PMT | I16: PRIORITY | J16: STATUS | L16: TYPE
C17: =IF(Debts!B8="","",Debts!B8) | E17: =IF(Debts!C8="","",Debts!C8) | F17: =IF(Debts!D8="","",Debts!D8) | G17: =IF(Debts!E8="","",Debts!E8) | I17: =IF(Debts!B8="","",IF(Dashboard!$C$5="Snowball",Debts!I32,Debts!J32)) | J17: =IF(Debts!C8="","",IF(Debts!C8<=0,"✓ Paid","● Active")) | L17: =IF(Debts!F8="","",Debts!F8)
C18: =IF(Debts!B9="","",Debts!B9) | E18: =IF(Debts!C9="","",Debts!C9) | F18: =IF(Debts!D9="","",Debts!D9) | G18: =IF(Debts!E9="","",Debts!E9) | I18: =IF(Debts!B9="","",IF(Dashboard!$C$5="Snowball",Debts!I33,Debts!J33)) | J18: =IF(Debts!C9="","",IF(Debts!C9<=0,"✓ Paid","● Active")) | L18: =IF(Debts!F9="","",Debts!F9)
C19: =IF(Debts!B10="","",Debts!B10) | E19: =IF(Debts!C10="","",Debts!C10) | F19: =IF(Debts!D10="","",Debts!D10) | G19: =IF(Debts!E10="","",Debts!E10) | I19: =IF(Debts!B10="","",IF(Dashboard!$C$5="Snowball",Debts!I34,Debts!J34)) | J19: =IF(Debts!C10="","",IF(Debts!C10<=0,"✓ Paid","● Active")) | L19: =IF(Debts!F10="","",Debts!F10)
C20: =IF(Debts!B11="","",Debts!B11) | E20: =IF(Debts!C11="","",Debts!C11) | F20: =IF(Debts!D11="","",Debts!D11) | G20: =IF(Debts!E11="","",Debts!E11) | I20: =IF(Debts!B11="","",IF(Dashboard!$C$5="Snowball",Debts!I35,Debts!J35)) | J20: =IF(Debts!C11="","",IF(Debts!C11<=0,"✓ Paid","● Active")) | L20: =IF(Debts!F11="","",Debts!F11)
C21: =IF(Debts!B12="","",Debts!B12) | E21: =IF(Debts!C12="","",Debts!C12) | F21: =IF(Debts!D12="","",Debts!D12) | G21: =IF(Debts!E12="","",Debts!E12) | I21: =IF(Debts!B12="","",IF(Dashboard!$C$5="Snowball",Debts!I36,Debts!J36)) | J21: =IF(Debts!C12="","",IF(Debts!C12<=0,"✓ Paid","● Active")) | L21: =IF(Debts!F12="","",Debts!F12)
C22: =IF(Debts!B13="","",Debts!B13) | E22: =IF(Debts!C13="","",Debts!C13) | F22: =IF(Debts!D13="","",Debts!D13) | G22: =IF(Debts!E13="","",Debts!E13) | I22: =IF(Debts!B13="","",IF(Dashboard!$C$5="Snowball",Debts!I37,Debts!J37)) | J22: =IF(Debts!C13="","",IF(Debts!C13<=0,"✓ Paid","● Active")) | L22: =IF(Debts!F13="","",Debts!F13)
C23: =IF(Debts!B14="","",Debts!B14) | E23: =IF(Debts!C14="","",Debts!C14) | F23: =IF(Debts!D14="","",Debts!D14) | G23: =IF(Debts!E14="","",Debts!E14) | I23: =IF(Debts!B14="","",IF(Dashboard!$C$5="Snowball",Debts!I38,Debts!J38)) | J23: =IF(Debts!C14="","",IF(Debts!C14<=0,"✓ Paid","● Active")) | L23: =IF(Debts!F14="","",Debts!F14)
C24: =IF(Debts!B15="","",Debts!B15) | E24: =IF(Debts!C15="","",Debts!C15) | F24: =IF(Debts!D15="","",Debts!D15) | G24: =IF(Debts!E15="","",Debts!E15) | I24: =IF(Debts!B15="","",IF(Dashboard!$C$5="Snowball",Debts!I39,Debts!J39)) | J24: =IF(Debts!C15="","",IF(Debts!C15<=0,"✓ Paid","● Active")) | L24: =IF(Debts!F15="","",Debts!F15)
C25: =IF(Debts!B16="","",Debts!B16) | E25: =IF(Debts!C16="","",Debts!C16) | F25: =IF(Debts!D16="","",Debts!D16) | G25: =IF(Debts!E16="","",Debts!E16) | I25: =IF(Debts!B16="","",IF(Dashboard!$C$5="Snowball",Debts!I40,Debts!J40)) | J25: =IF(Debts!C16="","",IF(Debts!C16<=0,"✓ Paid","● Active")) | L25: =IF(Debts!F16="","",Debts!F16)
C26: =IF(Debts!B17="","",Debts!B17) | E26: =IF(Debts!C17="","",Debts!C17) | F26: =IF(Debts!D17="","",Debts!D17) | G26: =IF(Debts!E17="","",Debts!E17) | I26: =IF(Debts!B17="","",IF(Dashboard!$C$5="Snowball",Debts!I41,Debts!J41)) | J26: =IF(Debts!C17="","",IF(Debts!C17<=0,"✓ Paid","● Active")) | L26: =IF(Debts!F17="","",Debts!F17)
C27: =IF(Debts!B18="","",Debts!B18) | E27: =IF(Debts!C18="","",Debts!C18) | F27: =IF(Debts!D18="","",Debts!D18) | G27: =IF(Debts!E18="","",Debts!E18) | I27: =IF(Debts!B18="","",IF(Dashboard!$C$5="Snowball",Debts!I42,Debts!J42)) | J27: =IF(Debts!C18="","",IF(Debts!C18<=0,"✓ Paid","● Active")) | L27: =IF(Debts!F18="","",Debts!F18)
C28: =IF(Debts!B19="","",Debts!B19) | E28: =IF(Debts!C19="","",Debts!C19) | F28: =IF(Debts!D19="","",Debts!D19) | G28: =IF(Debts!E19="","",Debts!E19) | I28: =IF(Debts!B19="","",IF(Dashboard!$C$5="Snowball",Debts!I43,Debts!J43)) | J28: =IF(Debts!C19="","",IF(Debts!C19<=0,"✓ Paid","● Active")) | L28: =IF(Debts!F19="","",Debts!F19)
... C36: =IF(Debts!B27="","",Debts!B27) | E36: =IF(Debts!C27="","",Debts!C27) | F36: =IF(Debts!D27="","",Debts!D27) | G36: =IF(Debts!E27="","",Debts!E27) | I36: =IF(Debts!B27="","",IF(Dashboard!$C$5="Snowball",Debts!I51,Debts!J51)) | J36: =IF(Debts!C27="","",IF(Debts!C27<=0,"✓ Paid","● Active")) | L36: =IF(Debts!F27="","",Debts!F27)
C38: ● SNOWBALL VS AVALANCHE
F39: SNOWBALL | I39: AVALANCHE | L39: SAVINGS
C40: Total Interest | F40: =Snowball!CJ2 | I40: =Avalanche!CJ2 | L40: =ABS(F40-I40)
C41: Months to Freedom | F41: =Snowball!CJ4 | I41: =Avalanche!CJ4 | L41: =ABS(F41-I41)
C42: Free Date | F42: =Snowball!CJ3 | I42: =Avalanche!CJ3
C44: =IF(Avalanche!CJ2<Snowball!CJ2,"● Avalanche saves you $"&TEXT(Snowball!CJ2-Avalanche!CJ2,"#,##0")&" in interest","● Both methods cost the same")

Sheet Debts
B2: ● ENTER YOUR DEBTS
B4: Replace sample data with your own. Blue text = editable.
B5: Highlighted cells = your input · Everything else auto-calculates
B6: DEBT NAME | C6: BALANCE OWED | D6: APR (%) | E6: MIN MONTHLY PMT | F6: TYPE | G6: LENDER / NOTES | I6: ━━ SUMMARY ━━
I8: =SUMIF(C8:C27,">"&0,C8:C27) | J8: Total Debt
I9: =SUMIF(C8:C27,">"&0,E8:E27) | J9: Total Min Payments
I10: =IF(I8>0,SUMPRODUCT((C8:C27>0)*C8:C27*D8:D27)/I8,0) | J10: Weighted Avg APR
I11: =COUNTIF(C8:C27,">"&0) | J11: Active Debts
B30: — Calculation helpers — | I30: SnowRk | J30: AvalRk
I31: =IF(C8="",99,IF(C8<=0,99,RANK(C8,C$8:C$27,1)+COUNTIFS(C$8:C$27,C8,D$8:D$27,">"&D8))) | J31: =IF(C8="",99,IF(C8<=0,99,RANK(D8,D$8:D$27,0)+COUNTIFS(D$8:D$27,D8,C$8:C$27,"<"&C8)))
I32: =IF(C9="",99,IF(C9<=0,99,RANK(C9,C$8:C$27,1)+COUNTIFS(C$8:C$27,C9,D$8:D$27,">"&D9))) | J32: =IF(C9="",99,IF(C9<=0,99,RANK(D9,D$8:D$27,0)+COUNTIFS(D$8:D$27,D9,C$8:C$27,"<"&C9)))
I33: =IF(C10="",99,IF(C10<=0,99,RANK(C10,C$8:C$27,1)+COUNTIFS(C$8:C$27,C10,D$8:D$27,">"&D10))) | J33: =IF(C10="",99,IF(C10<=0,99,RANK(D10,D$8:D$27,0)+COUNTIFS(D$8:D$27,D10,C$8:C$27,"<"&C10)))
I34: =IF(C11="",99,IF(C11<=0,99,RANK(C11,C$8:C$27,1)+COUNTIFS(C$8:C$27,C11,D$8:D$27,">"&D11))) | J34: =IF(C11="",99,IF(C11<=0,99,RANK(D11,D$8:D$27,0)+COUNTIFS(D$8:D$27,D11,C$8:C$27,"<"&C11)))
I35: =IF(C12="",99,IF(C12<=0,99,RANK(C12,C$8:C$27,1)+COUNTIFS(C$8:C$27,C12,D$8:D$27,">"&D12))) | J35: =IF(C12="",99,IF(C12<=0,99,RANK(D12,D$8:D$27,0)+COUNTIFS(D$8:D$27,D12,C$8:C$27,"<"&C12)))
I36: =IF(C13="",99,IF(C13<=0,99,RANK(C13,C$8:C$27,1)+COUNTIFS(C$8:C$27,C13,D$8:D$27,">"&D13))) | J36: =IF(C13="",99,IF(C13<=0,99,RANK(D13,D$8:D$27,0)+COUNTIFS(D$8:D$27,D13,C$8:C$27,"<"&C13)))
I37: =IF(C14="",99,IF(C14<=0,99,RANK(C14,C$8:C$27,1)+COUNTIFS(C$8:C$27,C14,D$8:D$27,">"&D14))) | J37: =IF(C14="",99,IF(C14<=0,99,RANK(D14,D$8:D$27,0)+COUNTIFS(D$8:D$27,D14,C$8:C$27,"<"&C14)))
I38: =IF(C15="",99,IF(C15<=0,99,RANK(C15,C$8:C$27,1)+COUNTIFS(C$8:C$27,C15,D$8:D$27,">"&D15))) | J38: =IF(C15="",99,IF(C15<=0,99,RANK(D15,D$8:D$27,0)+COUNTIFS(D$8:D$27,D15,C$8:C$27,"<"&C15)))
I39: =IF(C16="",99,IF(C16<=0,99,RANK(C16,C$8:C$27,1)+COUNTIFS(C$8:C$27,C16,D$8:D$27,">"&D16))) | J39: =IF(C16="",99,IF(C16<=0,99,RANK(D16,D$8:D$27,0)+COUNTIFS(D$8:D$27,D16,C$8:C$27,"<"&C16)))
I40: =IF(C17="",99,IF(C17<=0,99,RANK(C17,C$8:C$27,1)+COUNTIFS(C$8:C$27,C17,D$8:D$27,">"&D17))) | J40: =IF(C17="",99,IF(C17<=0,99,RANK(D17,D$8:D$27,0)+COUNTIFS(D$8:D$27,D17,C$8:C$27,"<"&C17)))
I41: =IF(C18="",99,IF(C18<=0,99,RANK(C18,C$8:C$27,1)+COUNTIFS(C$8:C$27,C18,D$8:D$27,">"&D18))) | J41: =IF(C18="",99,IF(C18<=0,99,RANK(D18,D$8:D$27,0)+COUNTIFS(D$8:D$27,D18,C$8:C$27,"<"&C18)))
I42: =IF(C19="",99,IF(C19<=0,99,RANK(C19,C$8:C$27,1)+COUNTIFS(C$8:C$27,C19,D$8:D$27,">"&D19))) | J42: =IF(C19="",99,IF(C19<=0,99,RANK(D19,D$8:D$27,0)+COUNTIFS(D$8:D$27,D19,C$8:C$27,"<"&C19)))
... I50: =IF(C27="",99,IF(C27<=0,99,RANK(C27,C$8:C$27,1)+COUNTIFS(C$8:C$27,C27,D$8:D$27,">"&D27))) | J50: =IF(C27="",99,IF(C27<=0,99,RANK(D27,D$8:D$27,0)+COUNTIFS(D$8:D$27,D27,C$8:C$27,"<"&C27)))

Sheet Snowball
B1: ● SNOWBALL SCHEDULE
B2: Month | C2: Total Paid | D2: =IF(Debts!B8="","—",Debts!B8) | H2: =IF(Debts!B9="","—",Debts!B9) | L2: =IF(Debts!B10="","—",Debts!B10) | P2: =IF(Debts!B11="","—",Debts!B11) | T2: =IF(Debts!B12="","—",Debts!B12) | X2: =IF(Debts!B13="","—",Debts!B13) | AB2: =IF(Debts!B14="","—",Debts!B14) | AF2: =IF(Debts!B15="","—",Debts!B15) | AJ2: =IF(Debts!B16="","—",Debts!B16) | AN2: =IF(Debts!B17="","—",Debts!B17) | AR2: =IF(Debts!B18="","—",Debts!B18) | AV2: =IF(Debts!B19="","—",Debts!B19) | AZ2: =IF(Debts!B20="","—",Debts!B20) | BD2: =IF(Debts!B21="","—",Debts!B21) | BH2: =IF(Debts!B22="","—",Debts!B22) | BL2: =IF(Debts!B23="","—",Debts!B23) | BP2: =IF(Debts!B24="","—",Debts!B24) | BT2: =IF(Debts!B25="","—",Debts!B25) | BX2: =IF(Debts!B26="","—",Debts!B26) | CB2: =IF(Debts!B27="","—",Debts!B27) | CF2: Total Rem | CG2: Month Int | CH2: Cum Int | CJ2: =CH124
D3: Bal | E3: Int | F3: Pmt | G3: End | H3: Bal | I3: Int | J3: Pmt | K3: End | L3: Bal | M3: Int | N3: Pmt | O3: End | P3: Bal | Q3: Int | R3: Pmt | S3: End | T3: Bal | U3: Int | V3: Pmt | W3: End | X3: Bal | Y3: Int | Z3: Pmt | AA3: End | AB3: Bal | AC3: Int | AD3: Pmt | AE3: End | AF3: Bal | AG3: Int | AH3: Pmt | AI3: End | AJ3: Bal | AK3: Int | AL3: Pmt | AM3: End | AN3: Bal | AO3: Int | AP3: Pmt | AQ3: End | AR3: Bal | AS3: Int | AT3: Pmt | AU3: End | AV3: Bal | AW3: Int | AX3: Pmt | AY3: End | AZ3: Bal | BA3: Int | BB3: Pmt | BC3: End | BD3: Bal | BE3: Int | BF3: Pmt | BG3: End | BH3: Bal | BI3: Int | BJ3: Pmt | BK3: End | BL3: Bal | BM3: Int | BN3: Pmt | BO3: End | BP3: Bal | BQ3: Int | BR3: Pmt | BS3: End | BT3: Bal | BU3: Int | BV3: Pmt | BW3: End | BX3: Bal | BY3: Int | BZ3: Pmt | CA3: End | CB3: Bal | CC3: Int | CD3: Pmt | CE3: End | CJ3: =IFERROR(DATE(YEAR(TODAY()),MONTH(TODAY())+MATCH(TRUE(),INDEX(CF5:CF124<=0.01,0),0),DAY(TODAY())),"10+ years")
B4: 0 | C4: 0 | D4: =IF(Debts!C8="",0,Debts!C8) | E4: 0 | F4: 0 | G4: =IF(Debts!C8="",0,Debts!C8) | H4: =IF(Debts!C9="",0,Debts!C9) | I4: 0 | J4: 0 | K4: =IF(Debts!C9="",0,Debts!C9) | L4: =IF(Debts!C10="",0,Debts!C10) | M4: 0 | N4: 0 | O4: =IF(Debts!C10="",0,Debts!C10) | P4: =IF(Debts!C11="",0,Debts!C11) | Q4: 0 | R4: 0 | S4: =IF(Debts!C11="",0,Debts!C11) | T4: =IF(Debts!C12="",0,Debts!C12) | U4: 0 | V4: 0 | W4: =IF(Debts!C12="",0,Debts!C12) | X4: =IF(Debts!C13="",0,Debts!C13) | Y4: 0 | Z4: 0 | AA4: =IF(Debts!C13="",0,Debts!C13) | AB4: =IF(Debts!C14="",0,Debts!C14) | AC4: 0 | AD4: 0 | AE4: =IF(Debts!C14="",0,Debts!C14) | AF4: =IF(Debts!C15="",0,Debts!C15) | AG4: 0 | AH4: 0 | AI4: =IF(Debts!C15="",0,Debts!C15) | AJ4: =IF(Debts!C16="",0,Debts!C16) | AK4: 0 | AL4: 0 | AM4: =IF(Debts!C16="",0,Debts!C16) | AN4: =IF(Debts!C17="",0,Debts!C17) | AO4: 0 | AP4: 0 | AQ4: =IF(Debts!C17="",0,Debts!C17) | AR4: =IF(Debts!C18="",0,Debts!C18) | AS4: 0 | AT4: 0 | AU4: =IF(Debts!C18="",0,Debts!C18) | AV4: =IF(Debts!C19="",0,Debts!C19) | AW4: 0 | AX4: 0 | AY4: =IF(Debts!C19="",0,Debts!C19) | AZ4: =IF(Debts!C20="",0,Debts!C20) | BA4: 0 | BB4: 0 | BC4: =IF(Debts!C20="",0,Debts!C20) | BD4: =IF(Debts!C21="",0,Debts!C21) | BE4: 0 | BF4: 0 | BG4: =IF(Debts!C21="",0,Debts!C21) | BH4: =IF(Debts!C22="",0,Debts!C22) | BI4: 0 | BJ4: 0 | BK4: =IF(Debts!C22="",0,Debts!C22) | BL4: =IF(Debts!C23="",0,Debts!C23) | BM4: 0 | BN4: 0 | BO4: =IF(Debts!C23="",0,Debts!C23) | BP4: =IF(Debts!C24="",0,Debts!C24) | BQ4: 0 | BR4: 0 | BS4: =IF(Debts!C24="",0,Debts!C24) | BT4: =IF(Debts!C25="",0,Debts!C25) | BU4: 0 | BV4: 0 | BW4: =IF(Debts!C25="",0,Debts!C25) | BX4: =IF(Debts!C26="",0,Debts!C26) | BY4: 0 | BZ4: 0 | CA4: =IF(Debts!C26="",0,Debts!C26) | CB4: =IF(Debts!C27="",0,Debts!C27) | CC4: 0 | CD4: 0 | CE4: =IF(Debts!C27="",0,Debts!C27) | CF4: =G4+K4+O4+S4+W4+AA4+AE4+AI4+AM4+AQ4+AU4+AY4+BC4+BG4+BK4+BO4+BS4+BW4+CA4+CE4 | CG4: 0 | CH4: 0 | CJ4: =IFERROR(MATCH(TRUE(),INDEX(CF5:CF124<=0.01,0),0),120)
B5: 1 | C5: =F5+J5+N5+R5+V5+Z5+AD5+AH5+AL5+AP5+AT5+AX5+BB5+BF5+BJ5+BN5+BR5+BV5+BZ5+CD5 | D5: =G4 | E5: =IF(D5>0.005,D5*Debts!D8/12,0) | F5: 0 | G5: =MAX(0,D5+E5-F5) | H5: =K4 | I5: =IF(H5>0.005,H5*Debts!D9/12,0) | J5: 0 | K5: =MAX(0,H5+I5-J5) | L5: =O4 | M5: =IF(L5>0.005,L5*Debts!D10/12,0) | N5: 0 | O5: =MAX(0,L5+M5-N5) | P5: =S4 | Q5: =IF(P5>0.005,P5*Debts!D11/12,0) | R5: 0 | S5: =MAX(0,P5+Q5-R5) | T5: =W4 | U5: =IF(T5>0.005,T5*Debts!D12/12,0) | V5: 0 | W5: =MAX(0,T5+U5-V5) | X5: =AA4 | Y5: =IF(X5>0.005,X5*Debts!D13/12,0) | Z5: 0 | AA5: =MAX(0,X5+Y5-Z5) | AB5: =AE4 | AC5: =IF(AB5>0.005,AB5*Debts!D14/12,0) | AD5: 0 | AE5: =MAX(0,AB5+AC5-AD5) | AF5: =AI4 | AG5: =IF(AF5>0.005,AF5*Debts!D15/12,0) | AH5: 0 | AI5: =MAX(0,AF5+AG5-AH5) | AJ5: =AM4 | AK5: =IF(AJ5>0.005,AJ5*Debts!D16/12,0) | AL5: 0 | AM5: =MAX(0,AJ5+AK5-AL5) | AN5: =AQ4 | AO5: =IF(AN5>0.005,AN5*Debts!D17/12,0) | AP5: 0 | AQ5: =MAX(0,AN5+AO5-AP5) | AR5: =AU4 | AS5: =IF(AR5>0.005,AR5*Debts!D18/12,0) | AT5: 0 | AU5: =MAX(0,AR5+AS5-AT5) | AV5: =AY4 | AW5: =IF(AV5>0.005,AV5*Debts!D19/12,0) | AX5: 0 | AY5: =MAX(0,AV5+AW5-AX5) | AZ5: =BC4 | BA5: =IF(AZ5>0.005,AZ5*Debts!D20/12,0) | BB5: 0 | BC5: =MAX(0,AZ5+BA5-BB5) | BD5: =BG4 | BE5: =IF(BD5>0.005,BD5*Debts!D21/12,0) | BF5: 0 | BG5: =MAX(0,BD5+BE5-BF5) | BH5: =BK4 | BI5: =IF(BH5>0.005,BH5*Debts!D22/12,0) | BJ5: 0 | BK5: =MAX(0,BH5+BI5-BJ5) | BL5: =BO4 | BM5: =IF(BL5>0.005,BL5*Debts!D23/12,0) | BN5: 0 | BO5: =MAX(0,BL5+BM5-BN5) | BP5: =BS4 | BQ5: =IF(BP5>0.005,BP5*Debts!D24/12,0) | BR5: 0 | BS5: =MAX(0,BP5+BQ5-BR5) | BT5: =BW4 | BU5: =IF(BT5>0.005,BT5*Debts!D25/12,0) | BV5: 0 | BW5: =MAX(0,BT5+BU5-BV5) | BX5: =CA4 | BY5: =IF(BX5>0.005,BX5*Debts!D26/12,0) | BZ5: 0 | CA5: =MAX(0,BX5+BY5-BZ5) | CB5: =CE4 | CC5: =IF(CB5>0.005,CB5*Debts!D27/12,0) | CD5: 0 | CE5: =MAX(0,CB5+CC5-CD5) | CF5: =G5+K5+O5+S5+W5+AA5+AE5+AI5+AM5+AQ5+AU5+AY5+BC5+BG5+BK5+BO5+BS5+BW5+CA5+CE5 | CG5: =E5+I5+M5+Q5+U5+Y5+AC5+AG5+AK5+AO5+AS5+AW5+BA5+BE5+BI5+BM5+BQ5+BU5+BY5+CC5 | CH5: =CH4+CG5 | CJ5: =CF5
B6: 2 | C6: =F6+J6+N6+R6+V6+Z6+AD6+AH6+AL6+AP6+AT6+AX6+BB6+BF6+BJ6+BN6+BR6+BV6+BZ6+CD6 | D6: =G5 | E6: =IF(D6>0.005,D6*Debts!D8/12,0) | F6: 0 | G6: =MAX(0,D6+E6-F6) | H6: =K5 | I6: =IF(H6>0.005,H6*Debts!D9/12,0) | J6: 0 | K6: =MAX(0,H6+I6-J6) | L6: =O5 | M6: =IF(L6>0.005,L6*Debts!D10/12,0) | N6: 0 | O6: =MAX(0,L6+M6-N6) | P6: =S5 | Q6: =IF(P6>0.005,P6*Debts!D11/12,0) | R6: 0 | S6: =MAX(0,P6+Q6-R6) | T6: =W5 | U6: =IF(T6>0.005,T6*Debts!D12/12,0) | V6: 0 | W6: =MAX(0,T6+U6-V6) | X6: =AA5 | Y6: =IF(X6>0.005,X6*Debts!D13/12,0) | Z6: 0 | AA6: =MAX(0,X6+Y6-Z6) | AB6: =AE5 | AC6: =IF(AB6>0.005,AB6*Debts!D14/12,0) | AD6: 0 | AE6: =MAX(0,AB6+AC6-AD6) | AF6: =AI5 | AG6: =IF(AF6>0.005,AF6*Debts!D15/12,0) | AH6: 0 | AI6: =MAX(0,AF6+AG6-AH6) | AJ6: =AM5 | AK6: =IF(AJ6>0.005,AJ6*Debts!D16/12,0) | AL6: 0 | AM6: =MAX(0,AJ6+AK6-AL6) | AN6: =AQ5 | AO6: =IF(AN6>0.005,AN6*Debts!D17/12,0) | AP6: 0 | AQ6: =MAX(0,AN6+AO6-AP6) | AR6: =AU5 | AS6: =IF(AR6>0.005,AR6*Debts!D18/12,0) | AT6: 0 | AU6: =MAX(0,AR6+AS6-AT6) | AV6: =AY5 | AW6: =IF(AV6>0.005,AV6*Debts!D19/12,0) | AX6: 0 | AY6: =MAX(0,AV6+AW6-AX6) | AZ6: =BC5 | BA6: =IF(AZ6>0.005,AZ6*Debts!D20/12,0) | BB6: 0 | BC6: =MAX(0,AZ6+BA6-BB6) | BD6: =BG5 | BE6: =IF(BD6>0.005,BD6*Debts!D21/12,0) | BF6: 0 | BG6: =MAX(0,BD6+BE6-BF6) | BH6: =BK5 | BI6: =IF(BH6>0.005,BH6*Debts!D22/12,0) | BJ6: 0 | BK6: =MAX(0,BH6+BI6-BJ6) | BL6: =BO5 | BM6: =IF(BL6>0.005,BL6*Debts!D23/12,0) | BN6: 0 | BO6: =MAX(0,BL6+BM6-BN6) | BP6: =BS5 | BQ6: =IF(BP6>0.005,BP6*Debts!D24/12,0) | BR6: 0 | BS6: =MAX(0,BP6+BQ6-BR6) | BT6: =BW5 | BU6: =IF(BT6>0.005,BT6*Debts!D25/12,0) | BV6: 0 | BW6: =MAX(0,BT6+BU6-BV6) | BX6: =CA5 | BY6: =IF(BX6>0.005,BX6*Debts!D26/12,0) | BZ6: 0 | CA6: =MAX(0,BX6+BY6-BZ6) | CB6: =CE5 | CC6: =IF(CB6>0.005,CB6*Debts!D27/12,0) | CD6: 0 | CE6: =MAX(0,CB6+CC6-CD6) | CF6: =G6+K6+O6+S6+W6+AA6+AE6+AI6+AM6+AQ6+AU6+AY6+BC6+BG6+BK6+BO6+BS6+BW6+CA6+CE6 | CG6: =E6+I6+M6+Q6+U6+Y6+AC6+AG6+AK6+AO6+AS6+AW6+BA6+BE6+BI6+BM6+BQ6+BU6+BY6+CC6 | CH6: =CH5+CG6
B7: 3 | C7: =F7+J7+N7+R7+V7+Z7+AD7+AH7+AL7+AP7+AT7+AX7+BB7+BF7+BJ7+BN7+BR7+BV7+BZ7+CD7 | D7: =G6 | E7: =IF(D7>0.005,D7*Debts!D8/12,0) | F7: 0 | G7: =MAX(0,D7+E7-F7) | H7: =K6 | I7: =IF(H7>0.005,H7*Debts!D9/12,0) | J7: 0 | K7: =MAX(0,H7+I7-J7) | L7: =O6 | M7: =IF(L7>0.005,L7*Debts!D10/12,0) | N7: 0 | O7: =MAX(0,L7+M7-N7) | P7: =S6 | Q7: =IF(P7>0.005,P7*Debts!D11/12,0) | R7: 0 | S7: =MAX(0,P7+Q7-R7) | T7: =W6 | U7: =IF(T7>0.005,T7*Debts!D12/12,0) | V7: 0 | W7: =MAX(0,T7+U7-V7) | X7: =AA6 | Y7: =IF(X7>0.005,X7*Debts!D13/12,0) | Z7: 0 | AA7: =MAX(0,X7+Y7-Z7) | AB7: =AE6 | AC7: =IF(AB7>0.005,AB7*Debts!D14/12,0) | AD7: 0 | AE7: =MAX(0,AB7+AC7-AD7) | AF7: =AI6 | AG7: =IF(AF7>0.005,AF7*Debts!D15/12,0) | AH7: 0 | AI7: =MAX(0,AF7+AG7-AH7) | AJ7: =AM6 | AK7: =IF(AJ7>0.005,AJ7*Debts!D16/12,0) | AL7: 0 | AM7: =MAX(0,AJ7+AK7-AL7) | AN7: =AQ6 | AO7: =IF(AN7>0.005,AN7*Debts!D17/12,0) | AP7: 0 | AQ7: =MAX(0,AN7+AO7-AP7) | AR7: =AU6 | AS7: =IF(AR7>0.005,AR7*Debts!D18/12,0) | AT7: 0 | AU7: =MAX(0,AR7+AS7-AT7) | AV7: =AY6 | AW7: =IF(AV7>0.005,AV7*Debts!D19/12,0) | AX7: 0 | AY7: =MAX(0,AV7+AW7-AX7) | AZ7: =BC6 | BA7: =IF(AZ7>0.005,AZ7*Debts!D20/12,0) | BB7: 0 | BC7: =MAX(0,AZ7+BA7-BB7) | BD7: =BG6 | BE7: =IF(BD7>0.005,BD7*Debts!D21/12,0) | BF7: 0 | BG7: =MAX(0,BD7+BE7-BF7) | BH7: =BK6 | BI7: =IF(BH7>0.005,BH7*Debts!D22/12,0) | BJ7: 0 | BK7: =MAX(0,BH7+BI7-BJ7) | BL7: =BO6 | BM7: =IF(BL7>0.005,BL7*Debts!D23/12,0) | BN7: 0 | BO7: =MAX(0,BL7+BM7-BN7) | BP7: =BS6 | BQ7: =IF(BP7>0.005,BP7*Debts!D24/12,0) | BR7: 0 | BS7: =MAX(0,BP7+BQ7-BR7) | BT7: =BW6 | BU7: =IF(BT7>0.005,BT7*Debts!D25/12,0) | BV7: 0 | BW7: =MAX(0,BT7+BU7-BV7) | BX7: =CA6 | BY7: =IF(BX7>0.005,BX7*Debts!D26/12,0) | BZ7: 0 | CA7: =MAX(0,BX7+BY7-BZ7) | CB7: =CE6 | CC7: =IF(CB7>0.005,CB7*Debts!D27/12,0) | CD7: 0 | CE7: =MAX(0,CB7+CC7-CD7) | CF7: =G7+K7+O7+S7+W7+AA7+AE7+AI7+AM7+AQ7+AU7+AY7+BC7+BG7+BK7+BO7+BS7+BW7+CA7+CE7 | CG7: =E7+I7+M7+Q7+U7+Y7+AC7+AG7+AK7+AO7+AS7+AW7+BA7+BE7+BI7+BM7+BQ7+BU7+BY7+CC7 | CH7: =CH6+CG7
B8: 4 | C8: =F8+J8+N8+R8+V8+Z8+AD8+AH8+AL8+AP8+AT8+AX8+BB8+BF8+BJ8+BN8+BR8+BV8+BZ8+CD8 | D8: =G7 | E8: =IF(D8>0.005,D8*Debts!D8/12,0) | F8: 0 | G8: =MAX(0,D8+E8-F8) | H8: =K7 | I8: =IF(H8>0.005,H8*Debts!D9/12,0) | J8: 0 | K8: =MAX(0,H8+I8-J8) | L8: =O7 | M8: =IF(L8>0.005,L8*Debts!D10/12,0) | N8: 0 | O8: =MAX(0,L8+M8-N8) | P8: =S7 | Q8: =IF(P8>0.005,P8*Debts!D11/12,0) | R8: 0 | S8: =MAX(0,P8+Q8-R8) | T8: =W7 | U8: =IF(T8>0.005,T8*Debts!D12/12,0) | V8: 0 | W8: =MAX(0,T8+U8-V8) | X8: =AA7 | Y8: =IF(X8>0.005,X8*Debts!D13/12,0) | Z8: 0 | AA8: =MAX(0,X8+Y8-Z8) | AB8: =AE7 | AC8: =IF(AB8>0.005,AB8*Debts!D14/12,0) | AD8: 0 | AE8: =MAX(0,AB8+AC8-AD8) | AF8: =AI7 | AG8: =IF(AF8>0.005,AF8*Debts!D15/12,0) | AH8: 0 | AI8: =MAX(0,AF8+AG8-AH8) | AJ8: =AM7 | AK8: =IF(AJ8>0.005,AJ8*Debts!D16/12,0) | AL8: 0 | AM8: =MAX(0,AJ8+AK8-AL8) | AN8: =AQ7 | AO8: =IF(AN8>0.005,AN8*Debts!D17/12,0) | AP8: 0 | AQ8: =MAX(0,AN8+AO8-AP8) | AR8: =AU7 | AS8: =IF(AR8>0.005,AR8*Debts!D18/12,0) | AT8: 0 | AU8: =MAX(0,AR8+AS8-AT8) | AV8: =AY7 | AW8: =IF(AV8>0.005,AV8*Debts!D19/12,0) | AX8: 0 | AY8: =MAX(0,AV8+AW8-AX8) | AZ8: =BC7 | BA8: =IF(AZ8>0.005,AZ8*Debts!D20/12,0) | BB8: 0 | BC8: =MAX(0,AZ8+BA8-BB8) | BD8: =BG7 | BE8: =IF(BD8>0.005,BD8*Debts!D21/12,0) | BF8: 0 | BG8: =MAX(0,BD8+BE8-BF8) | BH8: =BK7 | BI8: =IF(BH8>0.005,BH8*Debts!D22/12,0) | BJ8: 0 | BK8: =MAX(0,BH8+BI8-BJ8) | BL8: =BO7 | BM8: =IF(BL8>0.005,BL8*Debts!D23/12,0) | BN8: 0 | BO8: =MAX(0,BL8+BM8-BN8) | BP8: =BS7 | BQ8: =IF(BP8>0.005,BP8*Debts!D24/12,0) | BR8: 0 | BS8: =MAX(0,BP8+BQ8-BR8) | BT8: =BW7 | BU8: =IF(BT8>0.005,BT8*Debts!D25/12,0) | BV8: 0 | BW8: =MAX(0,BT8+BU8-BV8) | BX8: =CA7 | BY8: =IF(BX8>0.005,BX8*Debts!D26/12,0) | BZ8: 0 | CA8: =MAX(0,BX8+BY8-BZ8) | CB8: =CE7 | CC8: =IF(CB8>0.005,CB8*Debts!D27/12,0) | CD8: 0 | CE8: =MAX(0,CB8+CC8-CD8) | CF8: =G8+K8+O8+S8+W8+AA8+AE8+AI8+AM8+AQ8+AU8+AY8+BC8+BG8+BK8+BO8+BS8+BW8+CA8+CE8 | CG8: =E8+I8+M8+Q8+U8+Y8+AC8+AG8+AK8+AO8+AS8+AW8+BA8+BE8+BI8+BM8+BQ8+BU8+BY8+CC8 | CH8: =CH7+CG8
B9: 5 | C9: =F9+J9+N9+R9+V9+Z9+AD9+AH9+AL9+AP9+AT9+AX9+BB9+BF9+BJ9+BN9+BR9+BV9+BZ9+CD9 | D9: =G8 | E9: =IF(D9>0.005,D9*Debts!D8/12,0) | F9: 0 | G9: =MAX(0,D9+E9-F9) | H9: =K8 | I9: =IF(H9>0.005,H9*Debts!D9/12,0) | J9: 0 | K9: =MAX(0,H9+I9-J9) | L9: =O8 | M9: =IF(L9>0.005,L9*Debts!D10/12,0) | N9: 0 | O9: =MAX(0,L9+M9-N9) | P9: =S8 | Q9: =IF(P9>0.005,P9*Debts!D11/12,0) | R9: 0 | S9: =MAX(0,P9+Q9-R9) | T9: =W8 | U9: =IF(T9>0.005,T9*Debts!D12/12,0) | V9: 0 | W9: =MAX(0,T9+U9-V9) | X9: =AA8 | Y9: =IF(X9>0.005,X9*Debts!D13/12,0) | Z9: 0 | AA9: =MAX(0,X9+Y9-Z9) | AB9: =AE8 | AC9: =IF(AB9>0.005,AB9*Debts!D14/12,0) | AD9: 0 | AE9: =MAX(0,AB9+AC9-AD9) | AF9: =AI8 | AG9: =IF(AF9>0.005,AF9*Debts!D15/12,0) | AH9: 0 | AI9: =MAX(0,AF9+AG9-AH9) | AJ9: =AM8 | AK9: =IF(AJ9>0.005,AJ9*Debts!D16/12,0) | AL9: 0 | AM9: =MAX(0,AJ9+AK9-AL9) | AN9: =AQ8 | AO9: =IF(AN9>0.005,AN9*Debts!D17/12,0) | AP9: 0 | AQ9: =MAX(0,AN9+AO9-AP9) | AR9: =AU8 | AS9: =IF(AR9>0.005,AR9*Debts!D18/12,0) | AT9: 0 | AU9: =MAX(0,AR9+AS9-AT9) | AV9: =AY8 | AW9: =IF(AV9>0.005,AV9*Debts!D19/12,0) | AX9: 0 | AY9: =MAX(0,AV9+AW9-AX9) | AZ9: =BC8 | BA9: =IF(AZ9>0.005,AZ9*Debts!D20/12,0) | BB9: 0 | BC9: =MAX(0,AZ9+BA9-BB9) | BD9: =BG8 | BE9: =IF(BD9>0.005,BD9*Debts!D21/12,0) | BF9: 0 | BG9: =MAX(0,BD9+BE9-BF9) | BH9: =BK8 | BI9: =IF(BH9>0.005,BH9*Debts!D22/12,0) | BJ9: 0 | BK9: =MAX(0,BH9+BI9-BJ9) | BL9: =BO8 | BM9: =IF(BL9>0.005,BL9*Debts!D23/12,0) | BN9: 0 | BO9: =MAX(0,BL9+BM9-BN9) | BP9: =BS8 | BQ9: =IF(BP9>0.005,BP9*Debts!D24/12,0) | BR9: 0 | BS9: =MAX(0,BP9+BQ9-BR9) | BT9: =BW8 | BU9: =IF(BT9>0.005,BT9*Debts!D25/12,0) | BV9: 0 | BW9: =MAX(0,BT9+BU9-BV9) | BX9: =CA8 | BY9: =IF(BX9>0.005,BX9*Debts!D26/12,0) | BZ9: 0 | CA9: =MAX(0,BX9+BY9-BZ9) | CB9: =CE8 | CC9: =IF(CB9>0.005,CB9*Debts!D27/12,0) | CD9: 0 | CE9: =MAX(0,CB9+CC9-CD9) | CF9: =G9+K9+O9+S9+W9+AA9+AE9+AI9+AM9+AQ9+AU9+AY9+BC9+BG9+BK9+BO9+BS9+BW9+CA9+CE9 | CG9: =E9+I9+M9+Q9+U9+Y9+AC9+AG9+AK9+AO9+AS9+AW9+BA9+BE9+BI9+BM9+BQ9+BU9+BY9+CC9 | CH9: =CH8+CG9
B10: 6 | C10: =F10+J10+N10+R10+V10+Z10+AD10+AH10+AL10+AP10+AT10+AX10+BB10+BF10+BJ10+BN10+BR10+BV10+BZ10+CD10 | D10: =G9 | E10: =IF(D10>0.005,D10*Debts!D8/12,0) | F10: 0 | G10: =MAX(0,D10+E10-F10) | H10: =K9 | I10: =IF(H10>0.005,H10*Debts!D9/12,0) | J10: 0 | K10: =MAX(0,H10+I10-J10) | L10: =O9 | M10: =IF(L10>0.005,L10*Debts!D10/12,0) | N10: 0 | O10: =MAX(0,L10+M10-N10) | P10: =S9 | Q10: =IF(P10>0.005,P10*Debts!D11/12,0) | R10: 0 | S10: =MAX(0,P10+Q10-R10) | T10: =W9 | U10: =IF(T10>0.005,T10*Debts!D12/12,0) | V10: 0 | W10: =MAX(0,T10+U10-V10) | X10: =AA9 | Y10: =IF(X10>0.005,X10*Debts!D13/12,0) | Z10: 0 | AA10: =MAX(0,X10+Y10-Z10) | AB10: =AE9 | AC10: =IF(AB10>0.005,AB10*Debts!D14/12,0) | AD10: 0 | AE10: =MAX(0,AB10+AC10-AD10) | AF10: =AI9 | AG10: =IF(AF10>0.005,AF10*Debts!D15/12,0) | AH10: 0 | AI10: =MAX(0,AF10+AG10-AH10) | AJ10: =AM9 | AK10: =IF(AJ10>0.005,AJ10*Debts!D16/12,0) | AL10: 0 | AM10: =MAX(0,AJ10+AK10-AL10) | AN10: =AQ9 | AO10: =IF(AN10>0.005,AN10*Debts!D17/12,0) | AP10: 0 | AQ10: =MAX(0,AN10+AO10-AP10) | AR10: =AU9 | AS10: =IF(AR10>0.005,AR10*Debts!D18/12,0) | AT10: 0 | AU10: =MAX(0,AR10+AS10-AT10) | AV10: =AY9 | AW10: =IF(AV10>0.005,AV10*Debts!D19/12,0) | AX10: 0 | AY10: =MAX(0,AV10+AW10-AX10) | AZ10: =BC9 | BA10: =IF(AZ10>0.005,AZ10*Debts!D20/12,0) | BB10: 0 | BC10: =MAX(0,AZ10+BA10-BB10) | BD10: =BG9 | BE10: =IF(BD10>0.005,BD10*Debts!D21/12,0) | BF10: 0 | BG10: =MAX(0,BD10+BE10-BF10) | BH10: =BK9 | BI10: =IF(BH10>0.005,BH10*Debts!D22/12,0) | BJ10: 0 | BK10: =MAX(0,BH10+BI10-BJ10) | BL10: =BO9 | BM10: =IF(BL10>0.005,BL10*Debts!D23/12,0) | BN10: 0 | BO10: =MAX(0,BL10+BM10-BN10) | BP10: =BS9 | BQ10: =IF(BP10>0.005,BP10*Debts!D24/12,0) | BR10: 0 | BS10: =MAX(0,BP10+BQ10-BR10) | BT10: =BW9 | BU10: =IF(BT10>0.005,BT10*Debts!D25/12,0) | BV10: 0 | BW10: =MAX(0,BT10+BU10-BV10) | BX10: =CA9 | BY10: =IF(BX10>0.005,BX10*Debts!D26/12,0) | BZ10: 0 | CA10: =MAX(0,BX10+BY10-BZ10) | CB10: =CE9 | CC10: =IF(CB10>0.005,CB10*Debts!D27/12,0) | CD10: 0 | CE10: =MAX(0,CB10+CC10-CD10) | CF10: =G10+K10+O10+S10+W10+AA10+AE10+AI10+AM10+AQ10+AU10+AY10+BC10+BG10+BK10+BO10+BS10+BW10+CA10+CE10 | CG10: =E10+I10+M10+Q10+U10+Y10+AC10+AG10+AK10+AO10+AS10+AW10+BA10+BE10+BI10+BM10+BQ10+BU10+BY10+CC10 | CH10: =CH9+CG10
B11: 7 | C11: =F11+J11+N11+R11+V11+Z11+AD11+AH11+AL11+AP11+AT11+AX11+BB11+BF11+BJ11+BN11+BR11+BV11+BZ11+CD11 | D11: =G10 | E11: =IF(D11>0.005,D11*Debts!D8/12,0) | F11: 0 | G11: =MAX(0,D11+E11-F11) | H11: =K10 | I11: =IF(H11>0.005,H11*Debts!D9/12,0) | J11: 0 | K11: =MAX(0,H11+I11-J11) | L11: =O10 | M11: =IF(L11>0.005,L11*Debts!D10/12,0) | N11: 0 | O11: =MAX(0,L11+M11-N11) | P11: =S10 | Q11: =IF(P11>0.005,P11*Debts!D11/12,0) | R11: 0 | S11: =MAX(0,P11+Q11-R11) | T11: =W10 | U11: =IF(T11>0.005,T11*Debts!D12/12,0) | V11: 0 | W11: =MAX(0,T11+U11-V11) | X11: =AA10 | Y11: =IF(X11>0.005,X11*Debts!D13/12,0) | Z11: 0 | AA11: =MAX(0,X11+Y11-Z11) | AB11: =AE10 | AC11: =IF(AB11>0.005,AB11*Debts!D14/12,0) | AD11: 0 | AE11: =MAX(0,AB11+AC11-AD11) | AF11: =AI10 | AG11: =IF(AF11>0.005,AF11*Debts!D15/12,0) | AH11: 0 | AI11: =MAX(0,AF11+AG11-AH11) | AJ11: =AM10 | AK11: =IF(AJ11>0.005,AJ11*Debts!D16/12,0) | AL11: 0 | AM11: =MAX(0,AJ11+AK11-AL11) | AN11: =AQ10 | AO11: =IF(AN11>0.005,AN11*Debts!D17/12,0) | AP11: 0 | AQ11: =MAX(0,AN11+AO11-AP11) | AR11: =AU10 | AS11: =IF(AR11>0.005,AR11*Debts!D18/12,0) | AT11: 0 | AU11: =MAX(0,AR11+AS11-AT11) | AV11: =AY10 | AW11: =IF(AV11>0.005,AV11*Debts!D19/12,0) | AX11: 0 | AY11: =MAX(0,AV11+AW11-AX11) | AZ11: =BC10 | BA11: =IF(AZ11>0.005,AZ11*Debts!D20/12,0) | BB11: 0 | BC11: =MAX(0,AZ11+BA11-BB11) | BD11: =BG10 | BE11: =IF(BD11>0.005,BD11*Debts!D21/12,0) | BF11: 0 | BG11: =MAX(0,BD11+BE11-BF11) | BH11: =BK10 | BI11: =IF(BH11>0.005,BH11*Debts!D22/12,0) | BJ11: 0 | BK11: =MAX(0,BH11+BI11-BJ11) | BL11: =BO10 | BM11: =IF(BL11>0.005,BL11*Debts!D23/12,0) | BN11: 0 | BO11: =MAX(0,BL11+BM11-BN11) | BP11: =BS10 | BQ11: =IF(BP11>0.005,BP11*Debts!D24/12,0) | BR11: 0 | BS11: =MAX(0,BP11+BQ11-BR11) | BT11: =BW10 | BU11: =IF(BT11>0.005,BT11*Debts!D25/12,0) | BV11: 0 | BW11: =MAX(0,BT11+BU11-BV11) | BX11: =CA10 | BY11: =IF(BX11>0.005,BX11*Debts!D26/12,0) | BZ11: 0 | CA11: =MAX(0,BX11+BY11-BZ11) | CB11: =CE10 | CC11: =IF(CB11>0.005,CB11*Debts!D27/12,0) | CD11: 0 | CE11: =MAX(0,CB11+CC11-CD11) | CF11: =G11+K11+O11+S11+W11+AA11+AE11+AI11+AM11+AQ11+AU11+AY11+BC11+BG11+BK11+BO11+BS11+BW11+CA11+CE11 | CG11: =E11+I11+M11+Q11+U11+Y11+AC11+AG11+AK11+AO11+AS11+AW11+BA11+BE11+BI11+BM11+BQ11+BU11+BY11+CC11 | CH11: =CH10+CG11
B12: 8 | C12: =F12+J12+N12+R12+V12+Z12+AD12+AH12+AL12+AP12+AT12+AX12+BB12+BF12+BJ12+BN12+BR12+BV12+BZ12+CD12 | D12: =G11 | E12: =IF(D12>0.005,D12*Debts!D8/12,0) | F12: 0 | G12: =MAX(0,D12+E12-F12) | H12: =K11 | I12: =IF(H12>0.005,H12*Debts!D9/12,0) | J12: 0 | K12: =MAX(0,H12+I12-J12) | L12: =O11 | M12: =IF(L12>0.005,L12*Debts!D10/12,0) | N12: 0 | O12: =MAX(0,L12+M12-N12) | P12: =S11 | Q12: =IF(P12>0.005,P12*Debts!D11/12,0) | R12: 0 | S12: =MAX(0,P12+Q12-R12) | T12: =W11 | U12: =IF(T12>0.005,T12*Debts!D12/12,0) | V12: 0 | W12: =MAX(0,T12+U12-V12) | X12: =AA11 | Y12: =IF(X12>0.005,X12*Debts!D13/12,0) | Z12: 0 | AA12: =MAX(0,X12+Y12-Z12) | AB12: =AE11 | AC12: =IF(AB12>0.005,AB12*Debts!D14/12,0) | AD12: 0 | AE12: =MAX(0,AB12+AC12-AD12) | AF12: =AI11 | AG12: =IF(AF12>0.005,AF12*Debts!D15/12,0) | AH12: 0 | AI12: =MAX(0,AF12+AG12-AH12) | AJ12: =AM11 | AK12: =IF(AJ12>0.005,AJ12*Debts!D16/12,0) | AL12: 0 | AM12: =MAX(0,AJ12+AK12-AL12) | AN12: =AQ11 | AO12: =IF(AN12>0.005,AN12*Debts!D17/12,0) | AP12: 0 | AQ12: =MAX(0,AN12+AO12-AP12) | AR12: =AU11 | AS12: =IF(AR12>0.005,AR12*Debts!D18/12,0) | AT12: 0 | AU12: =MAX(0,AR12+AS12-AT12) | AV12: =AY11 | AW12: =IF(AV12>0.005,AV12*Debts!D19/12,0) | AX12: 0 | AY12: =MAX(0,AV12+AW12-AX12) | AZ12: =BC11 | BA12: =IF(AZ12>0.005,AZ12*Debts!D20/12,0) | BB12: 0 | BC12: =MAX(0,AZ12+BA12-BB12) | BD12: =BG11 | BE12: =IF(BD12>0.005,BD12*Debts!D21/12,0) | BF12: 0 | BG12: =MAX(0,BD12+BE12-BF12) | BH12: =BK11 | BI12: =IF(BH12>0.005,BH12*Debts!D22/12,0) | BJ12: 0 | BK12: =MAX(0,BH12+BI12-BJ12) | BL12: =BO11 | BM12: =IF(BL12>0.005,BL12*Debts!D23/12,0) | BN12: 0 | BO12: =MAX(0,BL12+BM12-BN12) | BP12: =BS11 | BQ12: =IF(BP12>0.005,BP12*Debts!D24/12,0) | BR12: 0 | BS12: =MAX(0,BP12+BQ12-BR12) | BT12: =BW11 | BU12: =IF(BT12>0.005,BT12*Debts!D25/12,0) | BV12: 0 | BW12: =MAX(0,BT12+BU12-BV12) | BX12: =CA11 | BY12: =IF(BX12>0.005,BX12*Debts!D26/12,0) | BZ12: 0 | CA12: =MAX(0,BX12+BY12-BZ12) | CB12: =CE11 | CC12: =IF(CB12>0.005,CB12*Debts!D27/12,0) | CD12: 0 | CE12: =MAX(0,CB12+CC12-CD12) | CF12: =G12+K12+O12+S12+W12+AA12+AE12+AI12+AM12+AQ12+AU12+AY12+BC12+BG12+BK12+BO12+BS12+BW12+CA12+CE12 | CG12: =E12+I12+M12+Q12+U12+Y12+AC12+AG12+AK12+AO12+AS12+AW12+BA12+BE12+BI12+BM12+BQ12+BU12+BY12+CC12 | CH12: =CH11+CG12
B13: 9 | C13: =F13+J13+N13+R13+V13+Z13+AD13+AH13+AL13+AP13+AT13+AX13+BB13+BF13+BJ13+BN13+BR13+BV13+BZ13+CD13 | D13: =G12 | E13: =IF(D13>0.005,D13*Debts!D8/12,0) | F13: 0 | G13: =MAX(0,D13+E13-F13) | H13: =K12 | I13: =IF(H13>0.005,H13*Debts!D9/12,0) | J13: 0 | K13: =MAX(0,H13+I13-J13) | L13: =O12 | M13: =IF(L13>0.005,L13*Debts!D10/12,0) | N13: 0 | O13: =MAX(0,L13+M13-N13) | P13: =S12 | Q13: =IF(P13>0.005,P13*Debts!D11/12,0) | R13: 0 | S13: =MAX(0,P13+Q13-R13) | T13: =W12 | U13: =IF(T13>0.005,T13*Debts!D12/12,0) | V13: 0 | W13: =MAX(0,T13+U13-V13) | X13: =AA12 | Y13: =IF(X13>0.005,X13*Debts!D13/12,0) | Z13: 0 | AA13: =MAX(0,X13+Y13-Z13) | AB13: =AE12 | AC13: =IF(AB13>0.005,AB13*Debts!D14/12,0) | AD13: 0 | AE13: =MAX(0,AB13+AC13-AD13) | AF13: =AI12 | AG13: =IF(AF13>0.005,AF13*Debts!D15/12,0) | AH13: 0 | AI13: =MAX(0,AF13+AG13-AH13) | AJ13: =AM12 | AK13: =IF(AJ13>0.005,AJ13*Debts!D16/12,0) | AL13: 0 | AM13: =MAX(0,AJ13+AK13-AL13) | AN13: =AQ12 | AO13: =IF(AN13>0.005,AN13*Debts!D17/12,0) | AP13: 0 | AQ13: =MAX(0,AN13+AO13-AP13) | AR13: =AU12 | AS13: =IF(AR13>0.005,AR13*Debts!D18/12,0) | AT13: 0 | AU13: =MAX(0,AR13+AS13-AT13) | AV13: =AY12 | AW13: =IF(AV13>0.005,AV13*Debts!D19/12,0) | AX13: 0 | AY13: =MAX(0,AV13+AW13-AX13) | AZ13: =BC12 | BA13: =IF(AZ13>0.005,AZ13*Debts!D20/12,0) | BB13: 0 | BC13: =MAX(0,AZ13+BA13-BB13) | BD13: =BG12 | BE13: =IF(BD13>0.005,BD13*Debts!D21/12,0) | BF13: 0 | BG13: =MAX(0,BD13+BE13-BF13) | BH13: =BK12 | BI13: =IF(BH13>0.005,BH13*Debts!D22/12,0) | BJ13: 0 | BK13: =MAX(0,BH13+BI13-BJ13) | BL13: =BO12 | BM13: =IF(BL13>0.005,BL13*Debts!D23/12,0) | BN13: 0 | BO13: =MAX(0,BL13+BM13-BN13) | BP13: =BS12 | BQ13: =IF(BP13>0.005,BP13*Debts!D24/12,0) | BR13: 0 | BS13: =MAX(0,BP13+BQ13-BR13) | BT13: =BW12 | BU13: =IF(BT13>0.005,BT13*Debts!D25/12,0) | BV13: 0 | BW13: =MAX(0,BT13+BU13-BV13) | BX13: =CA12 | BY13: =IF(BX13>0.005,BX13*Debts!D26/12,0) | BZ13: 0 | CA13: =MAX(0,BX13+BY13-BZ13) | CB13: =CE12 | CC13: =IF(CB13>0.005,CB13*Debts!D27/12,0) | CD13: 0 | CE13: =MAX(0,CB13+CC13-CD13) | CF13: =G13+K13+O13+S13+W13+AA13+AE13+AI13+AM13+AQ13+AU13+AY13+BC13+BG13+BK13+BO13+BS13+BW13+CA13+CE13 | CG13: =E13+I13+M13+Q13+U13+Y13+AC13+AG13+AK13+AO13+AS13+AW13+BA13+BE13+BI13+BM13+BQ13+BU13+BY13+CC13 | CH13: =CH12+CG13
B14: 10 | C14: =F14+J14+N14+R14+V14+Z14+AD14+AH14+AL14+AP14+AT14+AX14+BB14+BF14+BJ14+BN14+BR14+BV14+BZ14+CD14 | D14: =G13 | E14: =IF(D14>0.005,D14*Debts!D8/12,0) | F14: 0 | G14: =MAX(0,D14+E14-F14) | H14: =K13 | I14: =IF(H14>0.005,H14*Debts!D9/12,0) | J14: 0 | K14: =MAX(0,H14+I14-J14) | L14: =O13 | M14: =IF(L14>0.005,L14*Debts!D10/12,0) | N14: 0 | O14: =MAX(0,L14+M14-N14) | P14: =S13 | Q14: =IF(P14>0.005,P14*Debts!D11/12,0) | R14: 0 | S14: =MAX(0,P14+Q14-R14) | T14: =W13 | U14: =IF(T14>0.005,T14*Debts!D12/12,0) | V14: 0 | W14: =MAX(0,T14+U14-V14) | X14: =AA13 | Y14: =IF(X14>0.005,X14*Debts!D13/12,0) | Z14: 0 | AA14: =MAX(0,X14+Y14-Z14) | AB14: =AE13 | AC14: =IF(AB14>0.005,AB14*Debts!D14/12,0) | AD14: 0 | AE14: =MAX(0,AB14+AC14-AD14) | AF14: =AI13 | AG14: =IF(AF14>0.005,AF14*Debts!D15/12,0) | AH14: 0 | AI14: =MAX(0,AF14+AG14-AH14) | AJ14: =AM13 | AK14: =IF(AJ14>0.005,AJ14*Debts!D16/12,0) | AL14: 0 | AM14: =MAX(0,AJ14+AK14-AL14) | AN14: =AQ13 | AO14: =IF(AN14>0.005,AN14*Debts!D17/12,0) | AP14: 0 | AQ14: =MAX(0,AN14+AO14-AP14) | AR14: =AU13 | AS14: =IF(AR14>0.005,AR14*Debts!D18/12,0) | AT14: 0 | AU14: =MAX(0,AR14+AS14-AT14) | AV14: =AY13 | AW14: =IF(AV14>0.005,AV14*Debts!D19/12,0) | AX14: 0 | AY14: =MAX(0,AV14+AW14-AX14) | AZ14: =BC13 | BA14: =IF(AZ14>0.005,AZ14*Debts!D20/12,0) | BB14: 0 | BC14: =MAX(0,AZ14+BA14-BB14) | BD14: =BG13 | BE14: =IF(BD14>0.005,BD14*Debts!D21/12,0) | BF14: 0 | BG14: =MAX(0,BD14+BE14-BF14) | BH14: =BK13 | BI14: =IF(BH14>0.005,BH14*Debts!D22/12,0) | BJ14: 0 | BK14: =MAX(0,BH14+BI14-BJ14) | BL14: =BO13 | BM14: =IF(BL14>0.005,BL14*Debts!D23/12,0) | BN14: 0 | BO14: =MAX(0,BL14+BM14-BN14) | BP14: =BS13 | BQ14: =IF(BP14>0.005,BP14*Debts!D24/12,0) | BR14: 0 | BS14: =MAX(0,BP14+BQ14-BR14) | BT14: =BW13 | BU14: =IF(BT14>0.005,BT14*Debts!D25/12,0) | BV14: 0 | BW14: =MAX(0,BT14+BU14-BV14) | BX14: =CA13 | BY14: =IF(BX14>0.005,BX14*Debts!D26/12,0) | BZ14: 0 | CA14: =MAX(0,BX14+BY14-BZ14) | CB14: =CE13 | CC14: =IF(CB14>0.005,CB14*Debts!D27/12,0) | CD14: 0 | CE14: =MAX(0,CB14+CC14-CD14) | CF14: =G14+K14+O14+S14+W14+AA14+AE14+AI14+AM14+AQ14+AU14+AY14+BC14+BG14+BK14+BO14+BS14+BW14+CA14+CE14 | CG14: =E14+I14+M14+Q14+U14+Y14+AC14+AG14+AK14+AO14+AS14+AW14+BA14+BE14+BI14+BM14+BQ14+BU14+BY14+CC14 | CH14: =CH13+CG14
B15: 11 | C15: =F15+J15+N15+R15+V15+Z15+AD15+AH15+AL15+AP15+AT15+AX15+BB15+BF15+BJ15+BN15+BR15+BV15+BZ15+CD15 | D15: =G14 | E15: =IF(D15>0.005,D15*Debts!D8/12,0) | F15: 0 | G15: =MAX(0,D15+E15-F15) | H15: =K14 | I15: =IF(H15>0.005,H15*Debts!D9/12,0) | J15: 0 | K15: =MAX(0,H15+I15-J15) | L15: =O14 | M15: =IF(L15>0.005,L15*Debts!D10/12,0) | N15: 0 | O15: =MAX(0,L15+M15-N15) | P15: =S14 | Q15: =IF(P15>0.005,P15*Debts!D11/12,0) | R15: 0 | S15: =MAX(0,P15+Q15-R15) | T15: =W14 | U15: =IF(T15>0.005,T15*Debts!D12/12,0) | V15: 0 | W15: =MAX(0,T15+U15-V15) | X15: =AA14 | Y15: =IF(X15>0.005,X15*Debts!D13/12,0) | Z15: 0 | AA15: =MAX(0,X15+Y15-Z15) | AB15: =AE14 | AC15: =IF(AB15>0.005,AB15*Debts!D14/12,0) | AD15: 0 | AE15: =MAX(0,AB15+AC15-AD15) | AF15: =AI14 | AG15: =IF(AF15>0.005,AF15*Debts!D15/12,0) | AH15: 0 | AI15: =MAX(0,AF15+AG15-AH15) | AJ15: =AM14 | AK15: =IF(AJ15>0.005,AJ15*Debts!D16/12,0) | AL15: 0 | AM15: =MAX(0,AJ15+AK15-AL15) | AN15: =AQ14 | AO15: =IF(AN15>0.005,AN15*Debts!D17/12,0) | AP15: 0 | AQ15: =MAX(0,AN15+AO15-AP15) | AR15: =AU14 | AS15: =IF(AR15>0.005,AR15*Debts!D18/12,0) | AT15: 0 | AU15: =MAX(0,AR15+AS15-AT15) | AV15: =AY14 | AW15: =IF(AV15>0.005,AV15*Debts!D19/12,0) | AX15: 0 | AY15: =MAX(0,AV15+AW15-AX15) | AZ15: =BC14 | BA15: =IF(AZ15>0.005,AZ15*Debts!D20/12,0) | BB15: 0 | BC15: =MAX(0,AZ15+BA15-BB15) | BD15: =BG14 | BE15: =IF(BD15>0.005,BD15*Debts!D21/12,0) | BF15: 0 | BG15: =MAX(0,BD15+BE15-BF15) | BH15: =BK14 | BI15: =IF(BH15>0.005,BH15*Debts!D22/12,0) | BJ15: 0 | BK15: =MAX(0,BH15+BI15-BJ15) | BL15: =BO14 | BM15: =IF(BL15>0.005,BL15*Debts!D23/12,0) | BN15: 0 | BO15: =MAX(0,BL15+BM15-BN15) | BP15: =BS14 | BQ15: =IF(BP15>0.005,BP15*Debts!D24/12,0) | BR15: 0 | BS15: =MAX(0,BP15+BQ15-BR15) | BT15: =BW14 | BU15: =IF(BT15>0.005,BT15*Debts!D25/12,0) | BV15: 0 | BW15: =MAX(0,BT15+BU15-BV15) | BX15: =CA14 | BY15: =IF(BX15>0.005,BX15*Debts!D26/12,0) | BZ15: 0 | CA15: =MAX(0,BX15+BY15-BZ15) | CB15: =CE14 | CC15: =IF(CB15>0.005,CB15*Debts!D27/12,0) | CD15: 0 | CE15: =MAX(0,CB15+CC15-CD15) | CF15: =G15+K15+O15+S15+W15+AA15+AE15+AI15+AM15+AQ15+AU15+AY15+BC15+BG15+BK15+BO15+BS15+BW15+CA15+CE15 | CG15: =E15+I15+M15+Q15+U15+Y15+AC15+AG15+AK15+AO15+AS15+AW15+BA15+BE15+BI15+BM15+BQ15+BU15+BY15+CC15 | CH15: =CH14+CG15
B16: 12 | C16: =F16+J16+N16+R16+V16+Z16+AD16+AH16+AL16+AP16+AT16+AX16+BB16+BF16+BJ16+BN16+BR16+BV16+BZ16+CD16 | D16: =G15 | E16: =IF(D16>0.005,D16*Debts!D8/12,0) | F16: 0 | G16: =MAX(0,D16+E16-F16) | H16: =K15 | I16: =IF(H16>0.005,H16*Debts!D9/12,0) | J16: 0 | K16: =MAX(0,H16+I16-J16) | L16: =O15 | M16: =IF(L16>0.005,L16*Debts!D10/12,0) | N16: 0 | O16: =MAX(0,L16+M16-N16) | P16: =S15 | Q16: =IF(P16>0.005,P16*Debts!D11/12,0) | R16: 0 | S16: =MAX(0,P16+Q16-R16) | T16: =W15 | U16: =IF(T16>0.005,T16*Debts!D12/12,0) | V16: 0 | W16: =MAX(0,T16+U16-V16) | X16: =AA15 | Y16: =IF(X16>0.005,X16*Debts!D13/12,0) | Z16: 0 | AA16: =MAX(0,X16+Y16-Z16) | AB16: =AE15 | AC16: =IF(AB16>0.005,AB16*Debts!D14/12,0) | AD16: 0 | AE16: =MAX(0,AB16+AC16-AD16) | AF16: =AI15 | AG16: =IF(AF16>0.005,AF16*Debts!D15/12,0) | AH16: 0 | AI16: =MAX(0,AF16+AG16-AH16) | AJ16: =AM15 | AK16: =IF(AJ16>0.005,AJ16*Debts!D16/12,0) | AL16: 0 | AM16: =MAX(0,AJ16+AK16-AL16) | AN16: =AQ15 | AO16: =IF(AN16>0.005,AN16*Debts!D17/12,0) | AP16: 0 | AQ16: =MAX(0,AN16+AO16-AP16) | AR16: =AU15 | AS16: =IF(AR16>0.005,AR16*Debts!D18/12,0) | AT16: 0 | AU16: =MAX(0,AR16+AS16-AT16) | AV16: =AY15 | AW16: =IF(AV16>0.005,AV16*Debts!D19/12,0) | AX16: 0 | AY16: =MAX(0,AV16+AW16-AX16) | AZ16: =BC15 | BA16: =IF(AZ16>0.005,AZ16*Debts!D20/12,0) | BB16: 0 | BC16: =MAX(0,AZ16+BA16-BB16) | BD16: =BG15 | BE16: =IF(BD16>0.005,BD16*Debts!D21/12,0) | BF16: 0 | BG16: =MAX(0,BD16+BE16-BF16) | BH16: =BK15 | BI16: =IF(BH16>0.005,BH16*Debts!D22/12,0) | BJ16: 0 | BK16: =MAX(0,BH16+BI16-BJ16) | BL16: =BO15 | BM16: =IF(BL16>0.005,BL16*Debts!D23/12,0) | BN16: 0 | BO16: =MAX(0,BL16+BM16-BN16) | BP16: =BS15 | BQ16: =IF(BP16>0.005,BP16*Debts!D24/12,0) | BR16: 0 | BS16: =MAX(0,BP16+BQ16-BR16) | BT16: =BW15 | BU16: =IF(BT16>0.005,BT16*Debts!D25/12,0) | BV16: 0 | BW16: =MAX(0,BT16+BU16-BV16) | BX16: =CA15 | BY16: =IF(BX16>0.005,BX16*Debts!D26/12,0) | BZ16: 0 | CA16: =MAX(0,BX16+BY16-BZ16) | CB16: =CE15 | CC16: =IF(CB16>0.005,CB16*Debts!D27/12,0) | CD16: 0 | CE16: =MAX(0,CB16+CC16-CD16) | CF16: =G16+K16+O16+S16+W16+AA16+AE16+AI16+AM16+AQ16+AU16+AY16+BC16+BG16+BK16+BO16+BS16+BW16+CA16+CE16 | CG16: =E16+I16+M16+Q16+U16+Y16+AC16+AG16+AK16+AO16+AS16+AW16+BA16+BE16+BI16+BM16+BQ16+BU16+BY16+CC16 | CH16: =CH15+CG16
B17: 13 | C17: =F17+J17+N17+R17+V17+Z17+AD17+AH17+AL17+AP17+AT17+AX17+BB17+BF17+BJ17+BN17+BR17+BV17+BZ17+CD17 | D17: =G16 | E17: =IF(D17>0.005,D17*Debts!D8/12,0) | F17: 0 | G17: =MAX(0,D17+E17-F17) | H17: =K16 | I17: =IF(H17>0.005,H17*Debts!D9/12,0) | J17: 0 | K17: =MAX(0,H17+I17-J17) | L17: =O16 | M17: =IF(L17>0.005,L17*Debts!D10/12,0) | N17: 0 | O17: =MAX(0,L17+M17-N17) | P17: =S16 | Q17: =IF(P17>0.005,P17*Debts!D11/12,0) | R17: 0 | S17: =MAX(0,P17+Q17-R17) | T17: =W16 | U17: =IF(T17>0.005,T17*Debts!D12/12,0) | V17: 0 | W17: =MAX(0,T17+U17-V17) | X17: =AA16 | Y17: =IF(X17>0.005,X17*Debts!D13/12,0) | Z17: 0 | AA17: =MAX(0,X17+Y17-Z17) | AB17: =AE16 | AC17: =IF(AB17>0.005,AB17*Debts!D14/12,0) | AD17: 0 | AE17: =MAX(0,AB17+AC17-AD17) | AF17: =AI16 | AG17: =IF(AF17>0.005,AF17*Debts!D15/12,0) | AH17: 0 | AI17: =MAX(0,AF17+AG17-AH17) | AJ17: =AM16 | AK17: =IF(AJ17>0.005,AJ17*Debts!D16/12,0) | AL17: 0 | AM17: =MAX(0,AJ17+AK17-AL17) | AN17: =AQ16 | AO17: =IF(AN17>0.005,AN17*Debts!D17/12,0) | AP17: 0 | AQ17: =MAX(0,AN17+AO17-AP17) | AR17: =AU16 | AS17: =IF(AR17>0.005,AR17*Debts!D18/12,0) | AT17: 0 | AU17: =MAX(0,AR17+AS17-AT17) | AV17: =AY16 | AW17: =IF(AV17>0.005,AV17*Debts!D19/12,0) | AX17: 0 | AY17: =MAX(0,AV17+AW17-AX17) | AZ17: =BC16 | BA17: =IF(AZ17>0.005,AZ17*Debts!D20/12,0) | BB17: 0 | BC17: =MAX(0,AZ17+BA17-BB17) | BD17: =BG16 | BE17: =IF(BD17>0.005,BD17*Debts!D21/12,0) | BF17: 0 | BG17: =MAX(0,BD17+BE17-BF17) | BH17: =BK16 | BI17: =IF(BH17>0.005,BH17*Debts!D22/12,0) | BJ17: 0 | BK17: =MAX(0,BH17+BI17-BJ17) | BL17: =BO16 | BM17: =IF(BL17>0.005,BL17*Debts!D23/12,0) | BN17: 0 | BO17: =MAX(0,BL17+BM17-BN17) | BP17: =BS16 | BQ17: =IF(BP17>0.005,BP17*Debts!D24/12,0) | BR17: 0 | BS17: =MAX(0,BP17+BQ17-BR17) | BT17: =BW16 | BU17: =IF(BT17>0.005,BT17*Debts!D25/12,0) | BV17: 0 | BW17: =MAX(0,BT17+BU17-BV17) | BX17: =CA16 | BY17: =IF(BX17>0.005,BX17*Debts!D26/12,0) | BZ17: 0 | CA17: =MAX(0,BX17+BY17-BZ17) | CB17: =CE16 | CC17: =IF(CB17>0.005,CB17*Debts!D27/12,0) | CD17: 0 | CE17: =MAX(0,CB17+CC17-CD17) | CF17: =G17+K17+O17+S17+W17+AA17+AE17+AI17+AM17+AQ17+AU17+AY17+BC17+BG17+BK17+BO17+BS17+BW17+CA17+CE17 | CG17: =E17+I17+M17+Q17+U17+Y17+AC17+AG17+AK17+AO17+AS17+AW17+BA17+BE17+BI17+BM17+BQ17+BU17+BY17+CC17 | CH17: =CH16+CG17
B18: 14 | C18: =F18+J18+N18+R18+V18+Z18+AD18+AH18+AL18+AP18+AT18+AX18+BB18+BF18+BJ18+BN18+BR18+BV18+BZ18+CD18 | D18: =G17 | E18: =IF(D18>0.005,D18*Debts!D8/12,0) | F18: 0 | G18: =MAX(0,D18+E18-F18) | H18: =K17 | I18: =IF(H18>0.005,H18*Debts!D9/12,0) | J18: 0 | K18: =MAX(0,H18+I18-J18) | L18: =O17 | M18: =IF(L18>0.005,L18*Debts!D10/12,0) | N18: 0 | O18: =MAX(0,L18+M18-N18) | P18: =S17 | Q18: =IF(P18>0.005,P18*Debts!D11/12,0) | R18: 0 | S18: =MAX(0,P18+Q18-R18) | T18: =W17 | U18: =IF(T18>0.005,T18*Debts!D12/12,0) | V18: 0 | W18: =MAX(0,T18+U18-V18) | X18: =AA17 | Y18: =IF(X18>0.005,X18*Debts!D13/12,0) | Z18: 0 | AA18: =MAX(0,X18+Y18-Z18) | AB18: =AE17 | AC18: =IF(AB18>0.005,AB18*Debts!D14/12,0) | AD18: 0 | AE18: =MAX(0,AB18+AC18-AD18) | AF18: =AI17 | AG18: =IF(AF18>0.005,AF18*Debts!D15/12,0) | AH18: 0 | AI18: =MAX(0,AF18+AG18-AH18) | AJ18: =AM17 | AK18: =IF(AJ18>0.005,AJ18*Debts!D16/12,0) | AL18: 0 | AM18: =MAX(0,AJ18+AK18-AL18) | AN18: =AQ17 | AO18: =IF(AN18>0.005,AN18*Debts!D17/12,0) | AP18: 0 | AQ18: =MAX(0,AN18+AO18-AP18) | AR18: =AU17 | AS18: =IF(AR18>0.005,AR18*Debts!D18/12,0) | AT18: 0 | AU18: =MAX(0,AR18+AS18-AT18) | AV18: =AY17 | AW18: =IF(AV18>0.005,AV18*Debts!D19/12,0) | AX18: 0 | AY18: =MAX(0,AV18+AW18-AX18) | AZ18: =BC17 | BA18: =IF(AZ18>0.005,AZ18*Debts!D20/12,0) | BB18: 0 | BC18: =MAX(0,AZ18+BA18-BB18) | BD18: =BG17 | BE18: =IF(BD18>0.005,BD18*Debts!D21/12,0) | BF18: 0 | BG18: =MAX(0,BD18+BE18-BF18) | BH18: =BK17 | BI18: =IF(BH18>0.005,BH18*Debts!D22/12,0) | BJ18: 0 | BK18: =MAX(0,BH18+BI18-BJ18) | BL18: =BO17 | BM18: =IF(BL18>0.005,BL18*Debts!D23/12,0) | BN18: 0 | BO18: =MAX(0,BL18+BM18-BN18) | BP18: =BS17 | BQ18: =IF(BP18>0.005,BP18*Debts!D24/12,0) | BR18: 0 | BS18: =MAX(0,BP18+BQ18-BR18) | BT18: =BW17 | BU18: =IF(BT18>0.005,BT18*Debts!D25/12,0) | BV18: 0 | BW18: =MAX(0,BT18+BU18-BV18) | BX18: =CA17 | BY18: =IF(BX18>0.005,BX18*Debts!D26/12,0) | BZ18: 0 | CA18: =MAX(0,BX18+BY18-BZ18) | CB18: =CE17 | CC18: =IF(CB18>0.005,CB18*Debts!D27/12,0) | CD18: 0 | CE18: =MAX(0,CB18+CC18-CD18) | CF18: =G18+K18+O18+S18+W18+AA18+AE18+AI18+AM18+AQ18+AU18+AY18+BC18+BG18+BK18+BO18+BS18+BW18+CA18+CE18 | CG18: =E18+I18+M18+Q18+U18+Y18+AC18+AG18+AK18+AO18+AS18+AW18+BA18+BE18+BI18+BM18+BQ18+BU18+BY18+CC18 | CH18: =CH17+CG18
B19: 15 | C19: =F19+J19+N19+R19+V19+Z19+AD19+AH19+AL19+AP19+AT19+AX19+BB19+BF19+BJ19+BN19+BR19+BV19+BZ19+CD19 | D19: =G18 | E19: =IF(D19>0.005,D19*Debts!D8/12,0) | F19: 0 | G19: =MAX(0,D19+E19-F19) | H19: =K18 | I19: =IF(H19>0.005,H19*Debts!D9/12,0) | J19: 0 | K19: =MAX(0,H19+I19-J19) | L19: =O18 | M19: =IF(L19>0.005,L19*Debts!D10/12,0) | N19: 0 | O19: =MAX(0,L19+M19-N19) | P19: =S18 | Q19: =IF(P19>0.005,P19*Debts!D11/12,0) | R19: 0 | S19: =MAX(0,P19+Q19-R19) | T19: =W18 | U19: =IF(T19>0.005,T19*Debts!D12/12,0) | V19: 0 | W19: =MAX(0,T19+U19-V19) | X19: =AA18 | Y19: =IF(X19>0.005,X19*Debts!D13/12,0) | Z19: 0 | AA19: =MAX(0,X19+Y19-Z19) | AB19: =AE18 | AC19: =IF(AB19>0.005,AB19*Debts!D14/12,0) | AD19: 0 | AE19: =MAX(0,AB19+AC19-AD19) | AF19: =AI18 | AG19: =IF(AF19>0.005,AF19*Debts!D15/12,0) | AH19: 0 | AI19: =MAX(0,AF19+AG19-AH19) | AJ19: =AM18 | AK19: =IF(AJ19>0.005,AJ19*Debts!D16/12,0) | AL19: 0 | AM19: =MAX(0,AJ19+AK19-AL19) | AN19: =AQ18 | AO19: =IF(AN19>0.005,AN19*Debts!D17/12,0) | AP19: 0 | AQ19: =MAX(0,AN19+AO19-AP19) | AR19: =AU18 | AS19: =IF(AR19>0.005,AR19*Debts!D18/12,0) | AT19: 0 | AU19: =MAX(0,AR19+AS19-AT19) | AV19: =AY18 | AW19: =IF(AV19>0.005,AV19*Debts!D19/12,0) | AX19: 0 | AY19: =MAX(0,AV19+AW19-AX19) | AZ19: =BC18 | BA19: =IF(AZ19>0.005,AZ19*Debts!D20/12,0) | BB19: 0 | BC19: =MAX(0,AZ19+BA19-BB19) | BD19: =BG18 | BE19: =IF(BD19>0.005,BD19*Debts!D21/12,0) | BF19: 0 | BG19: =MAX(0,BD19+BE19-BF19) | BH19: =BK18 | BI19: =IF(BH19>0.005,BH19*Debts!D22/12,0) | BJ19: 0 | BK19: =MAX(0,BH19+BI19-BJ19) | BL19: =BO18 | BM19: =IF(BL19>0.005,BL19*Debts!D23/12,0) | BN19: 0 | BO19: =MAX(0,BL19+BM19-BN19) | BP19: =BS18 | BQ19: =IF(BP19>0.005,BP19*Debts!D24/12,0) | BR19: 0 | BS19: =MAX(0,BP19+BQ19-BR19) | BT19: =BW18 | BU19: =IF(BT19>0.005,BT19*Debts!D25/12,0) | BV19: 0 | BW19: =MAX(0,BT19+BU19-BV19) | BX19: =CA18 | BY19: =IF(BX19>0.005,BX19*Debts!D26/12,0) | BZ19: 0 | CA19: =MAX(0,BX19+BY19-BZ19) | CB19: =CE18 | CC19: =IF(CB19>0.005,CB19*Debts!D27/12,0) | CD19: 0 | CE19: =MAX(0,CB19+CC19-CD19) | CF19: =G19+K19+O19+S19+W19+AA19+AE19+AI19+AM19+AQ19+AU19+AY19+BC19+BG19+BK19+BO19+BS19+BW19+CA19+CE19 | CG19: =E19+I19+M19+Q19+U19+Y19+AC19+AG19+AK19+AO19+AS19+AW19+BA19+BE19+BI19+BM19+BQ19+BU19+BY19+CC19 | CH19: =CH18+CG19
B20: 16 | C20: =F20+J20+N20+R20+V20+Z20+AD20+AH20+AL20+AP20+AT20+AX20+BB20+BF20+BJ20+BN20+BR20+BV20+BZ20+CD20 | D20: =G19 | E20: =IF(D20>0.005,D20*Debts!D8/12,0) | F20: 0 | G20: =MAX(0,D20+E20-F20) | H20: =K19 | I20: =IF(H20>0.005,H20*Debts!D9/12,0) | J20: 0 | K20: =MAX(0,H20+I20-J20) | L20: =O19 | M20: =IF(L20>0.005,L20*Debts!D10/12,0) | N20: 0 | O20: =MAX(0,L20+M20-N20) | P20: =S19 | Q20: =IF(P20>0.005,P20*Debts!D11/12,0) | R20: 0 | S20: =MAX(0,P20+Q20-R20) | T20: =W19 | U20: =IF(T20>0.005,T20*Debts!D12/12,0) | V20: 0 | W20: =MAX(0,T20+U20-V20) | X20: =AA19 | Y20: =IF(X20>0.005,X20*Debts!D13/12,0) | Z20: 0 | AA20: =MAX(0,X20+Y20-Z20) | AB20: =AE19 | AC20: =IF(AB20>0.005,AB20*Debts!D14/12,0) | AD20: 0 | AE20: =MAX(0,AB20+AC20-AD20) | AF20: =AI19 | AG20: =IF(AF20>0.005,AF20*Debts!D15/12,0) | AH20: 0 | AI20: =MAX(0,AF20+AG20-AH20) | AJ20: =AM19 | AK20: =IF(AJ20>0.005,AJ20*Debts!D16/12,0) | AL20: 0 | AM20: =MAX(0,AJ20+AK20-AL20) | AN20: =AQ19 | AO20: =IF(AN20>0.005,AN20*Debts!D17/12,0) | AP20: 0 | AQ20: =MAX(0,AN20+AO20-AP20) | AR20: =AU19 | AS20: =IF(AR20>0.005,AR20*Debts!D18/12,0) | AT20: 0 | AU20: =MAX(0,AR20+AS20-AT20) | AV20: =AY19 | AW20: =IF(AV20>0.005,AV20*Debts!D19/12,0) | AX20: 0 | AY20: =MAX(0,AV20+AW20-AX20) | AZ20: =BC19 | BA20: =IF(AZ20>0.005,AZ20*Debts!D20/12,0) | BB20: 0 | BC20: =MAX(0,AZ20+BA20-BB20) | BD20: =BG19 | BE20: =IF(BD20>0.005,BD20*Debts!D21/12,0) | BF20: 0 | BG20: =MAX(0,BD20+BE20-BF20) | BH20: =BK19 | BI20: =IF(BH20>0.005,BH20*Debts!D22/12,0) | BJ20: 0 | BK20: =MAX(0,BH20+BI20-BJ20) | BL20: =BO19 | BM20: =IF(BL20>0.005,BL20*Debts!D23/12,0) | BN20: 0 | BO20: =MAX(0,BL20+BM20-BN20) | BP20: =BS19 | BQ20: =IF(BP20>0.005,BP20*Debts!D24/12,0) | BR20: 0 | BS20: =MAX(0,BP20+BQ20-BR20) | BT20: =BW19 | BU20: =IF(BT20>0.005,BT20*Debts!D25/12,0) | BV20: 0 | BW20: =MAX(0,BT20+BU20-BV20) | BX20: =CA19 | BY20: =IF(BX20>0.005,BX20*Debts!D26/12,0) | BZ20: 0 | CA20: =MAX(0,BX20+BY20-BZ20) | CB20: =CE19 | CC20: =IF(CB20>0.005,CB20*Debts!D27/12,0) | CD20: 0 | CE20: =MAX(0,CB20+CC20-CD20) | CF20: =G20+K20+O20+S20+W20+AA20+AE20+AI20+AM20+AQ20+AU20+AY20+BC20+BG20+BK20+BO20+BS20+BW20+CA20+CE20 | CG20: =E20+I20+M20+Q20+U20+Y20+AC20+AG20+AK20+AO20+AS20+AW20+BA20+BE20+BI20+BM20+BQ20+BU20+BY20+CC20 | CH20: =CH19+CG20
B21: 17 | C21: =F21+J21+N21+R21+V21+Z21+AD21+AH21+AL21+AP21+AT21+AX21+BB21+BF21+BJ21+BN21+BR21+BV21+BZ21+CD21 | D21: =G20 | E21: =IF(D21>0.005,D21*Debts!D8/12,0) | F21: 0 | G21: =MAX(0,D21+E21-F21) | H21: =K20 | I21: =IF(H21>0.005,H21*Debts!D9/12,0) | J21: 0 | K21: =MAX(0,H21+I21-J21) | L21: =O20 | M21: =IF(L21>0.005,L21*Debts!D10/12,0) | N21: 0 | O21: =MAX(0,L21+M21-N21) | P21: =S20 | Q21: =IF(P21>0.005,P21*Debts!D11/12,0) | R21: 0 | S21: =MAX(0,P21+Q21-R21) | T21: =W20 | U21: =IF(T21>0.005,T21*Debts!D12/12,0) | V21: 0 | W21: =MAX(0,T21+U21-V21) | X21: =AA20 | Y21: =IF(X21>0.005,X21*Debts!D13/12,0) | Z21: 0 | AA21: =MAX(0,X21+Y21-Z21) | AB21: =AE20 | AC21: =IF(AB21>0.005,AB21*Debts!D14/12,0) | AD21: 0 | AE21: =MAX(0,AB21+AC21-AD21) | AF21: =AI20 | AG21: =IF(AF21>0.005,AF21*Debts!D15/12,0) | AH21: 0 | AI21: =MAX(0,AF21+AG21-AH21) | AJ21: =AM20 | AK21: =IF(AJ21>0.005,AJ21*Debts!D16/12,0) | AL21: 0 | AM21: =MAX(0,AJ21+AK21-AL21) | AN21: =AQ20 | AO21: =IF(AN21>0.005,AN21*Debts!D17/12,0) | AP21: 0 | AQ21: =MAX(0,AN21+AO21-AP21) | AR21: =AU20 | AS21: =IF(AR21>0.005,AR21*Debts!D18/12,0) | AT21: 0 | AU21: =MAX(0,AR21+AS21-AT21) | AV21: =AY20 | AW21: =IF(AV21>0.005,AV21*Debts!D19/12,0) | AX21: 0 | AY21: =MAX(0,AV21+AW21-AX21) | AZ21: =BC20 | BA21: =IF(AZ21>0.005,AZ21*Debts!D20/12,0) | BB21: 0 | BC21: =MAX(0,AZ21+BA21-BB21) | BD21: =BG20 | BE21: =IF(BD21>0.005,BD21*Debts!D21/12,0) | BF21: 0 | BG21: =MAX(0,BD21+BE21-BF21) | BH21: =BK20 | BI21: =IF(BH21>0.005,BH21*Debts!D22/12,0) | BJ21: 0 | BK21: =MAX(0,BH21+BI21-BJ21) | BL21: =BO20 | BM21: =IF(BL21>0.005,BL21*Debts!D23/12,0) | BN21: 0 | BO21: =MAX(0,BL21+BM21-BN21) | BP21: =BS20 | BQ21: =IF(BP21>0.005,BP21*Debts!D24/12,0) | BR21: 0 | BS21: =MAX(0,BP21+BQ21-BR21) | BT21: =BW20 | BU21: =IF(BT21>0.005,BT21*Debts!D25/12,0) | BV21: 0 | BW21: =MAX(0,BT21+BU21-BV21) | BX21: =CA20 | BY21: =IF(BX21>0.005,BX21*Debts!D26/12,0) | BZ21: 0 | CA21: =MAX(0,BX21+BY21-BZ21) | CB21: =CE20 | CC21: =IF(CB21>0.005,CB21*Debts!D27/12,0) | CD21: 0 | CE21: =MAX(0,CB21+CC21-CD21) | CF21: =G21+K21+O21+S21+W21+AA21+AE21+AI21+AM21+AQ21+AU21+AY21+BC21+BG21+BK21+BO21+BS21+BW21+CA21+CE21 | CG21: =E21+I21+M21+Q21+U21+Y21+AC21+AG21+AK21+AO21+AS21+AW21+BA21+BE21+BI21+BM21+BQ21+BU21+BY21+CC21 | CH21: =CH20+CG21
B22: 18 | C22: =F22+J22+N22+R22+V22+Z22+AD22+AH22+AL22+AP22+AT22+AX22+BB22+BF22+BJ22+BN22+BR22+BV22+BZ22+CD22 | D22: =G21 | E22: =IF(D22>0.005,D22*Debts!D8/12,0) | F22: 0 | G22: =MAX(0,D22+E22-F22) | H22: =K21 | I22: =IF(H22>0.005,H22*Debts!D9/12,0) | J22: 0 | K22: =MAX(0,H22+I22-J22) | L22: =O21 | M22: =IF(L22>0.005,L22*Debts!D10/12,0) | N22: 0 | O22: =MAX(0,L22+M22-N22) | P22: =S21 | Q22: =IF(P22>0.005,P22*Debts!D11/12,0) | R22: 0 | S22: =MAX(0,P22+Q22-R22) | T22: =W21 | U22: =IF(T22>0.005,T22*Debts!D12/12,0) | V22: 0 | W22: =MAX(0,T22+U22-V22) | X22: =AA21 | Y22: =IF(X22>0.005,X22*Debts!D13/12,0) | Z22: 0 | AA22: =MAX(0,X22+Y22-Z22) | AB22: =AE21 | AC22: =IF(AB22>0.005,AB22*Debts!D14/12,0) | AD22: 0 | AE22: =MAX(0,AB22+AC22-AD22) | AF22: =AI21 | AG22: =IF(AF22>0.005,AF22*Debts!D15/12,0) | AH22: 0 | AI22: =MAX(0,AF22+AG22-AH22) | AJ22: =AM21 | AK22: =IF(AJ22>0.005,AJ22*Debts!D16/12,0) | AL22: 0 | AM22: =MAX(0,AJ22+AK22-AL22) | AN22: =AQ21 | AO22: =IF(AN22>0.005,AN22*Debts!D17/12,0) | AP22: 0 | AQ22: =MAX(0,AN22+AO22-AP22) | AR22: =AU21 | AS22: =IF(AR22>0.005,AR22*Debts!D18/12,0) | AT22: 0 | AU22: =MAX(0,AR22+AS22-AT22) | AV22: =AY21 | AW22: =IF(AV22>0.005,AV22*Debts!D19/12,0) | AX22: 0 | AY22: =MAX(0,AV22+AW22-AX22) | AZ22: =BC21 | BA22: =IF(AZ22>0.005,AZ22*Debts!D20/12,0) | BB22: 0 | BC22: =MAX(0,AZ22+BA22-BB22) | BD22: =BG21 | BE22: =IF(BD22>0.005,BD22*Debts!D21/12,0) | BF22: 0 | BG22: =MAX(0,BD22+BE22-BF22) | BH22: =BK21 | BI22: =IF(BH22>0.005,BH22*Debts!D22/12,0) | BJ22: 0 | BK22: =MAX(0,BH22+BI22-BJ22) | BL22: =BO21 | BM22: =IF(BL22>0.005,BL22*Debts!D23/12,0) | BN22: 0 | BO22: =MAX(0,BL22+BM22-BN22) | BP22: =BS21 | BQ22: =IF(BP22>0.005,BP22*Debts!D24/12,0) | BR22: 0 | BS22: =MAX(0,BP22+BQ22-BR22) | BT22: =BW21 | BU22: =IF(BT22>0.005,BT22*Debts!D25/12,0) | BV22: 0 | BW22: =MAX(0,BT22+BU22-BV22) | BX22: =CA21 | BY22: =IF(BX22>0.005,BX22*Debts!D26/12,0) | BZ22: 0 | CA22: =MAX(0,BX22+BY22-BZ22) | CB22: =CE21 | CC22: =IF(CB22>0.005,CB22*Debts!D27/12,0) | CD22: 0 | CE22: =MAX(0,CB22+CC22-CD22) | CF22: =G22+K22+O22+S22+W22+AA22+AE22+AI22+AM22+AQ22+AU22+AY22+BC22+BG22+BK22+BO22+BS22+BW22+CA22+CE22 | CG22: =E22+I22+M22+Q22+U22+Y22+AC22+AG22+AK22+AO22+AS22+AW22+BA22+BE22+BI22+BM22+BQ22+BU22+BY22+CC22 | CH22: =CH21+CG22
B23: 19 | C23: =F23+J23+N23+R23+V23+Z23+AD23+AH23+AL23+AP23+AT23+AX23+BB23+BF23+BJ23+BN23+BR23+BV23+BZ23+CD23 | D23: =G22 | E23: =IF(D23>0.005,D23*Debts!D8/12,0) | F23: 0 | G23: =MAX(0,D23+E23-F23) | H23: =K22 | I23: =IF(H23>0.005,H23*Debts!D9/12,0) | J23: 0 | K23: =MAX(0,H23+I23-J23) | L23: =O22 | M23: =IF(L23>0.005,L23*Debts!D10/12,0) | N23: 0 | O23: =MAX(0,L23+M23-N23) | P23: =S22 | Q23: =IF(P23>0.005,P23*Debts!D11/12,0) | R23: 0 | S23: =MAX(0,P23+Q23-R23) | T23: =W22 | U23: =IF(T23>0.005,T23*Debts!D12/12,0) | V23: 0 | W23: =MAX(0,T23+U23-V23) | X23: =AA22 | Y23: =IF(X23>0.005,X23*Debts!D13/12,0) | Z23: 0 | AA23: =MAX(0,X23+Y23-Z23) | AB23: =AE22 | AC23: =IF(AB23>0.005,AB23*Debts!D14/12,0) | AD23: 0 | AE23: =MAX(0,AB23+AC23-AD23) | AF23: =AI22 | AG23: =IF(AF23>0.005,AF23*Debts!D15/12,0) | AH23: 0 | AI23: =MAX(0,AF23+AG23-AH23) | AJ23: =AM22 | AK23: =IF(AJ23>0.005,AJ23*Debts!D16/12,0) | AL23: 0 | AM23: =MAX(0,AJ23+AK23-AL23) | AN23: =AQ22 | AO23: =IF(AN23>0.005,AN23*Debts!D17/12,0) | AP23: 0 | AQ23: =MAX(0,AN23+AO23-AP23) | AR23: =AU22 | AS23: =IF(AR23>0.005,AR23*Debts!D18/12,0) | AT23: 0 | AU23: =MAX(0,AR23+AS23-AT23) | AV23: =AY22 | AW23: =IF(AV23>0.005,AV23*Debts!D19/12,0) | AX23: 0 | AY23: =MAX(0,AV23+AW23-AX23) | AZ23: =BC22 | BA23: =IF(AZ23>0.005,AZ23*Debts!D20/12,0) | BB23: 0 | BC23: =MAX(0,AZ23+BA23-BB23) | BD23: =BG22 | BE23: =IF(BD23>0.005,BD23*Debts!D21/12,0) | BF23: 0 | BG23: =MAX(0,BD23+BE23-BF23) | BH23: =BK22 | BI23: =IF(BH23>0.005,BH23*Debts!D22/12,0) | BJ23: 0 | BK23: =MAX(0,BH23+BI23-BJ23) | BL23: =BO22 | BM23: =IF(BL23>0.005,BL23*Debts!D23/12,0) | BN23: 0 | BO23: =MAX(0,BL23+BM23-BN23) | BP23: =BS22 | BQ23: =IF(BP23>0.005,BP23*Debts!D24/12,0) | BR23: 0 | BS23: =MAX(0,BP23+BQ23-BR23) | BT23: =BW22 | BU23: =IF(BT23>0.005,BT23*Debts!D25/12,0) | BV23: 0 | BW23: =MAX(0,BT23+BU23-BV23) | BX23: =CA22 | BY23: =IF(BX23>0.005,BX23*Debts!D26/12,0) | BZ23: 0 | CA23: =MAX(0,BX23+BY23-BZ23) | CB23: =CE22 | CC23: =IF(CB23>0.005,CB23*Debts!D27/12,0) | CD23: 0 | CE23: =MAX(0,CB23+CC23-CD23) | CF23: =G23+K23+O23+S23+W23+AA23+AE23+AI23+AM23+AQ23+AU23+AY23+BC23+BG23+BK23+BO23+BS23+BW23+CA23+CE23 | CG23: =E23+I23+M23+Q23+U23+Y23+AC23+AG23+AK23+AO23+AS23+AW23+BA23+BE23+BI23+BM23+BQ23+BU23+BY23+CC23 | CH23: =CH22+CG23
B24: 20 | C24: =F24+J24+N24+R24+V24+Z24+AD24+AH24+AL24+AP24+AT24+AX24+BB24+BF24+BJ24+BN24+BR24+BV24+BZ24+CD24 | D24: =G23 | E24: =IF(D24>0.005,D24*Debts!D8/12,0) | F24: 0 | G24: =MAX(0,D24+E24-F24) | H24: =K23 | I24: =IF(H24>0.005,H24*Debts!D9/12,0) | J24: 0 | K24: =MAX(0,H24+I24-J24) | L24: =O23 | M24: =IF(L24>0.005,L24*Debts!D10/12,0) | N24: 0 | O24: =MAX(0,L24+M24-N24) | P24: =S23 | Q24: =IF(P24>0.005,P24*Debts!D11/12,0) | R24: 0 | S24: =MAX(0,P24+Q24-R24) | T24: =W23 | U24: =IF(T24>0.005,T24*Debts!D12/12,0) | V24: 0 | W24: =MAX(0,T24+U24-V24) | X24: =AA23 | Y24: =IF(X24>0.005,X24*Debts!D13/12,0) | Z24: 0 | AA24: =MAX(0,X24+Y24-Z24) | AB24: =AE23 | AC24: =IF(AB24>0.005,AB24*Debts!D14/12,0) | AD24: 0 | AE24: =MAX(0,AB24+AC24-AD24) | AF24: =AI23 | AG24: =IF(AF24>0.005,AF24*Debts!D15/12,0) | AH24: 0 | AI24: =MAX(0,AF24+AG24-AH24) | AJ24: =AM23 | AK24: =IF(AJ24>0.005,AJ24*Debts!D16/12,0) | AL24: 0 | AM24: =MAX(0,AJ24+AK24-AL24) | AN24: =AQ23 | AO24: =IF(AN24>0.005,AN24*Debts!D17/12,0) | AP24: 0 | AQ24: =MAX(0,AN24+AO24-AP24) | AR24: =AU23 | AS24: =IF(AR24>0.005,AR24*Debts!D18/12,0) | AT24: 0 | AU24: =MAX(0,AR24+AS24-AT24) | AV24: =AY23 | AW24: =IF(AV24>0.005,AV24*Debts!D19/12,0) | AX24: 0 | AY24: =MAX(0,AV24+AW24-AX24) | AZ24: =BC23 | BA24: =IF(AZ24>0.005,AZ24*Debts!D20/12,0) | BB24: 0 | BC24: =MAX(0,AZ24+BA24-BB24) | BD24: =BG23 | BE24: =IF(BD24>0.005,BD24*Debts!D21/12,0) | BF24: 0 | BG24: =MAX(0,BD24+BE24-BF24) | BH24: =BK23 | BI24: =IF(BH24>0.005,BH24*Debts!D22/12,0) | BJ24: 0 | BK24: =MAX(0,BH24+BI24-BJ24) | BL24: =BO23 | BM24: =IF(BL24>0.005,BL24*Debts!D23/12,0) | BN24: 0 | BO24: =MAX(0,BL24+BM24-BN24) | BP24: =BS23 | BQ24: =IF(BP24>0.005,BP24*Debts!D24/12,0) | BR24: 0 | BS24: =MAX(0,BP24+BQ24-BR24) | BT24: =BW23 | BU24: =IF(BT24>0.005,BT24*Debts!D25/12,0) | BV24: 0 | BW24: =MAX(0,BT24+BU24-BV24) | BX24: =CA23 | BY24: =IF(BX24>0.005,BX24*Debts!D26/12,0) | BZ24: 0 | CA24: =MAX(0,BX24+BY24-BZ24) | CB24: =CE23 | CC24: =IF(CB24>0.005,CB24*Debts!D27/12,0) | CD24: 0 | CE24: =MAX(0,CB24+CC24-CD24) | CF24: =G24+K24+O24+S24+W24+AA24+AE24+AI24+AM24+AQ24+AU24+AY24+BC24+BG24+BK24+BO24+BS24+BW24+CA24+CE24 | CG24: =E24+I24+M24+Q24+U24+Y24+AC24+AG24+AK24+AO24+AS24+AW24+BA24+BE24+BI24+BM24+BQ24+BU24+BY24+CC24 | CH24: =CH23+CG24
B25: 21 | C25: =F25+J25+N25+R25+V25+Z25+AD25+AH25+AL25+AP25+AT25+AX25+BB25+BF25+BJ25+BN25+BR25+BV25+BZ25+CD25 | D25: =G24 | E25: =IF(D25>0.005,D25*Debts!D8/12,0) | F25: 0 | G25: =MAX(0,D25+E25-F25) | H25: =K24 | I25: =IF(H25>0.005,H25*Debts!D9/12,0) | J25: 0 | K25: =MAX(0,H25+I25-J25) | L25: =O24 | M25: =IF(L25>0.005,L25*Debts!D10/12,0) | N25: 0 | O25: =MAX(0,L25+M25-N25) | P25: =S24 | Q25: =IF(P25>0.005,P25*Debts!D11/12,0) | R25: 0 | S25: =MAX(0,P25+Q25-R25) | T25: =W24 | U25: =IF(T25>0.005,T25*Debts!D12/12,0) | V25: 0 | W25: =MAX(0,T25+U25-V25) | X25: =AA24 | Y25: =IF(X25>0.005,X25*Debts!D13/12,0) | Z25: 0 | AA25: =MAX(0,X25+Y25-Z25) | AB25: =AE24 | AC25: =IF(AB25>0.005,AB25*Debts!D14/12,0) | AD25: 0 | AE25: =MAX(0,AB25+AC25-AD25) | AF25: =AI24 | AG25: =IF(AF25>0.005,AF25*Debts!D15/12,0) | AH25: 0 | AI25: =MAX(0,AF25+AG25-AH25) | AJ25: =AM24 | AK25: =IF(AJ25>0.005,AJ25*Debts!D16/12,0) | AL25: 0 | AM25: =MAX(0,AJ25+AK25-AL25) | AN25: =AQ24 | AO25: =IF(AN25>0.005,AN25*Debts!D17/12,0) | AP25: 0 | AQ25: =MAX(0,AN25+AO25-AP25) | AR25: =AU24 | AS25: =IF(AR25>0.005,AR25*Debts!D18/12,0) | AT25: 0 | AU25: =MAX(0,AR25+AS25-AT25) | AV25: =AY24 | AW25: =IF(AV25>0.005,AV25*Debts!D19/12,0) | AX25: 0 | AY25: =MAX(0,AV25+AW25-AX25) | AZ25: =BC24 | BA25: =IF(AZ25>0.005,AZ25*Debts!D20/12,0) | BB25: 0 | BC25: =MAX(0,AZ25+BA25-BB25) | BD25: =BG24 | BE25: =IF(BD25>0.005,BD25*Debts!D21/12,0) | BF25: 0 | BG25: =MAX(0,BD25+BE25-BF25) | BH25: =BK24 | BI25: =IF(BH25>0.005,BH25*Debts!D22/12,0) | BJ25: 0 | BK25: =MAX(0,BH25+BI25-BJ25) | BL25: =BO24 | BM25: =IF(BL25>0.005,BL25*Debts!D23/12,0) | BN25: 0 | BO25: =MAX(0,BL25+BM25-BN25) | BP25: =BS24 | BQ25: =IF(BP25>0.005,BP25*Debts!D24/12,0) | BR25: 0 | BS25: =MAX(0,BP25+BQ25-BR25) | BT25: =BW24 | BU25: =IF(BT25>0.005,BT25*Debts!D25/12,0) | BV25: 0 | BW25: =MAX(0,BT25+BU25-BV25) | BX25: =CA24 | BY25: =IF(BX25>0.005,BX25*Debts!D26/12,0) | BZ25: 0 | CA25: =MAX(0,BX25+BY25-BZ25) | CB25: =CE24 | CC25: =IF(CB25>0.005,CB25*Debts!D27/12,0) | CD25: 0 | CE25: =MAX(0,CB25+CC25-CD25) | CF25: =G25+K25+O25+S25+W25+AA25+AE25+AI25+AM25+AQ25+AU25+AY25+BC25+BG25+BK25+BO25+BS25+BW25+CA25+CE25 | CG25: =E25+I25+M25+Q25+U25+Y25+AC25+AG25+AK25+AO25+AS25+AW25+BA25+BE25+BI25+BM25+BQ25+BU25+BY25+CC25 | CH25: =CH24+CG25
B26: 22 | C26: =F26+J26+N26+R26+V26+Z26+AD26+AH26+AL26+AP26+AT26+AX26+BB26+BF26+BJ26+BN26+BR26+BV26+BZ26+CD26 | D26: =G25 | E26: =IF(D26>0.005,D26*Debts!D8/12,0) | F26: 0 | G26: =MAX(0,D26+E26-F26) | H26: =K25 | I26: =IF(H26>0.005,H26*Debts!D9/12,0) | J26: 0 | K26: =MAX(0,H26+I26-J26) | L26: =O25 | M26: =IF(L26>0.005,L26*Debts!D10/12,0) | N26: 0 | O26: =MAX(0,L26+M26-N26) | P26: =S25 | Q26: =IF(P26>0.005,P26*Debts!D11/12,0) | R26: 0 | S26: =MAX(0,P26+Q26-R26) | T26: =W25 | U26: =IF(T26>0.005,T26*Debts!D12/12,0) | V26: 0 | W26: =MAX(0,T26+U26-V26) | X26: =AA25 | Y26: =IF(X26>0.005,X26*Debts!D13/12,0) | Z26: 0 | AA26: =MAX(0,X26+Y26-Z26) | AB26: =AE25 | AC26: =IF(AB26>0.005,AB26*Debts!D14/12,0) | AD26: 0 | AE26: =MAX(0,AB26+AC26-AD26) | AF26: =AI25 | AG26: =IF(AF26>0.005,AF26*Debts!D15/12,0) | AH26: 0 | AI26: =MAX(0,AF26+AG26-AH26) | AJ26: =AM25 | AK26: =IF(AJ26>0.005,AJ26*Debts!D16/12,0) | AL26: 0 | AM26: =MAX(0,AJ26+AK26-AL26) | AN26: =AQ25 | AO26: =IF(AN26>0.005,AN26*Debts!D17/12,0) | AP26: 0 | AQ26: =MAX(0,AN26+AO26-AP26) | AR26: =AU25 | AS26: =IF(AR26>0.005,AR26*Debts!D18/12,0) | AT26: 0 | AU26: =MAX(0,AR26+AS26-AT26) | AV26: =AY25 | AW26: =IF(AV26>0.005,AV26*Debts!D19/12,0) | AX26: 0 | AY26: =MAX(0,AV26+AW26-AX26) | AZ26: =BC25 | BA26: =IF(AZ26>0.005,AZ26*Debts!D20/12,0) | BB26: 0 | BC26: =MAX(0,AZ26+BA26-BB26) | BD26: =BG25 | BE26: =IF(BD26>0.005,BD26*Debts!D21/12,0) | BF26: 0 | BG26: =MAX(0,BD26+BE26-BF26) | BH26: =BK25 | BI26: =IF(BH26>0.005,BH26*Debts!D22/12,0) | BJ26: 0 | BK26: =MAX(0,BH26+BI26-BJ26) | BL26: =BO25 | BM26: =IF(BL26>0.005,BL26*Debts!D23/12,0) | BN26: 0 | BO26: =MAX(0,BL26+BM26-BN26) | BP26: =BS25 | BQ26: =IF(BP26>0.005,BP26*Debts!D24/12,0) | BR26: 0 | BS26: =MAX(0,BP26+BQ26-BR26) | BT26: =BW25 | BU26: =IF(BT26>0.005,BT26*Debts!D25/12,0) | BV26: 0 | BW26: =MAX(0,BT26+BU26-BV26) | BX26: =CA25 | BY26: =IF(BX26>0.005,BX26*Debts!D26/12,0) | BZ26: 0 | CA26: =MAX(0,BX26+BY26-BZ26) | CB26: =CE25 | CC26: =IF(CB26>0.005,CB26*Debts!D27/12,0) | CD26: 0 | CE26: =MAX(0,CB26+CC26-CD26) | CF26: =G26+K26+O26+S26+W26+AA26+AE26+AI26+AM26+AQ26+AU26+AY26+BC26+BG26+BK26+BO26+BS26+BW26+CA26+CE26 | CG26: =E26+I26+M26+Q26+U26+Y26+AC26+AG26+AK26+AO26+AS26+AW26+BA26+BE26+BI26+BM26+BQ26+BU26+BY26+CC26 | CH26: =CH25+CG26
B27: 23 | C27: =F27+J27+N27+R27+V27+Z27+AD27+AH27+AL27+AP27+AT27+AX27+BB27+BF27+BJ27+BN27+BR27+BV27+BZ27+CD27 | D27: =G26 | E27: =IF(D27>0.005,D27*Debts!D8/12,0) | F27: 0 | G27: =MAX(0,D27+E27-F27) | H27: =K26 | I27: =IF(H27>0.005,H27*Debts!D9/12,0) | J27: 0 | K27: =MAX(0,H27+I27-J27) | L27: =O26 | M27: =IF(L27>0.005,L27*Debts!D10/12,0) | N27: 0 | O27: =MAX(0,L27+M27-N27) | P27: =S26 | Q27: =IF(P27>0.005,P27*Debts!D11/12,0) | R27: 0 | S27: =MAX(0,P27+Q27-R27) | T27: =W26 | U27: =IF(T27>0.005,T27*Debts!D12/12,0) | V27: 0 | W27: =MAX(0,T27+U27-V27) | X27: =AA26 | Y27: =IF(X27>0.005,X27*Debts!D13/12,0) | Z27: 0 | AA27: =MAX(0,X27+Y27-Z27) | AB27: =AE26 | AC27: =IF(AB27>0.005,AB27*Debts!D14/12,0) | AD27: 0 | AE27: =MAX(0,AB27+AC27-AD27) | AF27: =AI26 | AG27: =IF(AF27>0.005,AF27*Debts!D15/12,0) | AH27: 0 | AI27: =MAX(0,AF27+AG27-AH27) | AJ27: =AM26 | AK27: =IF(AJ27>0.005,AJ27*Debts!D16/12,0) | AL27: 0 | AM27: =MAX(0,AJ27+AK27-AL27) | AN27: =AQ26 | AO27: =IF(AN27>0.005,AN27*Debts!D17/12,0) | AP27: 0 | AQ27: =MAX(0,AN27+AO27-AP27) | AR27: =AU26 | AS27: =IF(AR27>0.005,AR27*Debts!D18/12,0) | AT27: 0 | AU27: =MAX(0,AR27+AS27-AT27) | AV27: =AY26 | AW27: =IF(AV27>0.005,AV27*Debts!D19/12,0) | AX27: 0 | AY27: =MAX(0,AV27+AW27-AX27) | AZ27: =BC26 | BA27: =IF(AZ27>0.005,AZ27*Debts!D20/12,0) | BB27: 0 | BC27: =MAX(0,AZ27+BA27-BB27) | BD27: =BG26 | BE27: =IF(BD27>0.005,BD27*Debts!D21/12,0) | BF27: 0 | BG27: =MAX(0,BD27+BE27-BF27) | BH27: =BK26 | BI27: =IF(BH27>0.005,BH27*Debts!D22/12,0) | BJ27: 0 | BK27: =MAX(0,BH27+BI27-BJ27) | BL27: =BO26 | BM27: =IF(BL27>0.005,BL27*Debts!D23/12,0) | BN27: 0 | BO27: =MAX(0,BL27+BM27-BN27) | BP27: =BS26 | BQ27: =IF(BP27>0.005,BP27*Debts!D24/12,0) | BR27: 0 | BS27: =MAX(0,BP27+BQ27-BR27) | BT27: =BW26 | BU27: =IF(BT27>0.005,BT27*Debts!D25/12,0) | BV27: 0 | BW27: =MAX(0,BT27+BU27-BV27) | BX27: =CA26 | BY27: =IF(BX27>0.005,BX27*Debts!D26/12,0) | BZ27: 0 | CA27: =MAX(0,BX27+BY27-BZ27) | CB27: =CE26 | CC27: =IF(CB27>0.005,CB27*Debts!D27/12,0) | CD27: 0 | CE27: =MAX(0,CB27+CC27-CD27) | CF27: =G27+K27+O27+S27+W27+AA27+AE27+AI27+AM27+AQ27+AU27+AY27+BC27+BG27+BK27+BO27+BS27+BW27+CA27+CE27 | CG27: =E27+I27+M27+Q27+U27+Y27+AC27+AG27+AK27+AO27+AS27+AW27+BA27+BE27+BI27+BM27+BQ27+BU27+BY27+CC27 | CH27: =CH26+CG27
B28: 24 | C28: =F28+J28+N28+R28+V28+Z28+AD28+AH28+AL28+AP28+AT28+AX28+BB28+BF28+BJ28+BN28+BR28+BV28+BZ28+CD28 | D28: =G27 | E28: =IF(D28>0.005,D28*Debts!D8/12,0) | F28: 0 | G28: =MAX(0,D28+E28-F28) | H28: =K27 | I28: =IF(H28>0.005,H28*Debts!D9/12,0) | J28: 0 | K28: =MAX(0,H28+I28-J28) | L28: =O27 | M28: =IF(L28>0.005,L28*Debts!D10/12,0) | N28: 0 | O28: =MAX(0,L28+M28-N28) | P28: =S27 | Q28: =IF(P28>0.005,P28*Debts!D11/12,0) | R28: 0 | S28: =MAX(0,P28+Q28-R28) | T28: =W27 | U28: =IF(T28>0.005,T28*Debts!D12/12,0) | V28: 0 | W28: =MAX(0,T28+U28-V28) | X28: =AA27 | Y28: =IF(X28>0.005,X28*Debts!D13/12,0) | Z28: 0 | AA28: =MAX(0,X28+Y28-Z28) | AB28: =AE27 | AC28: =IF(AB28>0.005,AB28*Debts!D14/12,0) | AD28: 0 | AE28: =MAX(0,AB28+AC28-AD28) | AF28: =AI27 | AG28: =IF(AF28>0.005,AF28*Debts!D15/12,0) | AH28: 0 | AI28: =MAX(0,AF28+AG28-AH28) | AJ28: =AM27 | AK28: =IF(AJ28>0.005,AJ28*Debts!D16/12,0) | AL28: 0 | AM28: =MAX(0,AJ28+AK28-AL28) | AN28: =AQ27 | AO28: =IF(AN28>0.005,AN28*Debts!D17/12,0) | AP28: 0 | AQ28: =MAX(0,AN28+AO28-AP28) | AR28: =AU27 | AS28: =IF(AR28>0.005,AR28*Debts!D18/12,0) | AT28: 0 | AU28: =MAX(0,AR28+AS28-AT28) | AV28: =AY27 | AW28: =IF(AV28>0.005,AV28*Debts!D19/12,0) | AX28: 0 | AY28: =MAX(0,AV28+AW28-AX28) | AZ28: =BC27 | BA28: =IF(AZ28>0.005,AZ28*Debts!D20/12,0) | BB28: 0 | BC28: =MAX(0,AZ28+BA28-BB28) | BD28: =BG27 | BE28: =IF(BD28>0.005,BD28*Debts!D21/12,0) | BF28: 0 | BG28: =MAX(0,BD28+BE28-BF28) | BH28: =BK27 | BI28: =IF(BH28>0.005,BH28*Debts!D22/12,0) | BJ28: 0 | BK28: =MAX(0,BH28+BI28-BJ28) | BL28: =BO27 | BM28: =IF(BL28>0.005,BL28*Debts!D23/12,0) | BN28: 0 | BO28: =MAX(0,BL28+BM28-BN28) | BP28: =BS27 | BQ28: =IF(BP28>0.005,BP28*Debts!D24/12,0) | BR28: 0 | BS28: =MAX(0,BP28+BQ28-BR28) | BT28: =BW27 | BU28: =IF(BT28>0.005,BT28*Debts!D25/12,0) | BV28: 0 | BW28: =MAX(0,BT28+BU28-BV28) | BX28: =CA27 | BY28: =IF(BX28>0.005,BX28*Debts!D26/12,0) | BZ28: 0 | CA28: =MAX(0,BX28+BY28-BZ28) | CB28: =CE27 | CC28: =IF(CB28>0.005,CB28*Debts!D27/12,0) | CD28: 0 | CE28: =MAX(0,CB28+CC28-CD28) | CF28: =G28+K28+O28+S28+W28+AA28+AE28+AI28+AM28+AQ28+AU28+AY28+BC28+BG28+BK28+BO28+BS28+BW28+CA28+CE28 | CG28: =E28+I28+M28+Q28+U28+Y28+AC28+AG28+AK28+AO28+AS28+AW28+BA28+BE28+BI28+BM28+BQ28+BU28+BY28+CC28 | CH28: =CH27+CG28
B29: 25 | C29: =F29+J29+N29+R29+V29+Z29+AD29+AH29+AL29+AP29+AT29+AX29+BB29+BF29+BJ29+BN29+BR29+BV29+BZ29+CD29 | D29: =G28 | E29: =IF(D29>0.005,D29*Debts!D8/12,0) | F29: 0 | G29: =MAX(0,D29+E29-F29) | H29: =K28 | I29: =IF(H29>0.005,H29*Debts!D9/12,0) | J29: 0 | K29: =MAX(0,H29+I29-J29) | L29: =O28 | M29: =IF(L29>0.005,L29*Debts!D10/12,0) | N29: 0 | O29: =MAX(0,L29+M29-N29) | P29: =S28 | Q29: =IF(P29>0.005,P29*Debts!D11/12,0) | R29: 0 | S29: =MAX(0,P29+Q29-R29) | T29: =W28 | U29: =IF(T29>0.005,T29*Debts!D12/12,0) | V29: 0 | W29: =MAX(0,T29+U29-V29) | X29: =AA28 | Y29: =IF(X29>0.005,X29*Debts!D13/12,0) | Z29: 0 | AA29: =MAX(0,X29+Y29-Z29) | AB29: =AE28 | AC29: =IF(AB29>0.005,AB29*Debts!D14/12,0) | AD29: 0 | AE29: =MAX(0,AB29+AC29-AD29) | AF29: =AI28 | AG29: =IF(AF29>0.005,AF29*Debts!D15/12,0) | AH29: 0 | AI29: =MAX(0,AF29+AG29-AH29) | AJ29: =AM28 | AK29: =IF(AJ29>0.005,AJ29*Debts!D16/12,0) | AL29: 0 | AM29: =MAX(0,AJ29+AK29-AL29) | AN29: =AQ28 | AO29: =IF(AN29>0.005,AN29*Debts!D17/12,0) | AP29: 0 | AQ29: =MAX(0,AN29+AO29-AP29) | AR29: =AU28 | AS29: =IF(AR29>0.005,AR29*Debts!D18/12,0) | AT29: 0 | AU29: =MAX(0,AR29+AS29-AT29) | AV29: =AY28 | AW29: =IF(AV29>0.005,AV29*Debts!D19/12,0) | AX29: 0 | AY29: =MAX(0,AV29+AW29-AX29) | AZ29: =BC28 | BA29: =IF(AZ29>0.005,AZ29*Debts!D20/12,0) | BB29: 0 | BC29: =MAX(0,AZ29+BA29-BB29) | BD29: =BG28 | BE29: =IF(BD29>0.005,BD29*Debts!D21/12,0) | BF29: 0 | BG29: =MAX(0,BD29+BE29-BF29) | BH29: =BK28 | BI29: =IF(BH29>0.005,BH29*Debts!D22/12,0) | BJ29: 0 | BK29: =MAX(0,BH29+BI29-BJ29) | BL29: =BO28 | BM29: =IF(BL29>0.005,BL29*Debts!D23/12,0) | BN29: 0 | BO29: =MAX(0,BL29+BM29-BN29) | BP29: =BS28 | BQ29: =IF(BP29>0.005,BP29*Debts!D24/12,0) | BR29: 0 | BS29: =MAX(0,BP29+BQ29-BR29) | BT29: =BW28 | BU29: =IF(BT29>0.005,BT29*Debts!D25/12,0) | BV29: 0 | BW29: =MAX(0,BT29+BU29-BV29) | BX29: =CA28 | BY29: =IF(BX29>0.005,BX29*Debts!D26/12,0) | BZ29: 0 | CA29: =MAX(0,BX29+BY29-BZ29) | CB29: =CE28 | CC29: =IF(CB29>0.005,CB29*Debts!D27/12,0) | CD29: 0 | CE29: =MAX(0,CB29+CC29-CD29) | CF29: =G29+K29+O29+S29+W29+AA29+AE29+AI29+AM29+AQ29+AU29+AY29+BC29+BG29+BK29+BO29+BS29+BW29+CA29+CE29 | CG29: =E29+I29+M29+Q29+U29+Y29+AC29+AG29+AK29+AO29+AS29+AW29+BA29+BE29+BI29+BM29+BQ29+BU29+BY29+CC29 | CH29: =CH28+CG29
B30: 26 | C30: =F30+J30+N30+R30+V30+Z30+AD30+AH30+AL30+AP30+AT30+AX30+BB30+BF30+BJ30+BN30+BR30+BV30+BZ30+CD30 | D30: =G29 | E30: =IF(D30>0.005,D30*Debts!D8/12,0) | F30: 0 | G30: =MAX(0,D30+E30-F30) | H30: =K29 | I30: =IF(H30>0.005,H30*Debts!D9/12,0) | J30: 0 | K30: =MAX(0,H30+I30-J30) | L30: =O29 | M30: =IF(L30>0.005,L30*Debts!D10/12,0) | N30: 0 | O30: =MAX(0,L30+M30-N30) | P30: =S29 | Q30: =IF(P30>0.005,P30*Debts!D11/12,0) | R30: 0 | S30: =MAX(0,P30+Q30-R30) | T30: =W29 | U30: =IF(T30>0.005,T30*Debts!D12/12,0) | V30: 0 | W30: =MAX(0,T30+U30-V30) | X30: =AA29 | Y30: =IF(X30>0.005,X30*Debts!D13/12,0) | Z30: 0 | AA30: =MAX(0,X30+Y30-Z30) | AB30: =AE29 | AC30: =IF(AB30>0.005,AB30*Debts!D14/12,0) | AD30: 0 | AE30: =MAX(0,AB30+AC30-AD30) | AF30: =AI29 | AG30: =IF(AF30>0.005,AF30*Debts!D15/12,0) | AH30: 0 | AI30: =MAX(0,AF30+AG30-AH30) | AJ30: =AM29 | AK30: =IF(AJ30>0.005,AJ30*Debts!D16/12,0) | AL30: 0 | AM30: =MAX(0,AJ30+AK30-AL30) | AN30: =AQ29 | AO30: =IF(AN30>0.005,AN30*Debts!D17/12,0) | AP30: 0 | AQ30: =MAX(0,AN30+AO30-AP30) | AR30: =AU29 | AS30: =IF(AR30>0.005,AR30*Debts!D18/12,0) | AT30: 0 | AU30: =MAX(0,AR30+AS30-AT30) | AV30: =AY29 | AW30: =IF(AV30>0.005,AV30*Debts!D19/12,0) | AX30: 0 | AY30: =MAX(0,AV30+AW30-AX30) | AZ30: =BC29 | BA30: =IF(AZ30>0.005,AZ30*Debts!D20/12,0) | BB30: 0 | BC30: =MAX(0,AZ30+BA30-BB30) | BD30: =BG29 | BE30: =IF(BD30>0.005,BD30*Debts!D21/12,0) | BF30: 0 | BG30: =MAX(0,BD30+BE30-BF30) | BH30: =BK29 | BI30: =IF(BH30>0.005,BH30*Debts!D22/12,0) | BJ30: 0 | BK30: =MAX(0,BH30+BI30-BJ30) | BL30: =BO29 | BM30: =IF(BL30>0.005,BL30*Debts!D23/12,0) | BN30: 0 | BO30: =MAX(0,BL30+BM30-BN30) | BP30: =BS29 | BQ30: =IF(BP30>0.005,BP30*Debts!D24/12,0) | BR30: 0 | BS30: =MAX(0,BP30+BQ30-BR30) | BT30: =BW29 | BU30: =IF(BT30>0.005,BT30*Debts!D25/12,0) | BV30: 0 | BW30: =MAX(0,BT30+BU30-BV30) | BX30: =CA29 | BY30: =IF(BX30>0.005,BX30*Debts!D26/12,0) | BZ30: 0 | CA30: =MAX(0,BX30+BY30-BZ30) | CB30: =CE29 | CC30: =IF(CB30>0.005,CB30*Debts!D27/12,0) | CD30: 0 | CE30: =MAX(0,CB30+CC30-CD30) | CF30: =G30+K30+O30+S30+W30+AA30+AE30+AI30+AM30+AQ30+AU30+AY30+BC30+BG30+BK30+BO30+BS30+BW30+CA30+CE30 | CG30: =E30+I30+M30+Q30+U30+Y30+AC30+AG30+AK30+AO30+AS30+AW30+BA30+BE30+BI30+BM30+BQ30+BU30+BY30+CC30 | CH30: =CH29+CG30
B31: 27 | C31: =F31+J31+N31+R31+V31+Z31+AD31+AH31+AL31+AP31+AT31+AX31+BB31+BF31+BJ31+BN31+BR31+BV31+BZ31+CD31 | D31: =G30 | E31: =IF(D31>0.005,D31*Debts!D8/12,0) | F31: 0 | G31: =MAX(0,D31+E31-F31) | H31: =K30 | I31: =IF(H31>0.005,H31*Debts!D9/12,0) | J31: 0 | K31: =MAX(0,H31+I31-J31) | L31: =O30 | M31: =IF(L31>0.005,L31*Debts!D10/12,0) | N31: 0 | O31: =MAX(0,L31+M31-N31) | P31: =S30 | Q31: =IF(P31>0.005,P31*Debts!D11/12,0) | R31: 0 | S31: =MAX(0,P31+Q31-R31) | T31: =W30 | U31: =IF(T31>0.005,T31*Debts!D12/12,0) | V31: 0 | W31: =MAX(0,T31+U31-V31) | X31: =AA30 | Y31: =IF(X31>0.005,X31*Debts!D13/12,0) | Z31: 0 | AA31: =MAX(0,X31+Y31-Z31) | AB31: =AE30 | AC31: =IF(AB31>0.005,AB31*Debts!D14/12,0) | AD31: 0 | AE31: =MAX(0,AB31+AC31-AD31) | AF31: =AI30 | AG31: =IF(AF31>0.005,AF31*Debts!D15/12,0) | AH31: 0 | AI31: =MAX(0,AF31+AG31-AH31) | AJ31: =AM30 | AK31: =IF(AJ31>0.005,AJ31*Debts!D16/12,0) | AL31: 0 | AM31: =MAX(0,AJ31+AK31-AL31) | AN31: =AQ30 | AO31: =IF(AN31>0.005,AN31*Debts!D17/12,0) | AP31: 0 | AQ31: =MAX(0,AN31+AO31-AP31) | AR31: =AU30 | AS31: =IF(AR31>0.005,AR31*Debts!D18/12,0) | AT31: 0 | AU31: =MAX(0,AR31+AS31-AT31) | AV31: =AY30 | AW31: =IF(AV31>0.005,AV31*Debts!D19/12,0) | AX31: 0 | AY31: =MAX(0,AV31+AW31-AX31) | AZ31: =BC30 | BA31: =IF(AZ31>0.005,AZ31*Debts!D20/12,0) | BB31: 0 | BC31: =MAX(0,AZ31+BA31-BB31) | BD31: =BG30 | BE31: =IF(BD31>0.005,BD31*Debts!D21/12,0) | BF31: 0 | BG31: =MAX(0,BD31+BE31-BF31) | BH31: =BK30 | BI31: =IF(BH31>0.005,BH31*Debts!D22/12,0) | BJ31: 0 | BK31: =MAX(0,BH31+BI31-BJ31) | BL31: =BO30 | BM31: =IF(BL31>0.005,BL31*Debts!D23/12,0) | BN31: 0 | BO31: =MAX(0,BL31+BM31-BN31) | BP31: =BS30 | BQ31: =IF(BP31>0.005,BP31*Debts!D24/12,0) | BR31: 0 | BS31: =MAX(0,BP31+BQ31-BR31) | BT31: =BW30 | BU31: =IF(BT31>0.005,BT31*Debts!D25/12,0) | BV31: 0 | BW31: =MAX(0,BT31+BU31-BV31) | BX31: =CA30 | BY31: =IF(BX31>0.005,BX31*Debts!D26/12,0) | BZ31: 0 | CA31: =MAX(0,BX31+BY31-BZ31) | CB31: =CE30 | CC31: =IF(CB31>0.005,CB31*Debts!D27/12,0) | CD31: 0 | CE31: =MAX(0,CB31+CC31-CD31) | CF31: =G31+K31+O31+S31+W31+AA31+AE31+AI31+AM31+AQ31+AU31+AY31+BC31+BG31+BK31+BO31+BS31+BW31+CA31+CE31 | CG31: =E31+I31+M31+Q31+U31+Y31+AC31+AG31+AK31+AO31+AS31+AW31+BA31+BE31+BI31+BM31+BQ31+BU31+BY31+CC31 | CH31: =CH30+CG31
B32: 28 | C32: =F32+J32+N32+R32+V32+Z32+AD32+AH32+AL32+AP32+AT32+AX32+BB32+BF32+BJ32+BN32+BR32+BV32+BZ32+CD32 | D32: =G31 | E32: =IF(D32>0.005,D32*Debts!D8/12,0) | F32: 0 | G32: =MAX(0,D32+E32-F32) | H32: =K31 | I32: =IF(H32>0.005,H32*Debts!D9/12,0) | J32: 0 | K32: =MAX(0,H32+I32-J32) | L32: =O31 | M32: =IF(L32>0.005,L32*Debts!D10/12,0) | N32: 0 | O32: =MAX(0,L32+M32-N32) | P32: =S31 | Q32: =IF(P32>0.005,P32*Debts!D11/12,0) | R32: 0 | S32: =MAX(0,P32+Q32-R32) | T32: =W31 | U32: =IF(T32>0.005,T32*Debts!D12/12,0) | V32: 0 | W32: =MAX(0,T32+U32-V32) | X32: =AA31 | Y32: =IF(X32>0.005,X32*Debts!D13/12,0) | Z32: 0 | AA32: =MAX(0,X32+Y32-Z32) | AB32: =AE31 | AC32: =IF(AB32>0.005,AB32*Debts!D14/12,0) | AD32: 0 | AE32: =MAX(0,AB32+AC32-AD32) | AF32: =AI31 | AG32: =IF(AF32>0.005,AF32*Debts!D15/12,0) | AH32: 0 | AI32: =MAX(0,AF32+AG32-AH32) | AJ32: =AM31 | AK32: =IF(AJ32>0.005,AJ32*Debts!D16/12,0) | AL32: 0 | AM32: =MAX(0,AJ32+AK32-AL32) | AN32: =AQ31 | AO32: =IF(AN32>0.005,AN32*Debts!D17/12,0) | AP32: 0 | AQ32: =MAX(0,AN32+AO32-AP32) | AR32: =AU31 | AS32: =IF(AR32>0.005,AR32*Debts!D18/12,0) | AT32: 0 | AU32: =MAX(0,AR32+AS32-AT32) | AV32: =AY31 | AW32: =IF(AV32>0.005,AV32*Debts!D19/12,0) | AX32: 0 | AY32: =MAX(0,AV32+AW32-AX32) | AZ32: =BC31 | BA32: =IF(AZ32>0.005,AZ32*Debts!D20/12,0) | BB32: 0 | BC32: =MAX(0,AZ32+BA32-BB32) | BD32: =BG31 | BE32: =IF(BD32>0.005,BD32*Debts!D21/12,0) | BF32: 0 | BG32: =MAX(0,BD32+BE32-BF32) | BH32: =BK31 | BI32: =IF(BH32>0.005,BH32*Debts!D22/12,0) | BJ32: 0 | BK32: =MAX(0,BH32+BI32-BJ32) | BL32: =BO31 | BM32: =IF(BL32>0.005,BL32*Debts!D23/12,0) | BN32: 0 | BO32: =MAX(0,BL32+BM32-BN32) | BP32: =BS31 | BQ32: =IF(BP32>0.005,BP32*Debts!D24/12,0) | BR32: 0 | BS32: =MAX(0,BP32+BQ32-BR32) | BT32: =BW31 | BU32: =IF(BT32>0.005,BT32*Debts!D25/12,0) | BV32: 0 | BW32: =MAX(0,BT32+BU32-BV32) | BX32: =CA31 | BY32: =IF(BX32>0.005,BX32*Debts!D26/12,0) | BZ32: 0 | CA32: =MAX(0,BX32+BY32-BZ32) | CB32: =CE31 | CC32: =IF(CB32>0.005,CB32*Debts!D27/12,0) | CD32: 0 | CE32: =MAX(0,CB32+CC32-CD32) | CF32: =G32+K32+O32+S32+W32+AA32+AE32+AI32+AM32+AQ32+AU32+AY32+BC32+BG32+BK32+BO32+BS32+BW32+CA32+CE32 | CG32: =E32+I32+M32+Q32+U32+Y32+AC32+AG32+AK32+AO32+AS32+AW32+BA32+BE32+BI32+BM32+BQ32+BU32+BY32+CC32 | CH32: =CH31+CG32
B33: 29 | C33: =F33+J33+N33+R33+V33+Z33+AD33+AH33+AL33+AP33+AT33+AX33+BB33+BF33+BJ33+BN33+BR33+BV33+BZ33+CD33 | D33: =G32 | E33: =IF(D33>0.005,D33*Debts!D8/12,0) | F33: 0 | G33: =MAX(0,D33+E33-F33) | H33: =K32 | I33: =IF(H33>0.005,H33*Debts!D9/12,0) | J33: 0 | K33: =MAX(0,H33+I33-J33) | L33: =O32 | M33: =IF(L33>0.005,L33*Debts!D10/12,0) | N33: 0 | O33: =MAX(0,L33+M33-N33) | P33: =S32 | Q33: =IF(P33>0.005,P33*Debts!D11/12,0) | R33: 0 | S33: =MAX(0,P33+Q33-R33) | T33: =W32 | U33: =IF(T33>0.005,T33*Debts!D12/12,0) | V33: 0 | W33: =MAX(0,T33+U33-V33) | X33: =AA32 | Y33: =IF(X33>0.005,X33*Debts!D13/12,0) | Z33: 0 | AA33: =MAX(0,X33+Y33-Z33) | AB33: =AE32 | AC33: =IF(AB33>0.005,AB33*Debts!D14/12,0) | AD33: 0 | AE33: =MAX(0,AB33+AC33-AD33) | AF33: =AI32 | AG33: =IF(AF33>0.005,AF33*Debts!D15/12,0) | AH33: 0 | AI33: =MAX(0,AF33+AG33-AH33) | AJ33: =AM32 | AK33: =IF(AJ33>0.005,AJ33*Debts!D16/12,0) | AL33: 0 | AM33: =MAX(0,AJ33+AK33-AL33) | AN33: =AQ32 | AO33: =IF(AN33>0.005,AN33*Debts!D17/12,0) | AP33: 0 | AQ33: =MAX(0,AN33+AO33-AP33) | AR33: =AU32 | AS33: =IF(AR33>0.005,AR33*Debts!D18/12,0) | AT33: 0 | AU33: =MAX(0,AR33+AS33-AT33) | AV33: =AY32 | AW33: =IF(AV33>0.005,AV33*Debts!D19/12,0) | AX33: 0 | AY33: =MAX(0,AV33+AW33-AX33) | AZ33: =BC32 | BA33: =IF(AZ33>0.005,AZ33*Debts!D20/12,0) | BB33: 0 | BC33: =MAX(0,AZ33+BA33-BB33) | BD33: =BG32 | BE33: =IF(BD33>0.005,BD33*Debts!D21/12,0) | BF33: 0 | BG33: =MAX(0,BD33+BE33-BF33) | BH33: =BK32 | BI33: =IF(BH33>0.005,BH33*Debts!D22/12,0) | BJ33: 0 | BK33: =MAX(0,BH33+BI33-BJ33) | BL33: =BO32 | BM33: =IF(BL33>0.005,BL33*Debts!D23/12,0) | BN33: 0 | BO33: =MAX(0,BL33+BM33-BN33) | BP33: =BS32 | BQ33: =IF(BP33>0.005,BP33*Debts!D24/12,0) | BR33: 0 | BS33: =MAX(0,BP33+BQ33-BR33) | BT33: =BW32 | BU33: =IF(BT33>0.005,BT33*Debts!D25/12,0) | BV33: 0 | BW33: =MAX(0,BT33+BU33-BV33) | BX33: =CA32 | BY33: =IF(BX33>0.005,BX33*Debts!D26/12,0) | BZ33: 0 | CA33: =MAX(0,BX33+BY33-BZ33) | CB33: =CE32 | CC33: =IF(CB33>0.005,CB33*Debts!D27/12,0) | CD33: 0 | CE33: =MAX(0,CB33+CC33-CD33) | CF33: =G33+K33+O33+S33+W33+AA33+AE33+AI33+AM33+AQ33+AU33+AY33+BC33+BG33+BK33+BO33+BS33+BW33+CA33+CE33 | CG33: =E33+I33+M33+Q33+U33+Y33+AC33+AG33+AK33+AO33+AS33+AW33+BA33+BE33+BI33+BM33+BQ33+BU33+BY33+CC33 | CH33: =CH32+CG33
B34: 30 | C34: =F34+J34+N34+R34+V34+Z34+AD34+AH34+AL34+AP34+AT34+AX34+BB34+BF34+BJ34+BN34+BR34+BV34+BZ34+CD34 | D34: =G33 | E34: =IF(D34>0.005,D34*Debts!D8/12,0) | F34: 0 | G34: =MAX(0,D34+E34-F34) | H34: =K33 | I34: =IF(H34>0.005,H34*Debts!D9/12,0) | J34: 0 | K34: =MAX(0,H34+I34-J34) | L34: =O33 | M34: =IF(L34>0.005,L34*Debts!D10/12,0) | N34: 0 | O34: =MAX(0,L34+M34-N34) | P34: =S33 | Q34: =IF(P34>0.005,P34*Debts!D11/12,0) | R34: 0 | S34: =MAX(0,P34+Q34-R34) | T34: =W33 | U34: =IF(T34>0.005,T34*Debts!D12/12,0) | V34: 0 | W34: =MAX(0,T34+U34-V34) | X34: =AA33 | Y34: =IF(X34>0.005,X34*Debts!D13/12,0) | Z34: 0 | AA34: =MAX(0,X34+Y34-Z34) | AB34: =AE33 | AC34: =IF(AB34>0.005,AB34*Debts!D14/12,0) | AD34: 0 | AE34: =MAX(0,AB34+AC34-AD34) | AF34: =AI33 | AG34: =IF(AF34>0.005,AF34*Debts!D15/12,0) | AH34: 0 | AI34: =MAX(0,AF34+AG34-AH34) | AJ34: =AM33 | AK34: =IF(AJ34>0.005,AJ34*Debts!D16/12,0) | AL34: 0 | AM34: =MAX(0,AJ34+AK34-AL34) | AN34: =AQ33 | AO34: =IF(AN34>0.005,AN34*Debts!D17/12,0) | AP34: 0 | AQ34: =MAX(0,AN34+AO34-AP34) | AR34: =AU33 | AS34: =IF(AR34>0.005,AR34*Debts!D18/12,0) | AT34: 0 | AU34: =MAX(0,AR34+AS34-AT34) | AV34: =AY33 | AW34: =IF(AV34>0.005,AV34*Debts!D19/12,0) | AX34: 0 | AY34: =MAX(0,AV34+AW34-AX34) | AZ34: =BC33 | BA34: =IF(AZ34>0.005,AZ34*Debts!D20/12,0) | BB34: 0 | BC34: =MAX(0,AZ34+BA34-BB34) | BD34: =BG33 | BE34: =IF(BD34>0.005,BD34*Debts!D21/12,0) | BF34: 0 | BG34: =MAX(0,BD34+BE34-BF34) | BH34: =BK33 | BI34: =IF(BH34>0.005,BH34*Debts!D22/12,0) | BJ34: 0 | BK34: =MAX(0,BH34+BI34-BJ34) | BL34: =BO33 | BM34: =IF(BL34>0.005,BL34*Debts!D23/12,0) | BN34: 0 | BO34: =MAX(0,BL34+BM34-BN34) | BP34: =BS33 | BQ34: =IF(BP34>0.005,BP34*Debts!D24/12,0) | BR34: 0 | BS34: =MAX(0,BP34+BQ34-BR34) | BT34: =BW33 | BU34: =IF(BT34>0.005,BT34*Debts!D25/12,0) | BV34: 0 | BW34: =MAX(0,BT34+BU34-BV34) | BX34: =CA33 | BY34: =IF(BX34>0.005,BX34*Debts!D26/12,0) | BZ34: 0 | CA34: =MAX(0,BX34+BY34-BZ34) | CB34: =CE33 | CC34: =IF(CB34>0.005,CB34*Debts!D27/12,0) | CD34: 0 | CE34: =MAX(0,CB34+CC34-CD34) | CF34: =G34+K34+O34+S34+W34+AA34+AE34+AI34+AM34+AQ34+AU34+AY34+BC34+BG34+BK34+BO34+BS34+BW34+CA34+CE34 | CG34: =E34+I34+M34+Q34+U34+Y34+AC34+AG34+AK34+AO34+AS34+AW34+BA34+BE34+BI34+BM34+BQ34+BU34+BY34+CC34 | CH34: =CH33+CG34
B35: 31 | C35: =F35+J35+N35+R35+V35+Z35+AD35+AH35+AL35+AP35+AT35+AX35+BB35+BF35+BJ35+BN35+BR35+BV35+BZ35+CD35 | D35: =G34 | E35: =IF(D35>0.005,D35*Debts!D8/12,0) | F35: 0 | G35: =MAX(0,D35+E35-F35) | H35: =K34 | I35: =IF(H35>0.005,H35*Debts!D9/12,0) | J35: 0 | K35: =MAX(0,H35+I35-J35) | L35: =O34 | M35: =IF(L35>0.005,L35*Debts!D10/12,0) | N35: 0 | O35: =MAX(0,L35+M35-N35) | P35: =S34 | Q35: =IF(P35>0.005,P35*Debts!D11/12,0) | R35: 0 | S35: =MAX(0,P35+Q35-R35) | T35: =W34 | U35: =IF(T35>0.005,T35*Debts!D12/12,0) | V35: 0 | W35: =MAX(0,T35+U35-V35) | X35: =AA34 | Y35: =IF(X35>0.005,X35*Debts!D13/12,0) | Z35: 0 | AA35: =MAX(0,X35+Y35-Z35) | AB35: =AE34 | AC35: =IF(AB35>0.005,AB35*Debts!D14/12,0) | AD35: 0 | AE35: =MAX(0,AB35+AC35-AD35) | AF35: =AI34 | AG35: =IF(AF35>0.005,AF35*Debts!D15/12,0) | AH35: 0 | AI35: =MAX(0,AF35+AG35-AH35) | AJ35: =AM34 | AK35: =IF(AJ35>0.005,AJ35*Debts!D16/12,0) | AL35: 0 | AM35: =MAX(0,AJ35+AK35-AL35) | AN35: =AQ34 | AO35: =IF(AN35>0.005,AN35*Debts!D17/12,0) | AP35: 0 | AQ35: =MAX(0,AN35+AO35-AP35) | AR35: =AU34 | AS35: =IF(AR35>0.005,AR35*Debts!D18/12,0) | AT35: 0 | AU35: =MAX(0,AR35+AS35-AT35) | AV35: =AY34 | AW35: =IF(AV35>0.005,AV35*Debts!D19/12,0) | AX35: 0 | AY35: =MAX(0,AV35+AW35-AX35) | AZ35: =BC34 | BA35: =IF(AZ35>0.005,AZ35*Debts!D20/12,0) | BB35: 0 | BC35: =MAX(0,AZ35+BA35-BB35) | BD35: =BG34 | BE35: =IF(BD35>0.005,BD35*Debts!D21/12,0) | BF35: 0 | BG35: =MAX(0,BD35+BE35-BF35) | BH35: =BK34 | BI35: =IF(BH35>0.005,BH35*Debts!D22/12,0) | BJ35: 0 | BK35: =MAX(0,BH35+BI35-BJ35) | BL35: =BO34 | BM35: =IF(BL35>0.005,BL35*Debts!D23/12,0) | BN35: 0 | BO35: =MAX(0,BL35+BM35-BN35) | BP35: =BS34 | BQ35: =IF(BP35>0.005,BP35*Debts!D24/12,0) | BR35: 0 | BS35: =MAX(0,BP35+BQ35-BR35) | BT35: =BW34 | BU35: =IF(BT35>0.005,BT35*Debts!D25/12,0) | BV35: 0 | BW35: =MAX(0,BT35+BU35-BV35) | BX35: =CA34 | BY35: =IF(BX35>0.005,BX35*Debts!D26/12,0) | BZ35: 0 | CA35: =MAX(0,BX35+BY35-BZ35) | CB35: =CE34 | CC35: =IF(CB35>0.005,CB35*Debts!D27/12,0) | CD35: 0 | CE35: =MAX(0,CB35+CC35-CD35) | CF35: =G35+K35+O35+S35+W35+AA35+AE35+AI35+AM35+AQ35+AU35+AY35+BC35+BG35+BK35+BO35+BS35+BW35+CA35+CE35 | CG35: =E35+I35+M35+Q35+U35+Y35+AC35+AG35+AK35+AO35+AS35+AW35+BA35+BE35+BI35+BM35+BQ35+BU35+BY35+CC35 | CH35: =CH34+CG35
B36: 32 | C36: =F36+J36+N36+R36+V36+Z36+AD36+AH36+AL36+AP36+AT36+AX36+BB36+BF36+BJ36+BN36+BR36+BV36+BZ36+CD36 | D36: =G35 | E36: =IF(D36>0.005,D36*Debts!D8/12,0) | F36: 0 | G36: =MAX(0,D36+E36-F36) | H36: =K35 | I36: =IF(H36>0.005,H36*Debts!D9/12,0) | J36: 0 | K36: =MAX(0,H36+I36-J36) | L36: =O35 | M36: =IF(L36>0.005,L36*Debts!D10/12,0) | N36: 0 | O36: =MAX(0,L36+M36-N36) | P36: =S35 | Q36: =IF(P36>0.005,P36*Debts!D11/12,0) | R36: 0 | S36: =MAX(0,P36+Q36-R36) | T36: =W35 | U36: =IF(T36>0.005,T36*Debts!D12/12,0) | V36: 0 | W36: =MAX(0,T36+U36-V36) | X36: =AA35 | Y36: =IF(X36>0.005,X36*Debts!D13/12,0) | Z36: 0 | AA36: =MAX(0,X36+Y36-Z36) | AB36: =AE35 | AC36: =IF(AB36>0.005,AB36*Debts!D14/12,0) | AD36: 0 | AE36: =MAX(0,AB36+AC36-AD36) | AF36: =AI35 | AG36: =IF(AF36>0.005,AF36*Debts!D15/12,0) | AH36: 0 | AI36: =MAX(0,AF36+AG36-AH36) | AJ36: =AM35 | AK36: =IF(AJ36>0.005,AJ36*Debts!D16/12,0) | AL36: 0 | AM36: =MAX(0,AJ36+AK36-AL36) | AN36: =AQ35 | AO36: =IF(AN36>0.005,AN36*Debts!D17/12,0) | AP36: 0 | AQ36: =MAX(0,AN36+AO36-AP36) | AR36: =AU35 | AS36: =IF(AR36>0.005,AR36*Debts!D18/12,0) | AT36: 0 | AU36: =MAX(0,AR36+AS36-AT36) | AV36: =AY35 | AW36: =IF(AV36>0.005,AV36*Debts!D19/12,0) | AX36: 0 | AY36: =MAX(0,AV36+AW36-AX36) | AZ36: =BC35 | BA36: =IF(AZ36>0.005,AZ36*Debts!D20/12,0) | BB36: 0 | BC36: =MAX(0,AZ36+BA36-BB36) | BD36: =BG35 | BE36: =IF(BD36>0.005,BD36*Debts!D21/12,0) | BF36: 0 | BG36: =MAX(0,BD36+BE36-BF36) | BH36: =BK35 | BI36: =IF(BH36>0.005,BH36*Debts!D22/12,0) | BJ36: 0 | BK36: =MAX(0,BH36+BI36-BJ36) | BL36: =BO35 | BM36: =IF(BL36>0.005,BL36*Debts!D23/12,0) | BN36: 0 | BO36: =MAX(0,BL36+BM36-BN36) | BP36: =BS35 | BQ36: =IF(BP36>0.005,BP36*Debts!D24/12,0) | BR36: 0 | BS36: =MAX(0,BP36+BQ36-BR36) | BT36: =BW35 | BU36: =IF(BT36>0.005,BT36*Debts!D25/12,0) | BV36: 0 | BW36: =MAX(0,BT36+BU36-BV36) | BX36: =CA35 | BY36: =IF(BX36>0.005,BX36*Debts!D26/12,0) | BZ36: 0 | CA36: =MAX(0,BX36+BY36-BZ36) | CB36: =CE35 | CC36: =IF(CB36>0.005,CB36*Debts!D27/12,0) | CD36: 0 | CE36: =MAX(0,CB36+CC36-CD36) | CF36: =G36+K36+O36+S36+W36+AA36+AE36+AI36+AM36+AQ36+AU36+AY36+BC36+BG36+BK36+BO36+BS36+BW36+CA36+CE36 | CG36: =E36+I36+M36+Q36+U36+Y36+AC36+AG36+AK36+AO36+AS36+AW36+BA36+BE36+BI36+BM36+BQ36+BU36+BY36+CC36 | CH36: =CH35+CG36
B37: 33 | C37: =F37+J37+N37+R37+V37+Z37+AD37+AH37+AL37+AP37+AT37+AX37+BB37+BF37+BJ37+BN37+BR37+BV37+BZ37+CD37 | D37: =G36 | E37: =IF(D37>0.005,D37*Debts!D8/12,0) | F37: 0 | G37: =MAX(0,D37+E37-F37) | H37: =K36 | I37: =IF(H37>0.005,H37*Debts!D9/12,0) | J37: 0 | K37: =MAX(0,H37+I37-J37) | L37: =O36 | M37: =IF(L37>0.005,L37*Debts!D10/12,0) | N37: 0 | O37: =MAX(0,L37+M37-N37) | P37: =S36 | Q37: =IF(P37>0.005,P37*Debts!D11/12,0) | R37: 0 | S37: =MAX(0,P37+Q37-R37) | T37: =W36 | U37: =IF(T37>0.005,T37*Debts!D12/12,0) | V37: 0 | W37: =MAX(0,T37+U37-V37) | X37: =AA36 | Y37: =IF(X37>0.005,X37*Debts!D13/12,0) | Z37: 0 | AA37: =MAX(0,X37+Y37-Z37) | AB37: =AE36 | AC37: =IF(AB37>0.005,AB37*Debts!D14/12,0) | AD37: 0 | AE37: =MAX(0,AB37+AC37-AD37) | AF37: =AI36 | AG37: =IF(AF37>0.005,AF37*Debts!D15/12,0) | AH37: 0 | AI37: =MAX(0,AF37+AG37-AH37) | AJ37: =AM36 | AK37: =IF(AJ37>0.005,AJ37*Debts!D16/12,0) | AL37: 0 | AM37: =MAX(0,AJ37+AK37-AL37) | AN37: =AQ36 | AO37: =IF(AN37>0.005,AN37*Debts!D17/12,0) | AP37: 0 | AQ37: =MAX(0,AN37+AO37-AP37) | AR37: =AU36 | AS37: =IF(AR37>0.005,AR37*Debts!D18/12,0) | AT37: 0 | AU37: =MAX(0,AR37+AS37-AT37) | AV37: =AY36 | AW37: =IF(AV37>0.005,AV37*Debts!D19/12,0) | AX37: 0 | AY37: =MAX(0,AV37+AW37-AX37) | AZ37: =BC36 | BA37: =IF(AZ37>0.005,AZ37*Debts!D20/12,0) | BB37: 0 | BC37: =MAX(0,AZ37+BA37-BB37) | BD37: =BG36 | BE37: =IF(BD37>0.005,BD37*Debts!D21/12,0) | BF37: 0 | BG37: =MAX(0,BD37+BE37-BF37) | BH37: =BK36 | BI37: =IF(BH37>0.005,BH37*Debts!D22/12,0) | BJ37: 0 | BK37: =MAX(0,BH37+BI37-BJ37) | BL37: =BO36 | BM37: =IF(BL37>0.005,BL37*Debts!D23/12,0) | BN37: 0 | BO37: =MAX(0,BL37+BM37-BN37) | BP37: =BS36 | BQ37: =IF(BP37>0.005,BP37*Debts!D24/12,0) | BR37: 0 | BS37: =MAX(0,BP37+BQ37-BR37) | BT37: =BW36 | BU37: =IF(BT37>0.005,BT37*Debts!D25/12,0) | BV37: 0 | BW37: =MAX(0,BT37+BU37-BV37) | BX37: =CA36 | BY37: =IF(BX37>0.005,BX37*Debts!D26/12,0) | BZ37: 0 | CA37: =MAX(0,BX37+BY37-BZ37) | CB37: =CE36 | CC37: =IF(CB37>0.005,CB37*Debts!D27/12,0) | CD37: 0 | CE37: =MAX(0,CB37+CC37-CD37) | CF37: =G37+K37+O37+S37+W37+AA37+AE37+AI37+AM37+AQ37+AU37+AY37+BC37+BG37+BK37+BO37+BS37+BW37+CA37+CE37 | CG37: =E37+I37+M37+Q37+U37+Y37+AC37+AG37+AK37+AO37+AS37+AW37+BA37+BE37+BI37+BM37+BQ37+BU37+BY37+CC37 | CH37: =CH36+CG37
B38: 34 | C38: =F38+J38+N38+R38+V38+Z38+AD38+AH38+AL38+AP38+AT38+AX38+BB38+BF38+BJ38+BN38+BR38+BV38+BZ38+CD38 | D38: =G37 | E38: =IF(D38>0.005,D38*Debts!D8/12,0) | F38: 0 | G38: =MAX(0,D38+E38-F38) | H38: =K37 | I38: =IF(H38>0.005,H38*Debts!D9/12,0) | J38: 0 | K38: =MAX(0,H38+I38-J38) | L38: =O37 | M38: =IF(L38>0.005,L38*Debts!D10/12,0) | N38: 0 | O38: =MAX(0,L38+M38-N38) | P38: =S37 | Q38: =IF(P38>0.005,P38*Debts!D11/12,0) | R38: 0 | S38: =MAX(0,P38+Q38-R38) | T38: =W37 | U38: =IF(T38>0.005,T38*Debts!D12/12,0) | V38: 0 | W38: =MAX(0,T38+U38-V38) | X38: =AA37 | Y38: =IF(X38>0.005,X38*Debts!D13/12,0) | Z38: 0 | AA38: =MAX(0,X38+Y38-Z38) | AB38: =AE37 | AC38: =IF(AB38>0.005,AB38*Debts!D14/12,0) | AD38: 0 | AE38: =MAX(0,AB38+AC38-AD38) | AF38: =AI37 | AG38: =IF(AF38>0.005,AF38*Debts!D15/12,0) | AH38: 0 | AI38: =MAX(0,AF38+AG38-AH38) | AJ38: =AM37 | AK38: =IF(AJ38>0.005,AJ38*Debts!D16/12,0) | AL38: 0 | AM38: =MAX(0,AJ38+AK38-AL38) | AN38: =AQ37 | AO38: =IF(AN38>0.005,AN38*Debts!D17/12,0) | AP38: 0 | AQ38: =MAX(0,AN38+AO38-AP38) | AR38: =AU37 | AS38: =IF(AR38>0.005,AR38*Debts!D18/12,0) | AT38: 0 | AU38: =MAX(0,AR38+AS38-AT38) | AV38: =AY37 | AW38: =IF(AV38>0.005,AV38*Debts!D19/12,0) | AX38: 0 | AY38: =MAX(0,AV38+AW38-AX38) | AZ38: =BC37 | BA38: =IF(AZ38>0.005,AZ38*Debts!D20/12,0) | BB38: 0 | BC38: =MAX(0,AZ38+BA38-BB38) | BD38: =BG37 | BE38: =IF(BD38>0.005,BD38*Debts!D21/12,0) | BF38: 0 | BG38: =MAX(0,BD38+BE38-BF38) | BH38: =BK37 | BI38: =IF(BH38>0.005,BH38*Debts!D22/12,0) | BJ38: 0 | BK38: =MAX(0,BH38+BI38-BJ38) | BL38: =BO37 | BM38: =IF(BL38>0.005,BL38*Debts!D23/12,0) | BN38: 0 | BO38: =MAX(0,BL38+BM38-BN38) | BP38: =BS37 | BQ38: =IF(BP38>0.005,BP38*Debts!D24/12,0) | BR38: 0 | BS38: =MAX(0,BP38+BQ38-BR38) | BT38: =BW37 | BU38: =IF(BT38>0.005,BT38*Debts!D25/12,0) | BV38: 0 | BW38: =MAX(0,BT38+BU38-BV38) | BX38: =CA37 | BY38: =IF(BX38>0.005,BX38*Debts!D26/12,0) | BZ38: 0 | CA38: =MAX(0,BX38+BY38-BZ38) | CB38: =CE37 | CC38: =IF(CB38>0.005,CB38*Debts!D27/12,0) | CD38: 0 | CE38: =MAX(0,CB38+CC38-CD38) | CF38: =G38+K38+O38+S38+W38+AA38+AE38+AI38+AM38+AQ38+AU38+AY38+BC38+BG38+BK38+BO38+BS38+BW38+CA38+CE38 | CG38: =E38+I38+M38+Q38+U38+Y38+AC38+AG38+AK38+AO38+AS38+AW38+BA38+BE38+BI38+BM38+BQ38+BU38+BY38+CC38 | CH38: =CH37+CG38
B39: 35 | C39: =F39+J39+N39+R39+V39+Z39+AD39+AH39+AL39+AP39+AT39+AX39+BB39+BF39+BJ39+BN39+BR39+BV39+BZ39+CD39 | D39: =G38 | E39: =IF(D39>0.005,D39*Debts!D8/12,0) | F39: 0 | G39: =MAX(0,D39+E39-F39) | H39: =K38 | I39: =IF(H39>0.005,H39*Debts!D9/12,0) | J39: 0 | K39: =MAX(0,H39+I39-J39) | L39: =O38 | M39: =IF(L39>0.005,L39*Debts!D10/12,0) | N39: 0 | O39: =MAX(0,L39+M39-N39) | P39: =S38 | Q39: =IF(P39>0.005,P39*Debts!D11/12,0) | R39: 0 | S39: =MAX(0,P39+Q39-R39) | T39: =W38 | U39: =IF(T39>0.005,T39*Debts!D12/12,0) | V39: 0 | W39: =MAX(0,T39+U39-V39) | X39: =AA38 | Y39: =IF(X39>0.005,X39*Debts!D13/12,0) | Z39: 0 | AA39: =MAX(0,X39+Y39-Z39) | AB39: =AE38 | AC39: =IF(AB39>0.005,AB39*Debts!D14/12,0) | AD39: 0 | AE39: =MAX(0,AB39+AC39-AD39) | AF39: =AI38 | AG39: =IF(AF39>0.005,AF39*Debts!D15/12,0) | AH39: 0 | AI39: =MAX(0,AF39+AG39-AH39) | AJ39: =AM38 | AK39: =IF(AJ39>0.005,AJ39*Debts!D16/12,0) | AL39: 0 | AM39: =MAX(0,AJ39+AK39-AL39) | AN39: =AQ38 | AO39: =IF(AN39>0.005,AN39*Debts!D17/12,0) | AP39: 0 | AQ39: =MAX(0,AN39+AO39-AP39) | AR39: =AU38 | AS39: =IF(AR39>0.005,AR39*Debts!D18/12,0) | AT39: 0 | AU39: =MAX(0,AR39+AS39-AT39) | AV39: =AY38 | AW39: =IF(AV39>0.005,AV39*Debts!D19/12,0) | AX39: 0 | AY39: =MAX(0,AV39+AW39-AX39) | AZ39: =BC38 | BA39: =IF(AZ39>0.005,AZ39*Debts!D20/12,0) | BB39: 0 | BC39: =MAX(0,AZ39+BA39-BB39) | BD39: =BG38 | BE39: =IF(BD39>0.005,BD39*Debts!D21/12,0) | BF39: 0 | BG39: =MAX(0,BD39+BE39-BF39) | BH39: =BK38 | BI39: =IF(BH39>0.005,BH39*Debts!D22/12,0) | BJ39: 0 | BK39: =MAX(0,BH39+BI39-BJ39) | BL39: =BO38 | BM39: =IF(BL39>0.005,BL39*Debts!D23/12,0) | BN39: 0 | BO39: =MAX(0,BL39+BM39-BN39) | BP39: =BS38 | BQ39: =IF(BP39>0.005,BP39*Debts!D24/12,0) | BR39: 0 | BS39: =MAX(0,BP39+BQ39-BR39) | BT39: =BW38 | BU39: =IF(BT39>0.005,BT39*Debts!D25/12,0) | BV39: 0 | BW39: =MAX(0,BT39+BU39-BV39) | BX39: =CA38 | BY39: =IF(BX39>0.005,BX39*Debts!D26/12,0) | BZ39: 0 | CA39: =MAX(0,BX39+BY39-BZ39) | CB39: =CE38 | CC39: =IF(CB39>0.005,CB39*Debts!D27/12,0) | CD39: 0 | CE39: =MAX(0,CB39+CC39-CD39) | CF39: =G39+K39+O39+S39+W39+AA39+AE39+AI39+AM39+AQ39+AU39+AY39+BC39+BG39+BK39+BO39+BS39+BW39+CA39+CE39 | CG39: =E39+I39+M39+Q39+U39+Y39+AC39+AG39+AK39+AO39+AS39+AW39+BA39+BE39+BI39+BM39+BQ39+BU39+BY39+CC39 | CH39: =CH38+CG39
B40: 36 | C40: =F40+J40+N40+R40+V40+Z40+AD40+AH40+AL40+AP40+AT40+AX40+BB40+BF40+BJ40+BN40+BR40+BV40+BZ40+CD40 | D40: =G39 | E40: =IF(D40>0.005,D40*Debts!D8/12,0) | F40: 0 | G40: =MAX(0,D40+E40-F40) | H40: =K39 | I40: =IF(H40>0.005,H40*Debts!D9/12,0) | J40: 0 | K40: =MAX(0,H40+I40-J40) | L40: =O39 | M40: =IF(L40>0.005,L40*Debts!D10/12,0) | N40: 0 | O40: =MAX(0,L40+M40-N40) | P40: =S39 | Q40: =IF(P40>0.005,P40*Debts!D11/12,0) | R40: 0 | S40: =MAX(0,P40+Q40-R40) | T40: =W39 | U40: =IF(T40>0.005,T40*Debts!D12/12,0) | V40: 0 | W40: =MAX(0,T40+U40-V40) | X40: =AA39 | Y40: =IF(X40>0.005,X40*Debts!D13/12,0) | Z40: 0 | AA40: =MAX(0,X40+Y40-Z40) | AB40: =AE39 | AC40: =IF(AB40>0.005,AB40*Debts!D14/12,0) | AD40: 0 | AE40: =MAX(0,AB40+AC40-AD40) | AF40: =AI39 | AG40: =IF(AF40>0.005,AF40*Debts!D15/12,0) | AH40: 0 | AI40: =MAX(0,AF40+AG40-AH40) | AJ40: =AM39 | AK40: =IF(AJ40>0.005,AJ40*Debts!D16/12,0) | AL40: 0 | AM40: =MAX(0,AJ40+AK40-AL40) | AN40: =AQ39 | AO40: =IF(AN40>0.005,AN40*Debts!D17/12,0) | AP40: 0 | AQ40: =MAX(0,AN40+AO40-AP40) | AR40: =AU39 | AS40: =IF(AR40>0.005,AR40*Debts!D18/12,0) | AT40: 0 | AU40: =MAX(0,AR40+AS40-AT40) | AV40: =AY39 | AW40: =IF(AV40>0.005,AV40*Debts!D19/12,0) | AX40: 0 | AY40: =MAX(0,AV40+AW40-AX40) | AZ40: =BC39 | BA40: =IF(AZ40>0.005,AZ40*Debts!D20/12,0) | BB40: 0 | BC40: =MAX(0,AZ40+BA40-BB40) | BD40: =BG39 | BE40: =IF(BD40>0.005,BD40*Debts!D21/12,0) | BF40: 0 | BG40: =MAX(0,BD40+BE40-BF40) | BH40: =BK39 | BI40: =IF(BH40>0.005,BH40*Debts!D22/12,0) | BJ40: 0 | BK40: =MAX(0,BH40+BI40-BJ40) | BL40: =BO39 | BM40: =IF(BL40>0.005,BL40*Debts!D23/12,0) | BN40: 0 | BO40: =MAX(0,BL40+BM40-BN40) | BP40: =BS39 | BQ40: =IF(BP40>0.005,BP40*Debts!D24/12,0) | BR40: 0 | BS40: =MAX(0,BP40+BQ40-BR40) | BT40: =BW39 | BU40: =IF(BT40>0.005,BT40*Debts!D25/12,0) | BV40: 0 | BW40: =MAX(0,BT40+BU40-BV40) | BX40: =CA39 | BY40: =IF(BX40>0.005,BX40*Debts!D26/12,0) | BZ40: 0 | CA40: =MAX(0,BX40+BY40-BZ40) | CB40: =CE39 | CC40: =IF(CB40>0.005,CB40*Debts!D27/12,0) | CD40: 0 | CE40: =MAX(0,CB40+CC40-CD40) | CF40: =G40+K40+O40+S40+W40+AA40+AE40+AI40+AM40+AQ40+AU40+AY40+BC40+BG40+BK40+BO40+BS40+BW40+CA40+CE40 | CG40: =E40+I40+M40+Q40+U40+Y40+AC40+AG40+AK40+AO40+AS40+AW40+BA40+BE40+BI40+BM40+BQ40+BU40+BY40+CC40 | CH40: =CH39+CG40
B41: 37 | C41: =F41+J41+N41+R41+V41+Z41+AD41+AH41+AL41+AP41+AT41+AX41+BB41+BF41+BJ41+BN41+BR41+BV41+BZ41+CD41 | D41: =G40 | E41: =IF(D41>0.005,D41*Debts!D8/12,0) | F41: 0 | G41: =MAX(0,D41+E41-F41) | H41: =K40 | I41: =IF(H41>0.005,H41*Debts!D9/12,0) | J41: 0 | K41: =MAX(0,H41+I41-J41) | L41: =O40 | M41: =IF(L41>0.005,L41*Debts!D10/12,0) | N41: 0 | O41: =MAX(0,L41+M41-N41) | P41: =S40 | Q41: =IF(P41>0.005,P41*Debts!D11/12,0) | R41: 0 | S41: =MAX(0,P41+Q41-R41) | T41: =W40 | U41: =IF(T41>0.005,T41*Debts!D12/12,0) | V41: 0 | W41: =MAX(0,T41+U41-V41) | X41: =AA40 | Y41: =IF(X41>0.005,X41*Debts!D13/12,0) | Z41: 0 | AA41: =MAX(0,X41+Y41-Z41) | AB41: =AE40 | AC41: =IF(AB41>0.005,AB41*Debts!D14/12,0) | AD41: 0 | AE41: =MAX(0,AB41+AC41-AD41) | AF41: =AI40 | AG41: =IF(AF41>0.005,AF41*Debts!D15/12,0) | AH41: 0 | AI41: =MAX(0,AF41+AG41-AH41) | AJ41: =AM40 | AK41: =IF(AJ41>0.005,AJ41*Debts!D16/12,0) | AL41: 0 | AM41: =MAX(0,AJ41+AK41-AL41) | AN41: =AQ40 | AO41: =IF(AN41>0.005,AN41*Debts!D17/12,0) | AP41: 0 | AQ41: =MAX(0,AN41+AO41-AP41) | AR41: =AU40 | AS41: =IF(AR41>0.005,AR41*Debts!D18/12,0) | AT41: 0 | AU41: =MAX(0,AR41+AS41-AT41) | AV41: =AY40 | AW41: =IF(AV41>0.005,AV41*Debts!D19/12,0) | AX41: 0 | AY41: =MAX(0,AV41+AW41-AX41) | AZ41: =BC40 | BA41: =IF(AZ41>0.005,AZ41*Debts!D20/12,0) | BB41: 0 | BC41: =MAX(0,AZ41+BA41-BB41) | BD41: =BG40 | BE41: =IF(BD41>0.005,BD41*Debts!D21/12,0) | BF41: 0 | BG41: =MAX(0,BD41+BE41-BF41) | BH41: =BK40 | BI41: =IF(BH41>0.005,BH41*Debts!D22/12,0) | BJ41: 0 | BK41: =MAX(0,BH41+BI41-BJ41) | BL41: =BO40 | BM41: =IF(BL41>0.005,BL41*Debts!D23/12,0) | BN41: 0 | BO41: =MAX(0,BL41+BM41-BN41) | BP41: =BS40 | BQ41: =IF(BP41>0.005,BP41*Debts!D24/12,0) | BR41: 0 | BS41: =MAX(0,BP41+BQ41-BR41) | BT41: =BW40 | BU41: =IF(BT41>0.005,BT41*Debts!D25/12,0) | BV41: 0 | BW41: =MAX(0,BT41+BU41-BV41) | BX41: =CA40 | BY41: =IF(BX41>0.005,BX41*Debts!D26/12,0) | BZ41: 0 | CA41: =MAX(0,BX41+BY41-BZ41) | CB41: =CE40 | CC41: =IF(CB41>0.005,CB41*Debts!D27/12,0) | CD41: 0 | CE41: =MAX(0,CB41+CC41-CD41) | CF41: =G41+K41+O41+S41+W41+AA41+AE41+AI41+AM41+AQ41+AU41+AY41+BC41+BG41+BK41+BO41+BS41+BW41+CA41+CE41 | CG41: =E41+I41+M41+Q41+U41+Y41+AC41+AG41+AK41+AO41+AS41+AW41+BA41+BE41+BI41+BM41+BQ41+BU41+BY41+CC41 | CH41: =CH40+CG41
B42: 38 | C42: =F42+J42+N42+R42+V42+Z42+AD42+AH42+AL42+AP42+AT42+AX42+BB42+BF42+BJ42+BN42+BR42+BV42+BZ42+CD42 | D42: =G41 | E42: =IF(D42>0.005,D42*Debts!D8/12,0) | F42: 0 | G42: =MAX(0,D42+E42-F42) | H42: =K41 | I42: =IF(H42>0.005,H42*Debts!D9/12,0) | J42: 0 | K42: =MAX(0,H42+I42-J42) | L42: =O41 | M42: =IF(L42>0.005,L42*Debts!D10/12,0) | N42: 0 | O42: =MAX(0,L42+M42-N42) | P42: =S41 | Q42: =IF(P42>0.005,P42*Debts!D11/12,0) | R42: 0 | S42: =MAX(0,P42+Q42-R42) | T42: =W41 | U42: =IF(T42>0.005,T42*Debts!D12/12,0) | V42: 0 | W42: =MAX(0,T42+U42-V42) | X42: =AA41 | Y42: =IF(X42>0.005,X42*Debts!D13/12,0) | Z42: 0 | AA42: =MAX(0,X42+Y42-Z42) | AB42: =AE41 | AC42: =IF(AB42>0.005,AB42*Debts!D14/12,0) | AD42: 0 | AE42: =MAX(0,AB42+AC42-AD42) | AF42: =AI41 | AG42: =IF(AF42>0.005,AF42*Debts!D15/12,0) | AH42: 0 | AI42: =MAX(0,AF42+AG42-AH42) | AJ42: =AM41 | AK42: =IF(AJ42>0.005,AJ42*Debts!D16/12,0) | AL42: 0 | AM42: =MAX(0,AJ42+AK42-AL42) | AN42: =AQ41 | AO42: =IF(AN42>0.005,AN42*Debts!D17/12,0) | AP42: 0 | AQ42: =MAX(0,AN42+AO42-AP42) | AR42: =AU41 | AS42: =IF(AR42>0.005,AR42*Debts!D18/12,0) | AT42: 0 | AU42: =MAX(0,AR42+AS42-AT42) | AV42: =AY41 | AW42: =IF(AV42>0.005,AV42*Debts!D19/12,0) | AX42: 0 | AY42: =MAX(0,AV42+AW42-AX42) | AZ42: =BC41 | BA42: =IF(AZ42>0.005,AZ42*Debts!D20/12,0) | BB42: 0 | BC42: =MAX(0,AZ42+BA42-BB42) | BD42: =BG41 | BE42: =IF(BD42>0.005,BD42*Debts!D21/12,0) | BF42: 0 | BG42: =MAX(0,BD42+BE42-BF42) | BH42: =BK41 | BI42: =IF(BH42>0.005,BH42*Debts!D22/12,0) | BJ42: 0 | BK42: =MAX(0,BH42+BI42-BJ42) | BL42: =BO41 | BM42: =IF(BL42>0.005,BL42*Debts!D23/12,0) | BN42: 0 | BO42: =MAX(0,BL42+BM42-BN42) | BP42: =BS41 | BQ42: =IF(BP42>0.005,BP42*Debts!D24/12,0) | BR42: 0 | BS42: =MAX(0,BP42+BQ42-BR42) | BT42: =BW41 | BU42: =IF(BT42>0.005,BT42*Debts!D25/12,0) | BV42: 0 | BW42: =MAX(0,BT42+BU42-BV42) | BX42: =CA41 | BY42: =IF(BX42>0.005,BX42*Debts!D26/12,0) | BZ42: 0 | CA42: =MAX(0,BX42+BY42-BZ42) | CB42: =CE41 | CC42: =IF(CB42>0.005,CB42*Debts!D27/12,0) | CD42: 0 | CE42: =MAX(0,CB42+CC42-CD42) | CF42: =G42+K42+O42+S42+W42+AA42+AE42+AI42+AM42+AQ42+AU42+AY42+BC42+BG42+BK42+BO42+BS42+BW42+CA42+CE42 | CG42: =E42+I42+M42+Q42+U42+Y42+AC42+AG42+AK42+AO42+AS42+AW42+BA42+BE42+BI42+BM42+BQ42+BU42+BY42+CC42 | CH42: =CH41+CG42
B43: 39 | C43: =F43+J43+N43+R43+V43+Z43+AD43+AH43+AL43+AP43+AT43+AX43+BB43+BF43+BJ43+BN43+BR43+BV43+BZ43+CD43 | D43: =G42 | E43: =IF(D43>0.005,D43*Debts!D8/12,0) | F43: 0 | G43: =MAX(0,D43+E43-F43) | H43: =K42 | I43: =IF(H43>0.005,H43*Debts!D9/12,0) | J43: 0 | K43: =MAX(0,H43+I43-J43) | L43: =O42 | M43: =IF(L43>0.005,L43*Debts!D10/12,0) | N43: 0 | O43: =MAX(0,L43+M43-N43) | P43: =S42 | Q43: =IF(P43>0.005,P43*Debts!D11/12,0) | R43: 0 | S43: =MAX(0,P43+Q43-R43) | T43: =W42 | U43: =IF(T43>0.005,T43*Debts!D12/12,0) | V43: 0 | W43: =MAX(0,T43+U43-V43) | X43: =AA42 | Y43: =IF(X43>0.005,X43*Debts!D13/12,0) | Z43: 0 | AA43: =MAX(0,X43+Y43-Z43) | AB43: =AE42 | AC43: =IF(AB43>0.005,AB43*Debts!D14/12,0) | AD43: 0 | AE43: =MAX(0,AB43+AC43-AD43) | AF43: =AI42 | AG43: =IF(AF43>0.005,AF43*Debts!D15/12,0) | AH43: 0 | AI43: =MAX(0,AF43+AG43-AH43) | AJ43: =AM42 | AK43: =IF(AJ43>0.005,AJ43*Debts!D16/12,0) | AL43: 0 | AM43: =MAX(0,AJ43+AK43-AL43) | AN43: =AQ42 | AO43: =IF(AN43>0.005,AN43*Debts!D17/12,0) | AP43: 0 | AQ43: =MAX(0,AN43+AO43-AP43) | AR43: =AU42 | AS43: =IF(AR43>0.005,AR43*Debts!D18/12,0) | AT43: 0 | AU43: =MAX(0,AR43+AS43-AT43) | AV43: =AY42 | AW43: =IF(AV43>0.005,AV43*Debts!D19/12,0) | AX43: 0 | AY43: =MAX(0,AV43+AW43-AX43) | AZ43: =BC42 | BA43: =IF(AZ43>0.005,AZ43*Debts!D20/12,0) | BB43: 0 | BC43: =MAX(0,AZ43+BA43-BB43) | BD43: =BG42 | BE43: =IF(BD43>0.005,BD43*Debts!D21/12,0) | BF43: 0 | BG43: =MAX(0,BD43+BE43-BF43) | BH43: =BK42 | BI43: =IF(BH43>0.005,BH43*Debts!D22/12,0) | BJ43: 0 | BK43: =MAX(0,BH43+BI43-BJ43) | BL43: =BO42 | BM43: =IF(BL43>0.005,BL43*Debts!D23/12,0) | BN43: 0 | BO43: =MAX(0,BL43+BM43-BN43) | BP43: =BS42 | BQ43: =IF(BP43>0.005,BP43*Debts!D24/12,0) | BR43: 0 | BS43: =MAX(0,BP43+BQ43-BR43) | BT43: =BW42 | BU43: =IF(BT43>0.005,BT43*Debts!D25/12,0) | BV43: 0 | BW43: =MAX(0,BT43+BU43-BV43) | BX43: =CA42 | BY43: =IF(BX43>0.005,BX43*Debts!D26/12,0) | BZ43: 0 | CA43: =MAX(0,BX43+BY43-BZ43) | CB43: =CE42 | CC43: =IF(CB43>0.005,CB43*Debts!D27/12,0) | CD43: 0 | CE43: =MAX(0,CB43+CC43-CD43) | CF43: =G43+K43+O43+S43+W43+AA43+AE43+AI43+AM43+AQ43+AU43+AY43+BC43+BG43+BK43+BO43+BS43+BW43+CA43+CE43 | CG43: =E43+I43+M43+Q43+U43+Y43+AC43+AG43+AK43+AO43+AS43+AW43+BA43+BE43+BI43+BM43+BQ43+BU43+BY43+CC43 | CH43: =CH42+CG43
B44: 40 | C44: =F44+J44+N44+R44+V44+Z44+AD44+AH44+AL44+AP44+AT44+AX44+BB44+BF44+BJ44+BN44+BR44+BV44+BZ44+CD44 | D44: =G43 | E44: =IF(D44>0.005,D44*Debts!D8/12,0) | F44: 0 | G44: =MAX(0,D44+E44-F44) | H44: =K43 | I44: =IF(H44>0.005,H44*Debts!D9/12,0) | J44: 0 | K44: =MAX(0,H44+I44-J44) | L44: =O43 | M44: =IF(L44>0.005,L44*Debts!D10/12,0) | N44: 0 | O44: =MAX(0,L44+M44-N44) | P44: =S43 | Q44: =IF(P44>0.005,P44*Debts!D11/12,0) | R44: 0 | S44: =MAX(0,P44+Q44-R44) | T44: =W43 | U44: =IF(T44>0.005,T44*Debts!D12/12,0) | V44: 0 | W44: =MAX(0,T44+U44-V44) | X44: =AA43 | Y44: =IF(X44>0.005,X44*Debts!D13/12,0) | Z44: 0 | AA44: =MAX(0,X44+Y44-Z44) | AB44: =AE43 | AC44: =IF(AB44>0.005,AB44*Debts!D14/12,0) | AD44: 0 | AE44: =MAX(0,AB44+AC44-AD44) | AF44: =AI43 | AG44: =IF(AF44>0.005,AF44*Debts!D15/12,0) | AH44: 0 | AI44: =MAX(0,AF44+AG44-AH44) | AJ44: =AM43 | AK44: =IF(AJ44>0.005,AJ44*Debts!D16/12,0) | AL44: 0 | AM44: =MAX(0,AJ44+AK44-AL44) | AN44: =AQ43 | AO44: =IF(AN44>0.005,AN44*Debts!D17/12,0) | AP44: 0 | AQ44: =MAX(0,AN44+AO44-AP44) | AR44: =AU43 | AS44: =IF(AR44>0.005,AR44*Debts!D18/12,0) | AT44: 0 | AU44: =MAX(0,AR44+AS44-AT44) | AV44: =AY43 | AW44: =IF(AV44>0.005,AV44*Debts!D19/12,0) | AX44: 0 | AY44: =MAX(0,AV44+AW44-AX44) | AZ44: =BC43 | BA44: =IF(AZ44>0.005,AZ44*Debts!D20/12,0) | BB44: 0 | BC44: =MAX(0,AZ44+BA44-BB44) | BD44: =BG43 | BE44: =IF(BD44>0.005,BD44*Debts!D21/12,0) | BF44: 0 | BG44: =MAX(0,BD44+BE44-BF44) | BH44: =BK43 | BI44: =IF(BH44>0.005,BH44*Debts!D22/12,0) | BJ44: 0 | BK44: =MAX(0,BH44+BI44-BJ44) | BL44: =BO43 | BM44: =IF(BL44>0.005,BL44*Debts!D23/12,0) | BN44: 0 | BO44: =MAX(0,BL44+BM44-BN44) | BP44: =BS43 | BQ44: =IF(BP44>0.005,BP44*Debts!D24/12,0) | BR44: 0 | BS44: =MAX(0,BP44+BQ44-BR44) | BT44: =BW43 | BU44: =IF(BT44>0.005,BT44*Debts!D25/12,0) | BV44: 0 | BW44: =MAX(0,BT44+BU44-BV44) | BX44: =CA43 | BY44: =IF(BX44>0.005,BX44*Debts!D26/12,0) | BZ44: 0 | CA44: =MAX(0,BX44+BY44-BZ44) | CB44: =CE43 | CC44: =IF(CB44>0.005,CB44*Debts!D27/12,0) | CD44: 0 | CE44: =MAX(0,CB44+CC44-CD44) | CF44: =G44+K44+O44+S44+W44+AA44+AE44+AI44+AM44+AQ44+AU44+AY44+BC44+BG44+BK44+BO44+BS44+BW44+CA44+CE44 | CG44: =E44+I44+M44+Q44+U44+Y44+AC44+AG44+AK44+AO44+AS44+AW44+BA44+BE44+BI44+BM44+BQ44+BU44+BY44+CC44 | CH44: =CH43+CG44
B45: 41 | C45: =F45+J45+N45+R45+V45+Z45+AD45+AH45+AL45+AP45+AT45+AX45+BB45+BF45+BJ45+BN45+BR45+BV45+BZ45+CD45 | D45: =G44 | E45: =IF(D45>0.005,D45*Debts!D8/12,0) | F45: 0 | G45: =MAX(0,D45+E45-F45) | H45: =K44 | I45: =IF(H45>0.005,H45*Debts!D9/12,0) | J45: 0 | K45: =MAX(0,H45+I45-J45) | L45: =O44 | M45: =IF(L45>0.005,L45*Debts!D10/12,0) | N45: 0 | O45: =MAX(0,L45+M45-N45) | P45: =S44 | Q45: =IF(P45>0.005,P45*Debts!D11/12,0) | R45: 0 | S45: =MAX(0,P45+Q45-R45) | T45: =W44 | U45: =IF(T45>0.005,T45*Debts!D12/12,0) | V45: 0 | W45: =MAX(0,T45+U45-V45) | X45: =AA44 | Y45: =IF(X45>0.005,X45*Debts!D13/12,0) | Z45: 0 | AA45: =MAX(0,X45+Y45-Z45) | AB45: =AE44 | AC45: =IF(AB45>0.005,AB45*Debts!D14/12,0) | AD45: 0 | AE45: =MAX(0,AB45+AC45-AD45) | AF45: =AI44 | AG45: =IF(AF45>0.005,AF45*Debts!D15/12,0) | AH45: 0 | AI45: =MAX(0,AF45+AG45-AH45) | AJ45: =AM44 | AK45: =IF(AJ45>0.005,AJ45*Debts!D16/12,0) | AL45: 0 | AM45: =MAX(0,AJ45+AK45-AL45) | AN45: =AQ44 | AO45: =IF(AN45>0.005,AN45*Debts!D17/12,0) | AP45: 0 | AQ45: =MAX(0,AN45+AO45-AP45) | AR45: =AU44 | AS45: =IF(AR45>0.005,AR45*Debts!D18/12,0) | AT45: 0 | AU45: =MAX(0,AR45+AS45-AT45) | AV45: =AY44 | AW45: =IF(AV45>0.005,AV45*Debts!D19/12,0) | AX45: 0 | AY45: =MAX(0,AV45+AW45-AX45) | AZ45: =BC44 | BA45: =IF(AZ45>0.005,AZ45*Debts!D20/12,0) | BB45: 0 | BC45: =MAX(0,AZ45+BA45-BB45) | BD45: =BG44 | BE45: =IF(BD45>0.005,BD45*Debts!D21/12,0) | BF45: 0 | BG45: =MAX(0,BD45+BE45-BF45) | BH45: =BK44 | BI45: =IF(BH45>0.005,BH45*Debts!D22/12,0) | BJ45: 0 | BK45: =MAX(0,BH45+BI45-BJ45) | BL45: =BO44 | BM45: =IF(BL45>0.005,BL45*Debts!D23/12,0) | BN45: 0 | BO45: =MAX(0,BL45+BM45-BN45) | BP45: =BS44 | BQ45: =IF(BP45>0.005,BP45*Debts!D24/12,0) | BR45: 0 | BS45: =MAX(0,BP45+BQ45-BR45) | BT45: =BW44 | BU45: =IF(BT45>0.005,BT45*Debts!D25/12,0) | BV45: 0 | BW45: =MAX(0,BT45+BU45-BV45) | BX45: =CA44 | BY45: =IF(BX45>0.005,BX45*Debts!D26/12,0) | BZ45: 0 | CA45: =MAX(0,BX45+BY45-BZ45) | CB45: =CE44 | CC45: =IF(CB45>0.005,CB45*Debts!D27/12,0) | CD45: 0 | CE45: =MAX(0,CB45+CC45-CD45) | CF45: =G45+K45+O45+S45+W45+AA45+AE45+AI45+AM45+AQ45+AU45+AY45+BC45+BG45+BK45+BO45+BS45+BW45+CA45+CE45 | CG45: =E45+I45+M45+Q45+U45+Y45+AC45+AG45+AK45+AO45+AS45+AW45+BA45+BE45+BI45+BM45+BQ45+BU45+BY45+CC45 | CH45: =CH44+CG45
B46: 42 | C46: =F46+J46+N46+R46+V46+Z46+AD46+AH46+AL46+AP46+AT46+AX46+BB46+BF46+BJ46+BN46+BR46+BV46+BZ46+CD46 | D46: =G45 | E46: =IF(D46>0.005,D46*Debts!D8/12,0) | F46: 0 | G46: =MAX(0,D46+E46-F46) | H46: =K45 | I46: =IF(H46>0.005,H46*Debts!D9/12,0) | J46: 0 | K46: =MAX(0,H46+I46-J46) | L46: =O45 | M46: =IF(L46>0.005,L46*Debts!D10/12,0) | N46: 0 | O46: =MAX(0,L46+M46-N46) | P46: =S45 | Q46: =IF(P46>0.005,P46*Debts!D11/12,0) | R46: 0 | S46: =MAX(0,P46+Q46-R46) | T46: =W45 | U46: =IF(T46>0.005,T46*Debts!D12/12,0) | V46: 0 | W46: =MAX(0,T46+U46-V46) | X46: =AA45 | Y46: =IF(X46>0.005,X46*Debts!D13/12,0) | Z46: 0 | AA46: =MAX(0,X46+Y46-Z46) | AB46: =AE45 | AC46: =IF(AB46>0.005,AB46*Debts!D14/12,0) | AD46: 0 | AE46: =MAX(0,AB46+AC46-AD46) | AF46: =AI45 | AG46: =IF(AF46>0.005,AF46*Debts!D15/12,0) | AH46: 0 | AI46: =MAX(0,AF46+AG46-AH46) | AJ46: =AM45 | AK46: =IF(AJ46>0.005,AJ46*Debts!D16/12,0) | AL46: 0 | AM46: =MAX(0,AJ46+AK46-AL46) | AN46: =AQ45 | AO46: =IF(AN46>0.005,AN46*Debts!D17/12,0) | AP46: 0 | AQ46: =MAX(0,AN46+AO46-AP46) | AR46: =AU45 | AS46: =IF(AR46>0.005,AR46*Debts!D18/12,0) | AT46: 0 | AU46: =MAX(0,AR46+AS46-AT46) | AV46: =AY45 | AW46: =IF(AV46>0.005,AV46*Debts!D19/12,0) | AX46: 0 | AY46: =MAX(0,AV46+AW46-AX46) | AZ46: =BC45 | BA46: =IF(AZ46>0.005,AZ46*Debts!D20/12,0) | BB46: 0 | BC46: =MAX(0,AZ46+BA46-BB46) | BD46: =BG45 | BE46: =IF(BD46>0.005,BD46*Debts!D21/12,0) | BF46: 0 | BG46: =MAX(0,BD46+BE46-BF46) | BH46: =BK45 | BI46: =IF(BH46>0.005,BH46*Debts!D22/12,0) | BJ46: 0 | BK46: =MAX(0,BH46+BI46-BJ46) | BL46: =BO45 | BM46: =IF(BL46>0.005,BL46*Debts!D23/12,0) | BN46: 0 | BO46: =MAX(0,BL46+BM46-BN46) | BP46: =BS45 | BQ46: =IF(BP46>0.005,BP46*Debts!D24/12,0) | BR46: 0 | BS46: =MAX(0,BP46+BQ46-BR46) | BT46: =BW45 | BU46: =IF(BT46>0.005,BT46*Debts!D25/12,0) | BV46: 0 | BW46: =MAX(0,BT46+BU46-BV46) | BX46: =CA45 | BY46: =IF(BX46>0.005,BX46*Debts!D26/12,0) | BZ46: 0 | CA46: =MAX(0,BX46+BY46-BZ46) | CB46: =CE45 | CC46: =IF(CB46>0.005,CB46*Debts!D27/12,0) | CD46: 0 | CE46: =MAX(0,CB46+CC46-CD46) | CF46: =G46+K46+O46+S46+W46+AA46+AE46+AI46+AM46+AQ46+AU46+AY46+BC46+BG46+BK46+BO46+BS46+BW46+CA46+CE46 | CG46: =E46+I46+M46+Q46+U46+Y46+AC46+AG46+AK46+AO46+AS46+AW46+BA46+BE46+BI46+BM46+BQ46+BU46+BY46+CC46 | CH46: =CH45+CG46
B47: 43 | C47: =F47+J47+N47+R47+V47+Z47+AD47+AH47+AL47+AP47+AT47+AX47+BB47+BF47+BJ47+BN47+BR47+BV47+BZ47+CD47 | D47: =G46 | E47: =IF(D47>0.005,D47*Debts!D8/12,0) | F47: 0 | G47: =MAX(0,D47+E47-F47) | H47: =K46 | I47: =IF(H47>0.005,H47*Debts!D9/12,0) | J47: 0 | K47: =MAX(0,H47+I47-J47) | L47: =O46 | M47: =IF(L47>0.005,L47*Debts!D10/12,0) | N47: 0 | O47: =MAX(0,L47+M47-N47) | P47: =S46 | Q47: =IF(P47>0.005,P47*Debts!D11/12,0) | R47: 0 | S47: =MAX(0,P47+Q47-R47) | T47: =W46 | U47: =IF(T47>0.005,T47*Debts!D12/12,0) | V47: 0 | W47: =MAX(0,T47+U47-V47) | X47: =AA46 | Y47: =IF(X47>0.005,X47*Debts!D13/12,0) | Z47: 0 | AA47: =MAX(0,X47+Y47-Z47) | AB47: =AE46 | AC47: =IF(AB47>0.005,AB47*Debts!D14/12,0) | AD47: 0 | AE47: =MAX(0,AB47+AC47-AD47) | AF47: =AI46 | AG47: =IF(AF47>0.005,AF47*Debts!D15/12,0) | AH47: 0 | AI47: =MAX(0,AF47+AG47-AH47) | AJ47: =AM46 | AK47: =IF(AJ47>0.005,AJ47*Debts!D16/12,0) | AL47: 0 | AM47: =MAX(0,AJ47+AK47-AL47) | AN47: =AQ46 | AO47: =IF(AN47>0.005,AN47*Debts!D17/12,0) | AP47: 0 | AQ47: =MAX(0,AN47+AO47-AP47) | AR47: =AU46 | AS47: =IF(AR47>0.005,AR47*Debts!D18/12,0) | AT47: 0 | AU47: =MAX(0,AR47+AS47-AT47) | AV47: =AY46 | AW47: =IF(AV47>0.005,AV47*Debts!D19/12,0) | AX47: 0 | AY47: =MAX(0,AV47+AW47-AX47) | AZ47: =BC46 | BA47: =IF(AZ47>0.005,AZ47*Debts!D20/12,0) | BB47: 0 | BC47: =MAX(0,AZ47+BA47-BB47) | BD47: =BG46 | BE47: =IF(BD47>0.005,BD47*Debts!D21/12,0) | BF47: 0 | BG47: =MAX(0,BD47+BE47-BF47) | BH47: =BK46 | BI47: =IF(BH47>0.005,BH47*Debts!D22/12,0) | BJ47: 0 | BK47: =MAX(0,BH47+BI47-BJ47) | BL47: =BO46 | BM47: =IF(BL47>0.005,BL47*Debts!D23/12,0) | BN47: 0 | BO47: =MAX(0,BL47+BM47-BN47) | BP47: =BS46 | BQ47: =IF(BP47>0.005,BP47*Debts!D24/12,0) | BR47: 0 | BS47: =MAX(0,BP47+BQ47-BR47) | BT47: =BW46 | BU47: =IF(BT47>0.005,BT47*Debts!D25/12,0) | BV47: 0 | BW47: =MAX(0,BT47+BU47-BV47) | BX47: =CA46 | BY47: =IF(BX47>0.005,BX47*Debts!D26/12,0) | BZ47: 0 | CA47: =MAX(0,BX47+BY47-BZ47) | CB47: =CE46 | CC47: =IF(CB47>0.005,CB47*Debts!D27/12,0) | CD47: 0 | CE47: =MAX(0,CB47+CC47-CD47) | CF47: =G47+K47+O47+S47+W47+AA47+AE47+AI47+AM47+AQ47+AU47+AY47+BC47+BG47+BK47+BO47+BS47+BW47+CA47+CE47 | CG47: =E47+I47+M47+Q47+U47+Y47+AC47+AG47+AK47+AO47+AS47+AW47+BA47+BE47+BI47+BM47+BQ47+BU47+BY47+CC47 | CH47: =CH46+CG47
B48: 44 | C48: =F48+J48+N48+R48+V48+Z48+AD48+AH48+AL48+AP48+AT48+AX48+BB48+BF48+BJ48+BN48+BR48+BV48+BZ48+CD48 | D48: =G47 | E48: =IF(D48>0.005,D48*Debts!D8/12,0) | F48: 0 | G48: =MAX(0,D48+E48-F48) | H48: =K47 | I48: =IF(H48>0.005,H48*Debts!D9/12,0) | J48: 0 | K48: =MAX(0,H48+I48-J48) | L48: =O47 | M48: =IF(L48>0.005,L48*Debts!D10/12,0) | N48: 0 | O48: =MAX(0,L48+M48-N48) | P48: =S47 | Q48: =IF(P48>0.005,P48*Debts!D11/12,0) | R48: 0 | S48: =MAX(0,P48+Q48-R48) | T48: =W47 | U48: =IF(T48>0.005,T48*Debts!D12/12,0) | V48: 0 | W48: =MAX(0,T48+U48-V48) | X48: =AA47 | Y48: =IF(X48>0.005,X48*Debts!D13/12,0) | Z48: 0 | AA48: =MAX(0,X48+Y48-Z48) | AB48: =AE47 | AC48: =IF(AB48>0.005,AB48*Debts!D14/12,0) | AD48: 0 | AE48: =MAX(0,AB48+AC48-AD48) | AF48: =AI47 | AG48: =IF(AF48>0.005,AF48*Debts!D15/12,0) | AH48: 0 | AI48: =MAX(0,AF48+AG48-AH48) | AJ48: =AM47 | AK48: =IF(AJ48>0.005,AJ48*Debts!D16/12,0) | AL48: 0 | AM48: =MAX(0,AJ48+AK48-AL48) | AN48: =AQ47 | AO48: =IF(AN48>0.005,AN48*Debts!D17/12,0) | AP48: 0 | AQ48: =MAX(0,AN48+AO48-AP48) | AR48: =AU47 | AS48: =IF(AR48>0.005,AR48*Debts!D18/12,0) | AT48: 0 | AU48: =MAX(0,AR48+AS48-AT48) | AV48: =AY47 | AW48: =IF(AV48>0.005,AV48*Debts!D19/12,0) | AX48: 0 | AY48: =MAX(0,AV48+AW48-AX48) | AZ48: =BC47 | BA48: =IF(AZ48>0.005,AZ48*Debts!D20/12,0) | BB48: 0 | BC48: =MAX(0,AZ48+BA48-BB48) | BD48: =BG47 | BE48: =IF(BD48>0.005,BD48*Debts!D21/12,0) | BF48: 0 | BG48: =MAX(0,BD48+BE48-BF48) | BH48: =BK47 | BI48: =IF(BH48>0.005,BH48*Debts!D22/12,0) | BJ48: 0 | BK48: =MAX(0,BH48+BI48-BJ48) | BL48: =BO47 | BM48: =IF(BL48>0.005,BL48*Debts!D23/12,0) | BN48: 0 | BO48: =MAX(0,BL48+BM48-BN48) | BP48: =BS47 | BQ48: =IF(BP48>0.005,BP48*Debts!D24/12,0) | BR48: 0 | BS48: =MAX(0,BP48+BQ48-BR48) | BT48: =BW47 | BU48: =IF(BT48>0.005,BT48*Debts!D25/12,0) | BV48: 0 | BW48: =MAX(0,BT48+BU48-BV48) | BX48: =CA47 | BY48: =IF(BX48>0.005,BX48*Debts!D26/12,0) | BZ48: 0 | CA48: =MAX(0,BX48+BY48-BZ48) | CB48: =CE47 | CC48: =IF(CB48>0.005,CB48*Debts!D27/12,0) | CD48: 0 | CE48: =MAX(0,CB48+CC48-CD48) | CF48: =G48+K48+O48+S48+W48+AA48+AE48+AI48+AM48+AQ48+AU48+AY48+BC48+BG48+BK48+BO48+BS48+BW48+CA48+CE48 | CG48: =E48+I48+M48+Q48+U48+Y48+AC48+AG48+AK48+AO48+AS48+AW48+BA48+BE48+BI48+BM48+BQ48+BU48+BY48+CC48 | CH48: =CH47+CG48
B49: 45 | C49: =F49+J49+N49+R49+V49+Z49+AD49+AH49+AL49+AP49+AT49+AX49+BB49+BF49+BJ49+BN49+BR49+BV49+BZ49+CD49 | D49: =G48 | E49: =IF(D49>0.005,D49*Debts!D8/12,0) | F49: 0 | G49: =MAX(0,D49+E49-F49) | H49: =K48 | I49: =IF(H49>0.005,H49*Debts!D9/12,0) | J49: 0 | K49: =MAX(0,H49+I49-J49) | L49: =O48 | M49: =IF(L49>0.005,L49*Debts!D10/12,0) | N49: 0 | O49: =MAX(0,L49+M49-N49) | P49: =S48 | Q49: =IF(P49>0.005,P49*Debts!D11/12,0) | R49: 0 | S49: =MAX(0,P49+Q49-R49) | T49: =W48 | U49: =IF(T49>0.005,T49*Debts!D12/12,0) | V49: 0 | W49: =MAX(0,T49+U49-V49) | X49: =AA48 | Y49: =IF(X49>0.005,X49*Debts!D13/12,0) | Z49: 0 | AA49: =MAX(0,X49+Y49-Z49) | AB49: =AE48 | AC49: =IF(AB49>0.005,AB49*Debts!D14/12,0) | AD49: 0 | AE49: =MAX(0,AB49+AC49-AD49) | AF49: =AI48 | AG49: =IF(AF49>0.005,AF49*Debts!D15/12,0) | AH49: 0 | AI49: =MAX(0,AF49+AG49-AH49) | AJ49: =AM48 | AK49: =IF(AJ49>0.005,AJ49*Debts!D16/12,0) | AL49: 0 | AM49: =MAX(0,AJ49+AK49-AL49) | AN49: =AQ48 | AO49: =IF(AN49>0.005,AN49*Debts!D17/12,0) | AP49: 0 | AQ49: =MAX(0,AN49+AO49-AP49) | AR49: =AU48 | AS49: =IF(AR49>0.005,AR49*Debts!D18/12,0) | AT49: 0 | AU49: =MAX(0,AR49+AS49-AT49) | AV49: =AY48 | AW49: =IF(AV49>0.005,AV49*Debts!D19/12,0) | AX49: 0 | AY49: =MAX(0,AV49+AW49-AX49) | AZ49: =BC48 | BA49: =IF(AZ49>0.005,AZ49*Debts!D20/12,0) | BB49: 0 | BC49: =MAX(0,AZ49+BA49-BB49) | BD49: =BG48 | BE49: =IF(BD49>0.005,BD49*Debts!D21/12,0) | BF49: 0 | BG49: =MAX(0,BD49+BE49-BF49) | BH49: =BK48 | BI49: =IF(BH49>0.005,BH49*Debts!D22/12,0) | BJ49: 0 | BK49: =MAX(0,BH49+BI49-BJ49) | BL49: =BO48 | BM49: =IF(BL49>0.005,BL49*Debts!D23/12,0) | BN49: 0 | BO49: =MAX(0,BL49+BM49-BN49) | BP49: =BS48 | BQ49: =IF(BP49>0.005,BP49*Debts!D24/12,0) | BR49: 0 | BS49: =MAX(0,BP49+BQ49-BR49) | BT49: =BW48 | BU49: =IF(BT49>0.005,BT49*Debts!D25/12,0) | BV49: 0 | BW49: =MAX(0,BT49+BU49-BV49) | BX49: =CA48 | BY49: =IF(BX49>0.005,BX49*Debts!D26/12,0) | BZ49: 0 | CA49: =MAX(0,BX49+BY49-BZ49) | CB49: =CE48 | CC49: =IF(CB49>0.005,CB49*Debts!D27/12,0) | CD49: 0 | CE49: =MAX(0,CB49+CC49-CD49) | CF49: =G49+K49+O49+S49+W49+AA49+AE49+AI49+AM49+AQ49+AU49+AY49+BC49+BG49+BK49+BO49+BS49+BW49+CA49+CE49 | CG49: =E49+I49+M49+Q49+U49+Y49+AC49+AG49+AK49+AO49+AS49+AW49+BA49+BE49+BI49+BM49+BQ49+BU49+BY49+CC49 | CH49: =CH48+CG49
B50: 46 | C50: =F50+J50+N50+R50+V50+Z50+AD50+AH50+AL50+AP50+AT50+AX50+BB50+BF50+BJ50+BN50+BR50+BV50+BZ50+CD50 | D50: =G49 | E50: =IF(D50>0.005,D50*Debts!D8/12,0) | F50: 0 | G50: =MAX(0,D50+E50-F50) | H50: =K49 | I50: =IF(H50>0.005,H50*Debts!D9/12,0) | J50: 0 | K50: =MAX(0,H50+I50-J50) | L50: =O49 | M50: =IF(L50>0.005,L50*Debts!D10/12,0) | N50: 0 | O50: =MAX(0,L50+M50-N50) | P50: =S49 | Q50: =IF(P50>0.005,P50*Debts!D11/12,0) | R50: 0 | S50: =MAX(0,P50+Q50-R50) | T50: =W49 | U50: =IF(T50>0.005,T50*Debts!D12/12,0) | V50: 0 | W50: =MAX(0,T50+U50-V50) | X50: =AA49 | Y50: =IF(X50>0.005,X50*Debts!D13/12,0) | Z50: 0 | AA50: =MAX(0,X50+Y50-Z50) | AB50: =AE49 | AC50: =IF(AB50>0.005,AB50*Debts!D14/12,0) | AD50: 0 | AE50: =MAX(0,AB50+AC50-AD50) | AF50: =AI49 | AG50: =IF(AF50>0.005,AF50*Debts!D15/12,0) | AH50: 0 | AI50: =MAX(0,AF50+AG50-AH50) | AJ50: =AM49 | AK50: =IF(AJ50>0.005,AJ50*Debts!D16/12,0) | AL50: 0 | AM50: =MAX(0,AJ50+AK50-AL50) | AN50: =AQ49 | AO50: =IF(AN50>0.005,AN50*Debts!D17/12,0) | AP50: 0 | AQ50: =MAX(0,AN50+AO50-AP50) | AR50: =AU49 | AS50: =IF(AR50>0.005,AR50*Debts!D18/12,0) | AT50: 0 | AU50: =MAX(0,AR50+AS50-AT50) | AV50: =AY49 | AW50: =IF(AV50>0.005,AV50*Debts!D19/12,0) | AX50: 0 | AY50: =MAX(0,AV50+AW50-AX50) | AZ50: =BC49 | BA50: =IF(AZ50>0.005,AZ50*Debts!D20/12,0) | BB50: 0 | BC50: =MAX(0,AZ50+BA50-BB50) | BD50: =BG49 | BE50: =IF(BD50>0.005,BD50*Debts!D21/12,0) | BF50: 0 | BG50: =MAX(0,BD50+BE50-BF50) | BH50: =BK49 | BI50: =IF(BH50>0.005,BH50*Debts!D22/12,0) | BJ50: 0 | BK50: =MAX(0,BH50+BI50-BJ50) | BL50: =BO49 | BM50: =IF(BL50>0.005,BL50*Debts!D23/12,0) | BN50: 0 | BO50: =MAX(0,BL50+BM50-BN50) | BP50: =BS49 | BQ50: =IF(BP50>0.005,BP50*Debts!D24/12,0) | BR50: 0 | BS50: =MAX(0,BP50+BQ50-BR50) | BT50: =BW49 | BU50: =IF(BT50>0.005,BT50*Debts!D25/12,0) | BV50: 0 | BW50: =MAX(0,BT50+BU50-BV50) | BX50: =CA49 | BY50: =IF(BX50>0.005,BX50*Debts!D26/12,0) | BZ50: 0 | CA50: =MAX(0,BX50+BY50-BZ50) | CB50: =CE49 | CC50: =IF(CB50>0.005,CB50*Debts!D27/12,0) | CD50: 0 | CE50: =MAX(0,CB50+CC50-CD50) | CF50: =G50+K50+O50+S50+W50+AA50+AE50+AI50+AM50+AQ50+AU50+AY50+BC50+BG50+BK50+BO50+BS50+BW50+CA50+CE50 | CG50: =E50+I50+M50+Q50+U50+Y50+AC50+AG50+AK50+AO50+AS50+AW50+BA50+BE50+BI50+BM50+BQ50+BU50+BY50+CC50 | CH50: =CH49+CG50
B51: 47 | C51: =F51+J51+N51+R51+V51+Z51+AD51+AH51+AL51+AP51+AT51+AX51+BB51+BF51+BJ51+BN51+BR51+BV51+BZ51+CD51 | D51: =G50 | E51: =IF(D51>0.005,D51*Debts!D8/12,0) | F51: 0 | G51: =MAX(0,D51+E51-F51) | H51: =K50 | I51: =IF(H51>0.005,H51*Debts!D9/12,0) | J51: 0 | K51: =MAX(0,H51+I51-J51) | L51: =O50 | M51: =IF(L51>0.005,L51*Debts!D10/12,0) | N51: 0 | O51: =MAX(0,L51+M51-N51) | P51: =S50 | Q51: =IF(P51>0.005,P51*Debts!D11/12,0) | R51: 0 | S51: =MAX(0,P51+Q51-R51) | T51: =W50 | U51: =IF(T51>0.005,T51*Debts!D12/12,0) | V51: 0 | W51: =MAX(0,T51+U51-V51) | X51: =AA50 | Y51: =IF(X51>0.005,X51*Debts!D13/12,0) | Z51: 0 | AA51: =MAX(0,X51+Y51-Z51) | AB51: =AE50 | AC51: =IF(AB51>0.005,AB51*Debts!D14/12,0) | AD51: 0 | AE51: =MAX(0,AB51+AC51-AD51) | AF51: =AI50 | AG51: =IF(AF51>0.005,AF51*Debts!D15/12,0) | AH51: 0 | AI51: =MAX(0,AF51+AG51-AH51) | AJ51: =AM50 | AK51: =IF(AJ51>0.005,AJ51*Debts!D16/12,0) | AL51: 0 | AM51: =MAX(0,AJ51+AK51-AL51) | AN51: =AQ50 | AO51: =IF(AN51>0.005,AN51*Debts!D17/12,0) | AP51: 0 | AQ51: =MAX(0,AN51+AO51-AP51) | AR51: =AU50 | AS51: =IF(AR51>0.005,AR51*Debts!D18/12,0) | AT51: 0 | AU51: =MAX(0,AR51+AS51-AT51) | AV51: =AY50 | AW51: =IF(AV51>0.005,AV51*Debts!D19/12,0) | AX51: 0 | AY51: =MAX(0,AV51+AW51-AX51) | AZ51: =BC50 | BA51: =IF(AZ51>0.005,AZ51*Debts!D20/12,0) | BB51: 0 | BC51: =MAX(0,AZ51+BA51-BB51) | BD51: =BG50 | BE51: =IF(BD51>0.005,BD51*Debts!D21/12,0) | BF51: 0 | BG51: =MAX(0,BD51+BE51-BF51) | BH51: =BK50 | BI51: =IF(BH51>0.005,BH51*Debts!D22/12,0) | BJ51: 0 | BK51: =MAX(0,BH51+BI51-BJ51) | BL51: =BO50 | BM51: =IF(BL51>0.005,BL51*Debts!D23/12,0) | BN51: 0 | BO51: =MAX(0,BL51+BM51-BN51) | BP51: =BS50 | BQ51: =IF(BP51>0.005,BP51*Debts!D24/12,0) | BR51: 0 | BS51: =MAX(0,BP51+BQ51-BR51) | BT51: =BW50 | BU51: =IF(BT51>0.005,BT51*Debts!D25/12,0) | BV51: 0 | BW51: =MAX(0,BT51+BU51-BV51) | BX51: =CA50 | BY51: =IF(BX51>0.005,BX51*Debts!D26/12,0) | BZ51: 0 | CA51: =MAX(0,BX51+BY51-BZ51) | CB51: =CE50 | CC51: =IF(CB51>0.005,CB51*Debts!D27/12,0) | CD51: 0 | CE51: =MAX(0,CB51+CC51-CD51) | CF51: =G51+K51+O51+S51+W51+AA51+AE51+AI51+AM51+AQ51+AU51+AY51+BC51+BG51+BK51+BO51+BS51+BW51+CA51+CE51 | CG51: =E51+I51+M51+Q51+U51+Y51+AC51+AG51+AK51+AO51+AS51+AW51+BA51+BE51+BI51+BM51+BQ51+BU51+BY51+CC51 | CH51: =CH50+CG51
B52: 48 | C52: =F52+J52+N52+R52+V52+Z52+AD52+AH52+AL52+AP52+AT52+AX52+BB52+BF52+BJ52+BN52+BR52+BV52+BZ52+CD52 | D52: =G51 | E52: =IF(D52>0.005,D52*Debts!D8/12,0) | F52: 0 | G52: =MAX(0,D52+E52-F52) | H52: =K51 | I52: =IF(H52>0.005,H52*Debts!D9/12,0) | J52: 0 | K52: =MAX(0,H52+I52-J52) | L52: =O51 | M52: =IF(L52>0.005,L52*Debts!D10/12,0) | N52: 0 | O52: =MAX(0,L52+M52-N52) | P52: =S51 | Q52: =IF(P52>0.005,P52*Debts!D11/12,0) | R52: 0 | S52: =MAX(0,P52+Q52-R52) | T52: =W51 | U52: =IF(T52>0.005,T52*Debts!D12/12,0) | V52: 0 | W52: =MAX(0,T52+U52-V52) | X52: =AA51 | Y52: =IF(X52>0.005,X52*Debts!D13/12,0) | Z52: 0 | AA52: =MAX(0,X52+Y52-Z52) | AB52: =AE51 | AC52: =IF(AB52>0.005,AB52*Debts!D14/12,0) | AD52: 0 | AE52: =MAX(0,AB52+AC52-AD52) | AF52: =AI51 | AG52: =IF(AF52>0.005,AF52*Debts!D15/12,0) | AH52: 0 | AI52: =MAX(0,AF52+AG52-AH52) | AJ52: =AM51 | AK52: =IF(AJ52>0.005,AJ52*Debts!D16/12,0) | AL52: 0 | AM52: =MAX(0,AJ52+AK52-AL52) | AN52: =AQ51 | AO52: =IF(AN52>0.005,AN52*Debts!D17/12,0) | AP52: 0 | AQ52: =MAX(0,AN52+AO52-AP52) | AR52: =AU51 | AS52: =IF(AR52>0.005,AR52*Debts!D18/12,0) | AT52: 0 | AU52: =MAX(0,AR52+AS52-AT52) | AV52: =AY51 | AW52: =IF(AV52>0.005,AV52*Debts!D19/12,0) | AX52: 0 | AY52: =MAX(0,AV52+AW52-AX52) | AZ52: =BC51 | BA52: =IF(AZ52>0.005,AZ52*Debts!D20/12,0) | BB52: 0 | BC52: =MAX(0,AZ52+BA52-BB52) | BD52: =BG51 | BE52: =IF(BD52>0.005,BD52*Debts!D21/12,0) | BF52: 0 | BG52: =MAX(0,BD52+BE52-BF52) | BH52: =BK51 | BI52: =IF(BH52>0.005,BH52*Debts!D22/12,0) | BJ52: 0 | BK52: =MAX(0,BH52+BI52-BJ52) | BL52: =BO51 | BM52: =IF(BL52>0.005,BL52*Debts!D23/12,0) | BN52: 0 | BO52: =MAX(0,BL52+BM52-BN52) | BP52: =BS51 | BQ52: =IF(BP52>0.005,BP52*Debts!D24/12,0) | BR52: 0 | BS52: =MAX(0,BP52+BQ52-BR52) | BT52: =BW51 | BU52: =IF(BT52>0.005,BT52*Debts!D25/12,0) | BV52: 0 | BW52: =MAX(0,BT52+BU52-BV52) | BX52: =CA51 | BY52: =IF(BX52>0.005,BX52*Debts!D26/12,0) | BZ52: 0 | CA52: =MAX(0,BX52+BY52-BZ52) | CB52: =CE51 | CC52: =IF(CB52>0.005,CB52*Debts!D27/12,0) | CD52: 0 | CE52: =MAX(0,CB52+CC52-CD52) | CF52: =G52+K52+O52+S52+W52+AA52+AE52+AI52+AM52+AQ52+AU52+AY52+BC52+BG52+BK52+BO52+BS52+BW52+CA52+CE52 | CG52: =E52+I52+M52+Q52+U52+Y52+AC52+AG52+AK52+AO52+AS52+AW52+BA52+BE52+BI52+BM52+BQ52+BU52+BY52+CC52 | CH52: =CH51+CG52
B53: 49 | C53: =F53+J53+N53+R53+V53+Z53+AD53+AH53+AL53+AP53+AT53+AX53+BB53+BF53+BJ53+BN53+BR53+BV53+BZ53+CD53 | D53: =G52 | E53: =IF(D53>0.005,D53*Debts!D8/12,0) | F53: 0 | G53: =MAX(0,D53+E53-F53) | H53: =K52 | I53: =IF(H53>0.005,H53*Debts!D9/12,0) | J53: 0 | K53: =MAX(0,H53+I53-J53) | L53: =O52 | M53: =IF(L53>0.005,L53*Debts!D10/12,0) | N53: 0 | O53: =MAX(0,L53+M53-N53) | P53: =S52 | Q53: =IF(P53>0.005,P53*Debts!D11/12,0) | R53: 0 | S53: =MAX(0,P53+Q53-R53) | T53: =W52 | U53: =IF(T53>0.005,T53*Debts!D12/12,0) | V53: 0 | W53: =MAX(0,T53+U53-V53) | X53: =AA52 | Y53: =IF(X53>0.005,X53*Debts!D13/12,0) | Z53: 0 | AA53: =MAX(0,X53+Y53-Z53) | AB53: =AE52 | AC53: =IF(AB53>0.005,AB53*Debts!D14/12,0) | AD53: 0 | AE53: =MAX(0,AB53+AC53-AD53) | AF53: =AI52 | AG53: =IF(AF53>0.005,AF53*Debts!D15/12,0) | AH53: 0 | AI53: =MAX(0,AF53+AG53-AH53) | AJ53: =AM52 | AK53: =IF(AJ53>0.005,AJ53*Debts!D16/12,0) | AL53: 0 | AM53: =MAX(0,AJ53+AK53-AL53) | AN53: =AQ52 | AO53: =IF(AN53>0.005,AN53*Debts!D17/12,0) | AP53: 0 | AQ53: =MAX(0,AN53+AO53-AP53) | AR53: =AU52 | AS53: =IF(AR53>0.005,AR53*Debts!D18/12,0) | AT53: 0 | AU53: =MAX(0,AR53+AS53-AT53) | AV53: =AY52 | AW53: =IF(AV53>0.005,AV53*Debts!D19/12,0) | AX53: 0 | AY53: =MAX(0,AV53+AW53-AX53) | AZ53: =BC52 | BA53: =IF(AZ53>0.005,AZ53*Debts!D20/12,0) | BB53: 0 | BC53: =MAX(0,AZ53+BA53-BB53) | BD53: =BG52 | BE53: =IF(BD53>0.005,BD53*Debts!D21/12,0) | BF53: 0 | BG53: =MAX(0,BD53+BE53-BF53) | BH53: =BK52 | BI53: =IF(BH53>0.005,BH53*Debts!D22/12,0) | BJ53: 0 | BK53: =MAX(0,BH53+BI53-BJ53) | BL53: =BO52 | BM53: =IF(BL53>0.005,BL53*Debts!D23/12,0) | BN53: 0 | BO53: =MAX(0,BL53+BM53-BN53) | BP53: =BS52 | BQ53: =IF(BP53>0.005,BP53*Debts!D24/12,0) | BR53: 0 | BS53: =MAX(0,BP53+BQ53-BR53) | BT53: =BW52 | BU53: =IF(BT53>0.005,BT53*Debts!D25/12,0) | BV53: 0 | BW53: =MAX(0,BT53+BU53-BV53) | BX53: =CA52 | BY53: =IF(BX53>0.005,BX53*Debts!D26/12,0) | BZ53: 0 | CA53: =MAX(0,BX53+BY53-BZ53) | CB53: =CE52 | CC53: =IF(CB53>0.005,CB53*Debts!D27/12,0) | CD53: 0 | CE53: =MAX(0,CB53+CC53-CD53) | CF53: =G53+K53+O53+S53+W53+AA53+AE53+AI53+AM53+AQ53+AU53+AY53+BC53+BG53+BK53+BO53+BS53+BW53+CA53+CE53 | CG53: =E53+I53+M53+Q53+U53+Y53+AC53+AG53+AK53+AO53+AS53+AW53+BA53+BE53+BI53+BM53+BQ53+BU53+BY53+CC53 | CH53: =CH52+CG53
B54: 50 | C54: =F54+J54+N54+R54+V54+Z54+AD54+AH54+AL54+AP54+AT54+AX54+BB54+BF54+BJ54+BN54+BR54+BV54+BZ54+CD54 | D54: =G53 | E54: =IF(D54>0.005,D54*Debts!D8/12,0) | F54: 0 | G54: =MAX(0,D54+E54-F54) | H54: =K53 | I54: =IF(H54>0.005,H54*Debts!D9/12,0) | J54: 0 | K54: =MAX(0,H54+I54-J54) | L54: =O53 | M54: =IF(L54>0.005,L54*Debts!D10/12,0) | N54: 0 | O54: =MAX(0,L54+M54-N54) | P54: =S53 | Q54: =IF(P54>0.005,P54*Debts!D11/12,0) | R54: 0 | S54: =MAX(0,P54+Q54-R54) | T54: =W53 | U54: =IF(T54>0.005,T54*Debts!D12/12,0) | V54: 0 | W54: =MAX(0,T54+U54-V54) | X54: =AA53 | Y54: =IF(X54>0.005,X54*Debts!D13/12,0) | Z54: 0 | AA54: =MAX(0,X54+Y54-Z54) | AB54: =AE53 | AC54: =IF(AB54>0.005,AB54*Debts!D14/12,0) | AD54: 0 | AE54: =MAX(0,AB54+AC54-AD54) | AF54: =AI53 | AG54: =IF(AF54>0.005,AF54*Debts!D15/12,0) | AH54: 0 | AI54: =MAX(0,AF54+AG54-AH54) | AJ54: =AM53 | AK54: =IF(AJ54>0.005,AJ54*Debts!D16/12,0) | AL54: 0 | AM54: =MAX(0,AJ54+AK54-AL54) | AN54: =AQ53 | AO54: =IF(AN54>0.005,AN54*Debts!D17/12,0) | AP54: 0 | AQ54: =MAX(0,AN54+AO54-AP54) | AR54: =AU53 | AS54: =IF(AR54>0.005,AR54*Debts!D18/12,0) | AT54: 0 | AU54: =MAX(0,AR54+AS54-AT54) | AV54: =AY53 | AW54: =IF(AV54>0.005,AV54*Debts!D19/12,0) | AX54: 0 | AY54: =MAX(0,AV54+AW54-AX54) | AZ54: =BC53 | BA54: =IF(AZ54>0.005,AZ54*Debts!D20/12,0) | BB54: 0 | BC54: =MAX(0,AZ54+BA54-BB54) | BD54: =BG53 | BE54: =IF(BD54>0.005,BD54*Debts!D21/12,0) | BF54: 0 | BG54: =MAX(0,BD54+BE54-BF54) | BH54: =BK53 | BI54: =IF(BH54>0.005,BH54*Debts!D22/12,0) | BJ54: 0 | BK54: =MAX(0,BH54+BI54-BJ54) | BL54: =BO53 | BM54: =IF(BL54>0.005,BL54*Debts!D23/12,0) | BN54: 0 | BO54: =MAX(0,BL54+BM54-BN54) | BP54: =BS53 | BQ54: =IF(BP54>0.005,BP54*Debts!D24/12,0) | BR54: 0 | BS54: =MAX(0,BP54+BQ54-BR54) | BT54: =BW53 | BU54: =IF(BT54>0.005,BT54*Debts!D25/12,0) | BV54: 0 | BW54: =MAX(0,BT54+BU54-BV54) | BX54: =CA53 | BY54: =IF(BX54>0.005,BX54*Debts!D26/12,0) | BZ54: 0 | CA54: =MAX(0,BX54+BY54-BZ54) | CB54: =CE53 | CC54: =IF(CB54>0.005,CB54*Debts!D27/12,0) | CD54: 0 | CE54: =MAX(0,CB54+CC54-CD54) | CF54: =G54+K54+O54+S54+W54+AA54+AE54+AI54+AM54+AQ54+AU54+AY54+BC54+BG54+BK54+BO54+BS54+BW54+CA54+CE54 | CG54: =E54+I54+M54+Q54+U54+Y54+AC54+AG54+AK54+AO54+AS54+AW54+BA54+BE54+BI54+BM54+BQ54+BU54+BY54+CC54 | CH54: =CH53+CG54
B55: 51 | C55: =F55+J55+N55+R55+V55+Z55+AD55+AH55+AL55+AP55+AT55+AX55+BB55+BF55+BJ55+BN55+BR55+BV55+BZ55+CD55 | D55: =G54 | E55: =IF(D55>0.005,D55*Debts!D8/12,0) | F55: 0 | G55: =MAX(0,D55+E55-F55) | H55: =K54 | I55: =IF(H55>0.005,H55*Debts!D9/12,0) | J55: 0 | K55: =MAX(0,H55+I55-J55) | L55: =O54 | M55: =IF(L55>0.005,L55*Debts!D10/12,0) | N55: 0 | O55: =MAX(0,L55+M55-N55) | P55: =S54 | Q55: =IF(P55>0.005,P55*Debts!D11/12,0) | R55: 0 | S55: =MAX(0,P55+Q55-R55) | T55: =W54 | U55: =IF(T55>0.005,T55*Debts!D12/12,0) | V55: 0 | W55: =MAX(0,T55+U55-V55) | X55: =AA54 | Y55: =IF(X55>0.005,X55*Debts!D13/12,0) | Z55: 0 | AA55: =MAX(0,X55+Y55-Z55) | AB55: =AE54 | AC55: =IF(AB55>0.005,AB55*Debts!D14/12,0) | AD55: 0 | AE55: =MAX(0,AB55+AC55-AD55) | AF55: =AI54 | AG55: =IF(AF55>0.005,AF55*Debts!D15/12,0) | AH55: 0 | AI55: =MAX(0,AF55+AG55-AH55) | AJ55: =AM54 | AK55: =IF(AJ55>0.005,AJ55*Debts!D16/12,0) | AL55: 0 | AM55: =MAX(0,AJ55+AK55-AL55) | AN55: =AQ54 | AO55: =IF(AN55>0.005,AN55*Debts!D17/12,0) | AP55: 0 | AQ55: =MAX(0,AN55+AO55-AP55) | AR55: =AU54 | AS55: =IF(AR55>0.005,AR55*Debts!D18/12,0) | AT55: 0 | AU55: =MAX(0,AR55+AS55-AT55) | AV55: =AY54 | AW55: =IF(AV55>0.005,AV55*Debts!D19/12,0) | AX55: 0 | AY55: =MAX(0,AV55+AW55-AX55) | AZ55: =BC54 | BA55: =IF(AZ55>0.005,AZ55*Debts!D20/12,0) | BB55: 0 | BC55: =MAX(0,AZ55+BA55-BB55) | BD55: =BG54 | BE55: =IF(BD55>0.005,BD55*Debts!D21/12,0) | BF55: 0 | BG55: =MAX(0,BD55+BE55-BF55) | BH55: =BK54 | BI55: =IF(BH55>0.005,BH55*Debts!D22/12,0) | BJ55: 0 | BK55: =MAX(0,BH55+BI55-BJ55) | BL55: =BO54 | BM55: =IF(BL55>0.005,BL55*Debts!D23/12,0) | BN55: 0 | BO55: =MAX(0,BL55+BM55-BN55) | BP55: =BS54 | BQ55: =IF(BP55>0.005,BP55*Debts!D24/12,0) | BR55: 0 | BS55: =MAX(0,BP55+BQ55-BR55) | BT55: =BW54 | BU55: =IF(BT55>0.005,BT55*Debts!D25/12,0) | BV55: 0 | BW55: =MAX(0,BT55+BU55-BV55) | BX55: =CA54 | BY55: =IF(BX55>0.005,BX55*Debts!D26/12,0) | BZ55: 0 | CA55: =MAX(0,BX55+BY55-BZ55) | CB55: =CE54 | CC55: =IF(CB55>0.005,CB55*Debts!D27/12,0) | CD55: 0 | CE55: =MAX(0,CB55+CC55-CD55) | CF55: =G55+K55+O55+S55+W55+AA55+AE55+AI55+AM55+AQ55+AU55+AY55+BC55+BG55+BK55+BO55+BS55+BW55+CA55+CE55 | CG55: =E55+I55+M55+Q55+U55+Y55+AC55+AG55+AK55+AO55+AS55+AW55+BA55+BE55+BI55+BM55+BQ55+BU55+BY55+CC55 | CH55: =CH54+CG55
B56: 52 | C56: =F56+J56+N56+R56+V56+Z56+AD56+AH56+AL56+AP56+AT56+AX56+BB56+BF56+BJ56+BN56+BR56+BV56+BZ56+CD56 | D56: =G55 | E56: =IF(D56>0.005,D56*Debts!D8/12,0) | F56: 0 | G56: =MAX(0,D56+E56-F56) | H56: =K55 | I56: =IF(H56>0.005,H56*Debts!D9/12,0) | J56: 0 | K56: =MAX(0,H56+I56-J56) | L56: =O55 | M56: =IF(L56>0.005,L56*Debts!D10/12,0) | N56: 0 | O56: =MAX(0,L56+M56-N56) | P56: =S55 | Q56: =IF(P56>0.005,P56*Debts!D11/12,0) | R56: 0 | S56: =MAX(0,P56+Q56-R56) | T56: =W55 | U56: =IF(T56>0.005,T56*Debts!D12/12,0) | V56: 0 | W56: =MAX(0,T56+U56-V56) | X56: =AA55 | Y56: =IF(X56>0.005,X56*Debts!D13/12,0) | Z56: 0 | AA56: =MAX(0,X56+Y56-Z56) | AB56: =AE55 | AC56: =IF(AB56>0.005,AB56*Debts!D14/12,0) | AD56: 0 | AE56: =MAX(0,AB56+AC56-AD56) | AF56: =AI55 | AG56: =IF(AF56>0.005,AF56*Debts!D15/12,0) | AH56: 0 | AI56: =MAX(0,AF56+AG56-AH56) | AJ56: =AM55 | AK56: =IF(AJ56>0.005,AJ56*Debts!D16/12,0) | AL56: 0 | AM56: =MAX(0,AJ56+AK56-AL56) | AN56: =AQ55 | AO56: =IF(AN56>0.005,AN56*Debts!D17/12,0) | AP56: 0 | AQ56: =MAX(0,AN56+AO56-AP56) | AR56: =AU55 | AS56: =IF(AR56>0.005,AR56*Debts!D18/12,0) | AT56: 0 | AU56: =MAX(0,AR56+AS56-AT56) | AV56: =AY55 | AW56: =IF(AV56>0.005,AV56*Debts!D19/12,0) | AX56: 0 | AY56: =MAX(0,AV56+AW56-AX56) | AZ56: =BC55 | BA56: =IF(AZ56>0.005,AZ56*Debts!D20/12,0) | BB56: 0 | BC56: =MAX(0,AZ56+BA56-BB56) | BD56: =BG55 | BE56: =IF(BD56>0.005,BD56*Debts!D21/12,0) | BF56: 0 | BG56: =MAX(0,BD56+BE56-BF56) | BH56: =BK55 | BI56: =IF(BH56>0.005,BH56*Debts!D22/12,0) | BJ56: 0 | BK56: =MAX(0,BH56+BI56-BJ56) | BL56: =BO55 | BM56: =IF(BL56>0.005,BL56*Debts!D23/12,0) | BN56: 0 | BO56: =MAX(0,BL56+BM56-BN56) | BP56: =BS55 | BQ56: =IF(BP56>0.005,BP56*Debts!D24/12,0) | BR56: 0 | BS56: =MAX(0,BP56+BQ56-BR56) | BT56: =BW55 | BU56: =IF(BT56>0.005,BT56*Debts!D25/12,0) | BV56: 0 | BW56: =MAX(0,BT56+BU56-BV56) | BX56: =CA55 | BY56: =IF(BX56>0.005,BX56*Debts!D26/12,0) | BZ56: 0 | CA56: =MAX(0,BX56+BY56-BZ56) | CB56: =CE55 | CC56: =IF(CB56>0.005,CB56*Debts!D27/12,0) | CD56: 0 | CE56: =MAX(0,CB56+CC56-CD56) | CF56: =G56+K56+O56+S56+W56+AA56+AE56+AI56+AM56+AQ56+AU56+AY56+BC56+BG56+BK56+BO56+BS56+BW56+CA56+CE56 | CG56: =E56+I56+M56+Q56+U56+Y56+AC56+AG56+AK56+AO56+AS56+AW56+BA56+BE56+BI56+BM56+BQ56+BU56+BY56+CC56 | CH56: =CH55+CG56
B57: 53 | C57: =F57+J57+N57+R57+V57+Z57+AD57+AH57+AL57+AP57+AT57+AX57+BB57+BF57+BJ57+BN57+BR57+BV57+BZ57+CD57 | D57: =G56 | E57: =IF(D57>0.005,D57*Debts!D8/12,0) | F57: 0 | G57: =MAX(0,D57+E57-F57) | H57: =K56 | I57: =IF(H57>0.005,H57*Debts!D9/12,0) | J57: 0 | K57: =MAX(0,H57+I57-J57) | L57: =O56 | M57: =IF(L57>0.005,L57*Debts!D10/12,0) | N57: 0 | O57: =MAX(0,L57+M57-N57) | P57: =S56 | Q57: =IF(P57>0.005,P57*Debts!D11/12,0) | R57: 0 | S57: =MAX(0,P57+Q57-R57) | T57: =W56 | U57: =IF(T57>0.005,T57*Debts!D12/12,0) | V57: 0 | W57: =MAX(0,T57+U57-V57) | X57: =AA56 | Y57: =IF(X57>0.005,X57*Debts!D13/12,0) | Z57: 0 | AA57: =MAX(0,X57+Y57-Z57) | AB57: =AE56 | AC57: =IF(AB57>0.005,AB57*Debts!D14/12,0) | AD57: 0 | AE57: =MAX(0,AB57+AC57-AD57) | AF57: =AI56 | AG57: =IF(AF57>0.005,AF57*Debts!D15/12,0) | AH57: 0 | AI57: =MAX(0,AF57+AG57-AH57) | AJ57: =AM56 | AK57: =IF(AJ57>0.005,AJ57*Debts!D16/12,0) | AL57: 0 | AM57: =MAX(0,AJ57+AK57-AL57) | AN57: =AQ56 | AO57: =IF(AN57>0.005,AN57*Debts!D17/12,0) | AP57: 0 | AQ57: =MAX(0,AN57+AO57-AP57) | AR57: =AU56 | AS57: =IF(AR57>0.005,AR57*Debts!D18/12,0) | AT57: 0 | AU57: =MAX(0,AR57+AS57-AT57) | AV57: =AY56 | AW57: =IF(AV57>0.005,AV57*Debts!D19/12,0) | AX57: 0 | AY57: =MAX(0,AV57+AW57-AX57) | AZ57: =BC56 | BA57: =IF(AZ57>0.005,AZ57*Debts!D20/12,0) | BB57: 0 | BC57: =MAX(0,AZ57+BA57-BB57) | BD57: =BG56 | BE57: =IF(BD57>0.005,BD57*Debts!D21/12,0) | BF57: 0 | BG57: =MAX(0,BD57+BE57-BF57) | BH57: =BK56 | BI57: =IF(BH57>0.005,BH57*Debts!D22/12,0) | BJ57: 0 | BK57: =MAX(0,BH57+BI57-BJ57) | BL57: =BO56 | BM57: =IF(BL57>0.005,BL57*Debts!D23/12,0) | BN57: 0 | BO57: =MAX(0,BL57+BM57-BN57) | BP57: =BS56 | BQ57: =IF(BP57>0.005,BP57*Debts!D24/12,0) | BR57: 0 | BS57: =MAX(0,BP57+BQ57-BR57) | BT57: =BW56 | BU57: =IF(BT57>0.005,BT57*Debts!D25/12,0) | BV57: 0 | BW57: =MAX(0,BT57+BU57-BV57) | BX57: =CA56 | BY57: =IF(BX57>0.005,BX57*Debts!D26/12,0) | BZ57: 0 | CA57: =MAX(0,BX57+BY57-BZ57) | CB57: =CE56 | CC57: =IF(CB57>0.005,CB57*Debts!D27/12,0) | CD57: 0 | CE57: =MAX(0,CB57+CC57-CD57) | CF57: =G57+K57+O57+S57+W57+AA57+AE57+AI57+AM57+AQ57+AU57+AY57+BC57+BG57+BK57+BO57+BS57+BW57+CA57+CE57 | CG57: =E57+I57+M57+Q57+U57+Y57+AC57+AG57+AK57+AO57+AS57+AW57+BA57+BE57+BI57+BM57+BQ57+BU57+BY57+CC57 | CH57: =CH56+CG57
B58: 54 | C58: =F58+J58+N58+R58+V58+Z58+AD58+AH58+AL58+AP58+AT58+AX58+BB58+BF58+BJ58+BN58+BR58+BV58+BZ58+CD58 | D58: =G57 | E58: =IF(D58>0.005,D58*Debts!D8/12,0) | F58: 0 | G58: =MAX(0,D58+E58-F58) | H58: =K57 | I58: =IF(H58>0.005,H58*Debts!D9/12,0) | J58: 0 | K58: =MAX(0,H58+I58-J58) | L58: =O57 | M58: =IF(L58>0.005,L58*Debts!D10/12,0) | N58: 0 | O58: =MAX(0,L58+M58-N58) | P58: =S57 | Q58: =IF(P58>0.005,P58*Debts!D11/12,0) | R58: 0 | S58: =MAX(0,P58+Q58-R58) | T58: =W57 | U58: =IF(T58>0.005,T58*Debts!D12/12,0) | V58: 0 | W58: =MAX(0,T58+U58-V58) | X58: =AA57 | Y58: =IF(X58>0.005,X58*Debts!D13/12,0) | Z58: 0 | AA58: =MAX(0,X58+Y58-Z58) | AB58: =AE57 | AC58: =IF(AB58>0.005,AB58*Debts!D14/12,0) | AD58: 0 | AE58: =MAX(0,AB58+AC58-AD58) | AF58: =AI57 | AG58: =IF(AF58>0.005,AF58*Debts!D15/12,0) | AH58: 0 | AI58: =MAX(0,AF58+AG58-AH58) | AJ58: =AM57 | AK58: =IF(AJ58>0.005,AJ58*Debts!D16/12,0) | AL58: 0 | AM58: =MAX(0,AJ58+AK58-AL58) | AN58: =AQ57 | AO58: =IF(AN58>0.005,AN58*Debts!D17/12,0) | AP58: 0 | AQ58: =MAX(0,AN58+AO58-AP58) | AR58: =AU57 | AS58: =IF(AR58>0.005,AR58*Debts!D18/12,0) | AT58: 0 | AU58: =MAX(0,AR58+AS58-AT58) | AV58: =AY57 | AW58: =IF(AV58>0.005,AV58*Debts!D19/12,0) | AX58: 0 | AY58: =MAX(0,AV58+AW58-AX58) | AZ58: =BC57 | BA58: =IF(AZ58>0.005,AZ58*Debts!D20/12,0) | BB58: 0 | BC58: =MAX(0,AZ58+BA58-BB58) | BD58: =BG57 | BE58: =IF(BD58>0.005,BD58*Debts!D21/12,0) | BF58: 0 | BG58: =MAX(0,BD58+BE58-BF58) | BH58: =BK57 | BI58: =IF(BH58>0.005,BH58*Debts!D22/12,0) | BJ58: 0 | BK58: =MAX(0,BH58+BI58-BJ58) | BL58: =BO57 | BM58: =IF(BL58>0.005,BL58*Debts!D23/12,0) | BN58: 0 | BO58: =MAX(0,BL58+BM58-BN58) | BP58: =BS57 | BQ58: =IF(BP58>0.005,BP58*Debts!D24/12,0) | BR58: 0 | BS58: =MAX(0,BP58+BQ58-BR58) | BT58: =BW57 | BU58: =IF(BT58>0.005,BT58*Debts!D25/12,0) | BV58: 0 | BW58: =MAX(0,BT58+BU58-BV58) | BX58: =CA57 | BY58: =IF(BX58>0.005,BX58*Debts!D26/12,0) | BZ58: 0 | CA58: =MAX(0,BX58+BY58-BZ58) | CB58: =CE57 | CC58: =IF(CB58>0.005,CB58*Debts!D27/12,0) | CD58: 0 | CE58: =MAX(0,CB58+CC58-CD58) | CF58: =G58+K58+O58+S58+W58+AA58+AE58+AI58+AM58+AQ58+AU58+AY58+BC58+BG58+BK58+BO58+BS58+BW58+CA58+CE58 | CG58: =E58+I58+M58+Q58+U58+Y58+AC58+AG58+AK58+AO58+AS58+AW58+BA58+BE58+BI58+BM58+BQ58+BU58+BY58+CC58 | CH58: =CH57+CG58
B59: 55 | C59: =F59+J59+N59+R59+V59+Z59+AD59+AH59+AL59+AP59+AT59+AX59+BB59+BF59+BJ59+BN59+BR59+BV59+BZ59+CD59 | D59: =G58 | E59: =IF(D59>0.005,D59*Debts!D8/12,0) | F59: 0 | G59: =MAX(0,D59+E59-F59) | H59: =K58 | I59: =IF(H59>0.005,H59*Debts!D9/12,0) | J59: 0 | K59: =MAX(0,H59+I59-J59) | L59: =O58 | M59: =IF(L59>0.005,L59*Debts!D10/12,0) | N59: 0 | O59: =MAX(0,L59+M59-N59) | P59: =S58 | Q59: =IF(P59>0.005,P59*Debts!D11/12,0) | R59: 0 | S59: =MAX(0,P59+Q59-R59) | T59: =W58 | U59: =IF(T59>0.005,T59*Debts!D12/12,0) | V59: 0 | W59: =MAX(0,T59+U59-V59) | X59: =AA58 | Y59: =IF(X59>0.005,X59*Debts!D13/12,0) | Z59: 0 | AA59: =MAX(0,X59+Y59-Z59) | AB59: =AE58 | AC59: =IF(AB59>0.005,AB59*Debts!D14/12,0) | AD59: 0 | AE59: =MAX(0,AB59+AC59-AD59) | AF59: =AI58 | AG59: =IF(AF59>0.005,AF59*Debts!D15/12,0) | AH59: 0 | AI59: =MAX(0,AF59+AG59-AH59) | AJ59: =AM58 | AK59: =IF(AJ59>0.005,AJ59*Debts!D16/12,0) | AL59: 0 | AM59: =MAX(0,AJ59+AK59-AL59) | AN59: =AQ58 | AO59: =IF(AN59>0.005,AN59*Debts!D17/12,0) | AP59: 0 | AQ59: =MAX(0,AN59+AO59-AP59) | AR59: =AU58 | AS59: =IF(AR59>0.005,AR59*Debts!D18/12,0) | AT59: 0 | AU59: =MAX(0,AR59+AS59-AT59) | AV59: =AY58 | AW59: =IF(AV59>0.005,AV59*Debts!D19/12,0) | AX59: 0 | AY59: =MAX(0,AV59+AW59-AX59) | AZ59: =BC58 | BA59: =IF(AZ59>0.005,AZ59*Debts!D20/12,0) | BB59: 0 | BC59: =MAX(0,AZ59+BA59-BB59) | BD59: =BG58 | BE59: =IF(BD59>0.005,BD59*Debts!D21/12,0) | BF59: 0 | BG59: =MAX(0,BD59+BE59-BF59) | BH59: =BK58 | BI59: =IF(BH59>0.005,BH59*Debts!D22/12,0) | BJ59: 0 | BK59: =MAX(0,BH59+BI59-BJ59) | BL59: =BO58 | BM59: =IF(BL59>0.005,BL59*Debts!D23/12,0) | BN59: 0 | BO59: =MAX(0,BL59+BM59-BN59) | BP59: =BS58 | BQ59: =IF(BP59>0.005,BP59*Debts!D24/12,0) | BR59: 0 | BS59: =MAX(0,BP59+BQ59-BR59) | BT59: =BW58 | BU59: =IF(BT59>0.005,BT59*Debts!D25/12,0) | BV59: 0 | BW59: =MAX(0,BT59+BU59-BV59) | BX59: =CA58 | BY59: =IF(BX59>0.005,BX59*Debts!D26/12,0) | BZ59: 0 | CA59: =MAX(0,BX59+BY59-BZ59) | CB59: =CE58 | CC59: =IF(CB59>0.005,CB59*Debts!D27/12,0) | CD59: 0 | CE59: =MAX(0,CB59+CC59-CD59) | CF59: =G59+K59+O59+S59+W59+AA59+AE59+AI59+AM59+AQ59+AU59+AY59+BC59+BG59+BK59+BO59+BS59+BW59+CA59+CE59 | CG59: =E59+I59+M59+Q59+U59+Y59+AC59+AG59+AK59+AO59+AS59+AW59+BA59+BE59+BI59+BM59+BQ59+BU59+BY59+CC59 | CH59: =CH58+CG59
B60: 56 | C60: =F60+J60+N60+R60+V60+Z60+AD60+AH60+AL60+AP60+AT60+AX60+BB60+BF60+BJ60+BN60+BR60+BV60+BZ60+CD60 | D60: =G59 | E60: =IF(D60>0.005,D60*Debts!D8/12,0) | F60: 0 | G60: =MAX(0,D60+E60-F60) | H60: =K59 | I60: =IF(H60>0.005,H60*Debts!D9/12,0) | J60: 0 | K60: =MAX(0,H60+I60-J60) | L60: =O59 | M60: =IF(L60>0.005,L60*Debts!D10/12,0) | N60: 0 | O60: =MAX(0,L60+M60-N60) | P60: =S59 | Q60: =IF(P60>0.005,P60*Debts!D11/12,0) | R60: 0 | S60: =MAX(0,P60+Q60-R60) | T60: =W59 | U60: =IF(T60>0.005,T60*Debts!D12/12,0) | V60: 0 | W60: =MAX(0,T60+U60-V60) | X60: =AA59 | Y60: =IF(X60>0.005,X60*Debts!D13/12,0) | Z60: 0 | AA60: =MAX(0,X60+Y60-Z60) | AB60: =AE59 | AC60: =IF(AB60>0.005,AB60*Debts!D14/12,0) | AD60: 0 | AE60: =MAX(0,AB60+AC60-AD60) | AF60: =AI59 | AG60: =IF(AF60>0.005,AF60*Debts!D15/12,0) | AH60: 0 | AI60: =MAX(0,AF60+AG60-AH60) | AJ60: =AM59 | AK60: =IF(AJ60>0.005,AJ60*Debts!D16/12,0) | AL60: 0 | AM60: =MAX(0,AJ60+AK60-AL60) | AN60: =AQ59 | AO60: =IF(AN60>0.005,AN60*Debts!D17/12,0) | AP60: 0 | AQ60: =MAX(0,AN60+AO60-AP60) | AR60: =AU59 | AS60: =IF(AR60>0.005,AR60*Debts!D18/12,0) | AT60: 0 | AU60: =MAX(0,AR60+AS60-AT60) | AV60: =AY59 | AW60: =IF(AV60>0.005,AV60*Debts!D19/12,0) | AX60: 0 | AY60: =MAX(0,AV60+AW60-AX60) | AZ60: =BC59 | BA60: =IF(AZ60>0.005,AZ60*Debts!D20/12,0) | BB60: 0 | BC60: =MAX(0,AZ60+BA60-BB60) | BD60: =BG59 | BE60: =IF(BD60>0.005,BD60*Debts!D21/12,0) | BF60: 0 | BG60: =MAX(0,BD60+BE60-BF60) | BH60: =BK59 | BI60: =IF(BH60>0.005,BH60*Debts!D22/12,0) | BJ60: 0 | BK60: =MAX(0,BH60+BI60-BJ60) | BL60: =BO59 | BM60: =IF(BL60>0.005,BL60*Debts!D23/12,0) | BN60: 0 | BO60: =MAX(0,BL60+BM60-BN60) | BP60: =BS59 | BQ60: =IF(BP60>0.005,BP60*Debts!D24/12,0) | BR60: 0 | BS60: =MAX(0,BP60+BQ60-BR60) | BT60: =BW59 | BU60: =IF(BT60>0.005,BT60*Debts!D25/12,0) | BV60: 0 | BW60: =MAX(0,BT60+BU60-BV60) | BX60: =CA59 | BY60: =IF(BX60>0.005,BX60*Debts!D26/12,0) | BZ60: 0 | CA60: =MAX(0,BX60+BY60-BZ60) | CB60: =CE59 | CC60: =IF(CB60>0.005,CB60*Debts!D27/12,0) | CD60: 0 | CE60: =MAX(0,CB60+CC60-CD60) | CF60: =G60+K60+O60+S60+W60+AA60+AE60+AI60+AM60+AQ60+AU60+AY60+BC60+BG60+BK60+BO60+BS60+BW60+CA60+CE60 | CG60: =E60+I60+M60+Q60+U60+Y60+AC60+AG60+AK60+AO60+AS60+AW60+BA60+BE60+BI60+BM60+BQ60+BU60+BY60+CC60 | CH60: =CH59+CG60
B61: 57 | C61: =F61+J61+N61+R61+V61+Z61+AD61+AH61+AL61+AP61+AT61+AX61+BB61+BF61+BJ61+BN61+BR61+BV61+BZ61+CD61 | D61: =G60 | E61: =IF(D61>0.005,D61*Debts!D8/12,0) | F61: 0 | G61: =MAX(0,D61+E61-F61) | H61: =K60 | I61: =IF(H61>0.005,H61*Debts!D9/12,0) | J61: 0 | K61: =MAX(0,H61+I61-J61) | L61: =O60 | M61: =IF(L61>0.005,L61*Debts!D10/12,0) | N61: 0 | O61: =MAX(0,L61+M61-N61) | P61: =S60 | Q61: =IF(P61>0.005,P61*Debts!D11/12,0) | R61: 0 | S61: =MAX(0,P61+Q61-R61) | T61: =W60 | U61: =IF(T61>0.005,T61*Debts!D12/12,0) | V61: 0 | W61: =MAX(0,T61+U61-V61) | X61: =AA60 | Y61: =IF(X61>0.005,X61*Debts!D13/12,0) | Z61: 0 | AA61: =MAX(0,X61+Y61-Z61) | AB61: =AE60 | AC61: =IF(AB61>0.005,AB61*Debts!D14/12,0) | AD61: 0 | AE61: =MAX(0,AB61+AC61-AD61) | AF61: =AI60 | AG61: =IF(AF61>0.005,AF61*Debts!D15/12,0) | AH61: 0 | AI61: =MAX(0,AF61+AG61-AH61) | AJ61: =AM60 | AK61: =IF(AJ61>0.005,AJ61*Debts!D16/12,0) | AL61: 0 | AM61: =MAX(0,AJ61+AK61-AL61) | AN61: =AQ60 | AO61: =IF(AN61>0.005,AN61*Debts!D17/12,0) | AP61: 0 | AQ61: =MAX(0,AN61+AO61-AP61) | AR61: =AU60 | AS61: =IF(AR61>0.005,AR61*Debts!D18/12,0) | AT61: 0 | AU61: =MAX(0,AR61+AS61-AT61) | AV61: =AY60 | AW61: =IF(AV61>0.005,AV61*Debts!D19/12,0) | AX61: 0 | AY61: =MAX(0,AV61+AW61-AX61) | AZ61: =BC60 | BA61: =IF(AZ61>0.005,AZ61*Debts!D20/12,0) | BB61: 0 | BC61: =MAX(0,AZ61+BA61-BB61) | BD61: =BG60 | BE61: =IF(BD61>0.005,BD61*Debts!D21/12,0) | BF61: 0 | BG61: =MAX(0,BD61+BE61-BF61) | BH61: =BK60 | BI61: =IF(BH61>0.005,BH61*Debts!D22/12,0) | BJ61: 0 | BK61: =MAX(0,BH61+BI61-BJ61) | BL61: =BO60 | BM61: =IF(BL61>0.005,BL61*Debts!D23/12,0) | BN61: 0 | BO61: =MAX(0,BL61+BM61-BN61) | BP61: =BS60 | BQ61: =IF(BP61>0.005,BP61*Debts!D24/12,0) | BR61: 0 | BS61: =MAX(0,BP61+BQ61-BR61) | BT61: =BW60 | BU61: =IF(BT61>0.005,BT61*Debts!D25/12,0) | BV61: 0 | BW61: =MAX(0,BT61+BU61-BV61) | BX61: =CA60 | BY61: =IF(BX61>0.005,BX61*Debts!D26/12,0) | BZ61: 0 | CA61: =MAX(0,BX61+BY61-BZ61) | CB61: =CE60 | CC61: =IF(CB61>0.005,CB61*Debts!D27/12,0) | CD61: 0 | CE61: =MAX(0,CB61+CC61-CD61) | CF61: =G61+K61+O61+S61+W61+AA61+AE61+AI61+AM61+AQ61+AU61+AY61+BC61+BG61+BK61+BO61+BS61+BW61+CA61+CE61 | CG61: =E61+I61+M61+Q61+U61+Y61+AC61+AG61+AK61+AO61+AS61+AW61+BA61+BE61+BI61+BM61+BQ61+BU61+BY61+CC61 | CH61: =CH60+CG61
B62: 58 | C62: =F62+J62+N62+R62+V62+Z62+AD62+AH62+AL62+AP62+AT62+AX62+BB62+BF62+BJ62+BN62+BR62+BV62+BZ62+CD62 | D62: =G61 | E62: =IF(D62>0.005,D62*Debts!D8/12,0) | F62: 0 | G62: =MAX(0,D62+E62-F62) | H62: =K61 | I62: =IF(H62>0.005,H62*Debts!D9/12,0) | J62: 0 | K62: =MAX(0,H62+I62-J62) | L62: =O61 | M62: =IF(L62>0.005,L62*Debts!D10/12,0) | N62: 0 | O62: =MAX(0,L62+M62-N62) | P62: =S61 | Q62: =IF(P62>0.005,P62*Debts!D11/12,0) | R62: 0 | S62: =MAX(0,P62+Q62-R62) | T62: =W61 | U62: =IF(T62>0.005,T62*Debts!D12/12,0) | V62: 0 | W62: =MAX(0,T62+U62-V62) | X62: =AA61 | Y62: =IF(X62>0.005,X62*Debts!D13/12,0) | Z62: 0 | AA62: =MAX(0,X62+Y62-Z62) | AB62: =AE61 | AC62: =IF(AB62>0.005,AB62*Debts!D14/12,0) | AD62: 0 | AE62: =MAX(0,AB62+AC62-AD62) | AF62: =AI61 | AG62: =IF(AF62>0.005,AF62*Debts!D15/12,0) | AH62: 0 | AI62: =MAX(0,AF62+AG62-AH62) | AJ62: =AM61 | AK62: =IF(AJ62>0.005,AJ62*Debts!D16/12,0) | AL62: 0 | AM62: =MAX(0,AJ62+AK62-AL62) | AN62: =AQ61 | AO62: =IF(AN62>0.005,AN62*Debts!D17/12,0) | AP62: 0 | AQ62: =MAX(0,AN62+AO62-AP62) | AR62: =AU61 | AS62: =IF(AR62>0.005,AR62*Debts!D18/12,0) | AT62: 0 | AU62: =MAX(0,AR62+AS62-AT62) | AV62: =AY61 | AW62: =IF(AV62>0.005,AV62*Debts!D19/12,0) | AX62: 0 | AY62: =MAX(0,AV62+AW62-AX62) | AZ62: =BC61 | BA62: =IF(AZ62>0.005,AZ62*Debts!D20/12,0) | BB62: 0 | BC62: =MAX(0,AZ62+BA62-BB62) | BD62: =BG61 | BE62: =IF(BD62>0.005,BD62*Debts!D21/12,0) | BF62: 0 | BG62: =MAX(0,BD62+BE62-BF62) | BH62: =BK61 | BI62: =IF(BH62>0.005,BH62*Debts!D22/12,0) | BJ62: 0 | BK62: =MAX(0,BH62+BI62-BJ62) | BL62: =BO61 | BM62: =IF(BL62>0.005,BL62*Debts!D23/12,0) | BN62: 0 | BO62: =MAX(0,BL62+BM62-BN62) | BP62: =BS61 | BQ62: =IF(BP62>0.005,BP62*Debts!D24/12,0) | BR62: 0 | BS62: =MAX(0,BP62+BQ62-BR62) | BT62: =BW61 | BU62: =IF(BT62>0.005,BT62*Debts!D25/12,0) | BV62: 0 | BW62: =MAX(0,BT62+BU62-BV62) | BX62: =CA61 | BY62: =IF(BX62>0.005,BX62*Debts!D26/12,0) | BZ62: 0 | CA62: =MAX(0,BX62+BY62-BZ62) | CB62: =CE61 | CC62: =IF(CB62>0.005,CB62*Debts!D27/12,0) | CD62: 0 | CE62: =MAX(0,CB62+CC62-CD62) | CF62: =G62+K62+O62+S62+W62+AA62+AE62+AI62+AM62+AQ62+AU62+AY62+BC62+BG62+BK62+BO62+BS62+BW62+CA62+CE62 | CG62: =E62+I62+M62+Q62+U62+Y62+AC62+AG62+AK62+AO62+AS62+AW62+BA62+BE62+BI62+BM62+BQ62+BU62+BY62+CC62 | CH62: =CH61+CG62
B63: 59 | C63: =F63+J63+N63+R63+V63+Z63+AD63+AH63+AL63+AP63+AT63+AX63+BB63+BF63+BJ63+BN63+BR63+BV63+BZ63+CD63 | D63: =G62 | E63: =IF(D63>0.005,D63*Debts!D8/12,0) | F63: 0 | G63: =MAX(0,D63+E63-F63) | H63: =K62 | I63: =IF(H63>0.005,H63*Debts!D9/12,0) | J63: 0 | K63: =MAX(0,H63+I63-J63) | L63: =O62 | M63: =IF(L63>0.005,L63*Debts!D10/12,0) | N63: 0 | O63: =MAX(0,L63+M63-N63) | P63: =S62 | Q63: =IF(P63>0.005,P63*Debts!D11/12,0) | R63: 0 | S63: =MAX(0,P63+Q63-R63) | T63: =W62 | U63: =IF(T63>0.005,T63*Debts!D12/12,0) | V63: 0 | W63: =MAX(0,T63+U63-V63) | X63: =AA62 | Y63: =IF(X63>0.005,X63*Debts!D13/12,0) | Z63: 0 | AA63: =MAX(0,X63+Y63-Z63) | AB63: =AE62 | AC63: =IF(AB63>0.005,AB63*Debts!D14/12,0) | AD63: 0 | AE63: =MAX(0,AB63+AC63-AD63) | AF63: =AI62 | AG63: =IF(AF63>0.005,AF63*Debts!D15/12,0) | AH63: 0 | AI63: =MAX(0,AF63+AG63-AH63) | AJ63: =AM62 | AK63: =IF(AJ63>0.005,AJ63*Debts!D16/12,0) | AL63: 0 | AM63: =MAX(0,AJ63+AK63-AL63) | AN63: =AQ62 | AO63: =IF(AN63>0.005,AN63*Debts!D17/12,0) | AP63: 0 | AQ63: =MAX(0,AN63+AO63-AP63) | AR63: =AU62 | AS63: =IF(AR63>0.005,AR63*Debts!D18/12,0) | AT63: 0 | AU63: =MAX(0,AR63+AS63-AT63) | AV63: =AY62 | AW63: =IF(AV63>0.005,AV63*Debts!D19/12,0) | AX63: 0 | AY63: =MAX(0,AV63+AW63-AX63) | AZ63: =BC62 | BA63: =IF(AZ63>0.005,AZ63*Debts!D20/12,0) | BB63: 0 | BC63: =MAX(0,AZ63+BA63-BB63) | BD63: =BG62 | BE63: =IF(BD63>0.005,BD63*Debts!D21/12,0) | BF63: 0 | BG63: =MAX(0,BD63+BE63-BF63) | BH63: =BK62 | BI63: =IF(BH63>0.005,BH63*Debts!D22/12,0) | BJ63: 0 | BK63: =MAX(0,BH63+BI63-BJ63) | BL63: =BO62 | BM63: =IF(BL63>0.005,BL63*Debts!D23/12,0) | BN63: 0 | BO63: =MAX(0,BL63+BM63-BN63) | BP63: =BS62 | BQ63: =IF(BP63>0.005,BP63*Debts!D24/12,0) | BR63: 0 | BS63: =MAX(0,BP63+BQ63-BR63) | BT63: =BW62 | BU63: =IF(BT63>0.005,BT63*Debts!D25/12,0) | BV63: 0 | BW63: =MAX(0,BT63+BU63-BV63) | BX63: =CA62 | BY63: =IF(BX63>0.005,BX63*Debts!D26/12,0) | BZ63: 0 | CA63: =MAX(0,BX63+BY63-BZ63) | CB63: =CE62 | CC63: =IF(CB63>0.005,CB63*Debts!D27/12,0) | CD63: 0 | CE63: =MAX(0,CB63+CC63-CD63) | CF63: =G63+K63+O63+S63+W63+AA63+AE63+AI63+AM63+AQ63+AU63+AY63+BC63+BG63+BK63+BO63+BS63+BW63+CA63+CE63 | CG63: =E63+I63+M63+Q63+U63+Y63+AC63+AG63+AK63+AO63+AS63+AW63+BA63+BE63+BI63+BM63+BQ63+BU63+BY63+CC63 | CH63: =CH62+CG63
B64: 60 | C64: =F64+J64+N64+R64+V64+Z64+AD64+AH64+AL64+AP64+AT64+AX64+BB64+BF64+BJ64+BN64+BR64+BV64+BZ64+CD64 | D64: =G63 | E64: =IF(D64>0.005,D64*Debts!D8/12,0) | F64: 0 | G64: =MAX(0,D64+E64-F64) | H64: =K63 | I64: =IF(H64>0.005,H64*Debts!D9/12,0) | J64: 0 | K64: =MAX(0,H64+I64-J64) | L64: =O63 | M64: =IF(L64>0.005,L64*Debts!D10/12,0) | N64: 0 | O64: =MAX(0,L64+M64-N64) | P64: =S63 | Q64: =IF(P64>0.005,P64*Debts!D11/12,0) | R64: 0 | S64: =MAX(0,P64+Q64-R64) | T64: =W63 | U64: =IF(T64>0.005,T64*Debts!D12/12,0) | V64: 0 | W64: =MAX(0,T64+U64-V64) | X64: =AA63 | Y64: =IF(X64>0.005,X64*Debts!D13/12,0) | Z64: 0 | AA64: =MAX(0,X64+Y64-Z64) | AB64: =AE63 | AC64: =IF(AB64>0.005,AB64*Debts!D14/12,0) | AD64: 0 | AE64: =MAX(0,AB64+AC64-AD64) | AF64: =AI63 | AG64: =IF(AF64>0.005,AF64*Debts!D15/12,0) | AH64: 0 | AI64: =MAX(0,AF64+AG64-AH64) | AJ64: =AM63 | AK64: =IF(AJ64>0.005,AJ64*Debts!D16/12,0) | AL64: 0 | AM64: =MAX(0,AJ64+AK64-AL64) | AN64: =AQ63 | AO64: =IF(AN64>0.005,AN64*Debts!D17/12,0) | AP64: 0 | AQ64: =MAX(0,AN64+AO64-AP64) | AR64: =AU63 | AS64: =IF(AR64>0.005,AR64*Debts!D18/12,0) | AT64: 0 | AU64: =MAX(0,AR64+AS64-AT64) | AV64: =AY63 | AW64: =IF(AV64>0.005,AV64*Debts!D19/12,0) | AX64: 0 | AY64: =MAX(0,AV64+AW64-AX64) | AZ64: =BC63 | BA64: =IF(AZ64>0.005,AZ64*Debts!D20/12,0) | BB64: 0 | BC64: =MAX(0,AZ64+BA64-BB64) | BD64: =BG63 | BE64: =IF(BD64>0.005,BD64*Debts!D21/12,0) | BF64: 0 | BG64: =MAX(0,BD64+BE64-BF64) | BH64: =BK63 | BI64: =IF(BH64>0.005,BH64*Debts!D22/12,0) | BJ64: 0 | BK64: =MAX(0,BH64+BI64-BJ64) | BL64: =BO63 | BM64: =IF(BL64>0.005,BL64*Debts!D23/12,0) | BN64: 0 | BO64: =MAX(0,BL64+BM64-BN64) | BP64: =BS63 | BQ64: =IF(BP64>0.005,BP64*Debts!D24/12,0) | BR64: 0 | BS64: =MAX(0,BP64+BQ64-BR64) | BT64: =BW63 | BU64: =IF(BT64>0.005,BT64*Debts!D25/12,0) | BV64: 0 | BW64: =MAX(0,BT64+BU64-BV64) | BX64: =CA63 | BY64: =IF(BX64>0.005,BX64*Debts!D26/12,0) | BZ64: 0 | CA64: =MAX(0,BX64+BY64-BZ64) | CB64: =CE63 | CC64: =IF(CB64>0.005,CB64*Debts!D27/12,0) | CD64: 0 | CE64: =MAX(0,CB64+CC64-CD64) | CF64: =G64+K64+O64+S64+W64+AA64+AE64+AI64+AM64+AQ64+AU64+AY64+BC64+BG64+BK64+BO64+BS64+BW64+CA64+CE64 | CG64: =E64+I64+M64+Q64+U64+Y64+AC64+AG64+AK64+AO64+AS64+AW64+BA64+BE64+BI64+BM64+BQ64+BU64+BY64+CC64 | CH64: =CH63+CG64
B65: 61 | C65: =F65+J65+N65+R65+V65+Z65+AD65+AH65+AL65+AP65+AT65+AX65+BB65+BF65+BJ65+BN65+BR65+BV65+BZ65+CD65 | D65: =G64 | E65: =IF(D65>0.005,D65*Debts!D8/12,0) | F65: 0 | G65: =MAX(0,D65+E65-F65) | H65: =K64 | I65: =IF(H65>0.005,H65*Debts!D9/12,0) | J65: 0 | K65: =MAX(0,H65+I65-J65) | L65: =O64 | M65: =IF(L65>0.005,L65*Debts!D10/12,0) | N65: 0 | O65: =MAX(0,L65+M65-N65) | P65: =S64 | Q65: =IF(P65>0.005,P65*Debts!D11/12,0) | R65: 0 | S65: =MAX(0,P65+Q65-R65) | T65: =W64 | U65: =IF(T65>0.005,T65*Debts!D12/12,0) | V65: 0 | W65: =MAX(0,T65+U65-V65) | X65: =AA64 | Y65: =IF(X65>0.005,X65*Debts!D13/12,0) | Z65: 0 | AA65: =MAX(0,X65+Y65-Z65) | AB65: =AE64 | AC65: =IF(AB65>0.005,AB65*Debts!D14/12,0) | AD65: 0 | AE65: =MAX(0,AB65+AC65-AD65) | AF65: =AI64 | AG65: =IF(AF65>0.005,AF65*Debts!D15/12,0) | AH65: 0 | AI65: =MAX(0,AF65+AG65-AH65) | AJ65: =AM64 | AK65: =IF(AJ65>0.005,AJ65*Debts!D16/12,0) | AL65: 0 | AM65: =MAX(0,AJ65+AK65-AL65) | AN65: =AQ64 | AO65: =IF(AN65>0.005,AN65*Debts!D17/12,0) | AP65: 0 | AQ65: =MAX(0,AN65+AO65-AP65) | AR65: =AU64 | AS65: =IF(AR65>0.005,AR65*Debts!D18/12,0) | AT65: 0 | AU65: =MAX(0,AR65+AS65-AT65) | AV65: =AY64 | AW65: =IF(AV65>0.005,AV65*Debts!D19/12,0) | AX65: 0 | AY65: =MAX(0,AV65+AW65-AX65) | AZ65: =BC64 | BA65: =IF(AZ65>0.005,AZ65*Debts!D20/12,0) | BB65: 0 | BC65: =MAX(0,AZ65+BA65-BB65) | BD65: =BG64 | BE65: =IF(BD65>0.005,BD65*Debts!D21/12,0) | BF65: 0 | BG65: =MAX(0,BD65+BE65-BF65) | BH65: =BK64 | BI65: =IF(BH65>0.005,BH65*Debts!D22/12,0) | BJ65: 0 | BK65: =MAX(0,BH65+BI65-BJ65) | BL65: =BO64 | BM65: =IF(BL65>0.005,BL65*Debts!D23/12,0) | BN65: 0 | BO65: =MAX(0,BL65+BM65-BN65) | BP65: =BS64 | BQ65: =IF(BP65>0.005,BP65*Debts!D24/12,0) | BR65: 0 | BS65: =MAX(0,BP65+BQ65-BR65) | BT65: =BW64 | BU65: =IF(BT65>0.005,BT65*Debts!D25/12,0) | BV65: 0 | BW65: =MAX(0,BT65+BU65-BV65) | BX65: =CA64 | BY65: =IF(BX65>0.005,BX65*Debts!D26/12,0) | BZ65: 0 | CA65: =MAX(0,BX65+BY65-BZ65) | CB65: =CE64 | CC65: =IF(CB65>0.005,CB65*Debts!D27/12,0) | CD65: 0 | CE65: =MAX(0,CB65+CC65-CD65) | CF65: =G65+K65+O65+S65+W65+AA65+AE65+AI65+AM65+AQ65+AU65+AY65+BC65+BG65+BK65+BO65+BS65+BW65+CA65+CE65 | CG65: =E65+I65+M65+Q65+U65+Y65+AC65+AG65+AK65+AO65+AS65+AW65+BA65+BE65+BI65+BM65+BQ65+BU65+BY65+CC65 | CH65: =CH64+CG65
B66: 62 | C66: =F66+J66+N66+R66+V66+Z66+AD66+AH66+AL66+AP66+AT66+AX66+BB66+BF66+BJ66+BN66+BR66+BV66+BZ66+CD66 | D66: =G65 | E66: =IF(D66>0.005,D66*Debts!D8/12,0) | F66: 0 | G66: =MAX(0,D66+E66-F66) | H66: =K65 | I66: =IF(H66>0.005,H66*Debts!D9/12,0) | J66: 0 | K66: =MAX(0,H66+I66-J66) | L66: =O65 | M66: =IF(L66>0.005,L66*Debts!D10/12,0) | N66: 0 | O66: =MAX(0,L66+M66-N66) | P66: =S65 | Q66: =IF(P66>0.005,P66*Debts!D11/12,0) | R66: 0 | S66: =MAX(0,P66+Q66-R66) | T66: =W65 | U66: =IF(T66>0.005,T66*Debts!D12/12,0) | V66: 0 | W66: =MAX(0,T66+U66-V66) | X66: =AA65 | Y66: =IF(X66>0.005,X66*Debts!D13/12,0) | Z66: 0 | AA66: =MAX(0,X66+Y66-Z66) | AB66: =AE65 | AC66: =IF(AB66>0.005,AB66*Debts!D14/12,0) | AD66: 0 | AE66: =MAX(0,AB66+AC66-AD66) | AF66: =AI65 | AG66: =IF(AF66>0.005,AF66*Debts!D15/12,0) | AH66: 0 | AI66: =MAX(0,AF66+AG66-AH66) | AJ66: =AM65 | AK66: =IF(AJ66>0.005,AJ66*Debts!D16/12,0) | AL66: 0 | AM66: =MAX(0,AJ66+AK66-AL66) | AN66: =AQ65 | AO66: =IF(AN66>0.005,AN66*Debts!D17/12,0) | AP66: 0 | AQ66: =MAX(0,AN66+AO66-AP66) | AR66: =AU65 | AS66: =IF(AR66>0.005,AR66*Debts!D18/12,0) | AT66: 0 | AU66: =MAX(0,AR66+AS66-AT66) | AV66: =AY65 | AW66: =IF(AV66>0.005,AV66*Debts!D19/12,0) | AX66: 0 | AY66: =MAX(0,AV66+AW66-AX66) | AZ66: =BC65 | BA66: =IF(AZ66>0.005,AZ66*Debts!D20/12,0) | BB66: 0 | BC66: =MAX(0,AZ66+BA66-BB66) | BD66: =BG65 | BE66: =IF(BD66>0.005,BD66*Debts!D21/12,0) | BF66: 0 | BG66: =MAX(0,BD66+BE66-BF66) | BH66: =BK65 | BI66: =IF(BH66>0.005,BH66*Debts!D22/12,0) | BJ66: 0 | BK66: =MAX(0,BH66+BI66-BJ66) | BL66: =BO65 | BM66: =IF(BL66>0.005,BL66*Debts!D23/12,0) | BN66: 0 | BO66: =MAX(0,BL66+BM66-BN66) | BP66: =BS65 | BQ66: =IF(BP66>0.005,BP66*Debts!D24/12,0) | BR66: 0 | BS66: =MAX(0,BP66+BQ66-BR66) | BT66: =BW65 | BU66: =IF(BT66>0.005,BT66*Debts!D25/12,0) | BV66: 0 | BW66: =MAX(0,BT66+BU66-BV66) | BX66: =CA65 | BY66: =IF(BX66>0.005,BX66*Debts!D26/12,0) | BZ66: 0 | CA66: =MAX(0,BX66+BY66-BZ66) | CB66: =CE65 | CC66: =IF(CB66>0.005,CB66*Debts!D27/12,0) | CD66: 0 | CE66: =MAX(0,CB66+CC66-CD66) | CF66: =G66+K66+O66+S66+W66+AA66+AE66+AI66+AM66+AQ66+AU66+AY66+BC66+BG66+BK66+BO66+BS66+BW66+CA66+CE66 | CG66: =E66+I66+M66+Q66+U66+Y66+AC66+AG66+AK66+AO66+AS66+AW66+BA66+BE66+BI66+BM66+BQ66+BU66+BY66+CC66 | CH66: =CH65+CG66
B67: 63 | C67: =F67+J67+N67+R67+V67+Z67+AD67+AH67+AL67+AP67+AT67+AX67+BB67+BF67+BJ67+BN67+BR67+BV67+BZ67+CD67 | D67: =G66 | E67: =IF(D67>0.005,D67*Debts!D8/12,0) | F67: 0 | G67: =MAX(0,D67+E67-F67) | H67: =K66 | I67: =IF(H67>0.005,H67*Debts!D9/12,0) | J67: 0 | K67: =MAX(0,H67+I67-J67) | L67: =O66 | M67: =IF(L67>0.005,L67*Debts!D10/12,0) | N67: 0 | O67: =MAX(0,L67+M67-N67) | P67: =S66 | Q67: =IF(P67>0.005,P67*Debts!D11/12,0) | R67: 0 | S67: =MAX(0,P67+Q67-R67) | T67: =W66 | U67: =IF(T67>0.005,T67*Debts!D12/12,0) | V67: 0 | W67: =MAX(0,T67+U67-V67) | X67: =AA66 | Y67: =IF(X67>0.005,X67*Debts!D13/12,0) | Z67: 0 | AA67: =MAX(0,X67+Y67-Z67) | AB67: =AE66 | AC67: =IF(AB67>0.005,AB67*Debts!D14/12,0) | AD67: 0 | AE67: =MAX(0,AB67+AC67-AD67) | AF67: =AI66 | AG67: =IF(AF67>0.005,AF67*Debts!D15/12,0) | AH67: 0 | AI67: =MAX(0,AF67+AG67-AH67) | AJ67: =AM66 | AK67: =IF(AJ67>0.005,AJ67*Debts!D16/12,0) | AL67: 0 | AM67: =MAX(0,AJ67+AK67-AL67) | AN67: =AQ66 | AO67: =IF(AN67>0.005,AN67*Debts!D17/12,0) | AP67: 0 | AQ67: =MAX(0,AN67+AO67-AP67) | AR67: =AU66 | AS67: =IF(AR67>0.005,AR67*Debts!D18/12,0) | AT67: 0 | AU67: =MAX(0,AR67+AS67-AT67) | AV67: =AY66 | AW67: =IF(AV67>0.005,AV67*Debts!D19/12,0) | AX67: 0 | AY67: =MAX(0,AV67+AW67-AX67) | AZ67: =BC66 | BA67: =IF(AZ67>0.005,AZ67*Debts!D20/12,0) | BB67: 0 | BC67: =MAX(0,AZ67+BA67-BB67) | BD67: =BG66 | BE67: =IF(BD67>0.005,BD67*Debts!D21/12,0) | BF67: 0 | BG67: =MAX(0,BD67+BE67-BF67) | BH67: =BK66 | BI67: =IF(BH67>0.005,BH67*Debts!D22/12,0) | BJ67: 0 | BK67: =MAX(0,BH67+BI67-BJ67) | BL67: =BO66 | BM67: =IF(BL67>0.005,BL67*Debts!D23/12,0) | BN67: 0 | BO67: =MAX(0,BL67+BM67-BN67) | BP67: =BS66 | BQ67: =IF(BP67>0.005,BP67*Debts!D24/12,0) | BR67: 0 | BS67: =MAX(0,BP67+BQ67-BR67) | BT67: =BW66 | BU67: =IF(BT67>0.005,BT67*Debts!D25/12,0) | BV67: 0 | BW67: =MAX(0,BT67+BU67-BV67) | BX67: =CA66 | BY67: =IF(BX67>0.005,BX67*Debts!D26/12,0) | BZ67: 0 | CA67: =MAX(0,BX67+BY67-BZ67) | CB67: =CE66 | CC67: =IF(CB67>0.005,CB67*Debts!D27/12,0) | CD67: 0 | CE67: =MAX(0,CB67+CC67-CD67) | CF67: =G67+K67+O67+S67+W67+AA67+AE67+AI67+AM67+AQ67+AU67+AY67+BC67+BG67+BK67+BO67+BS67+BW67+CA67+CE67 | CG67: =E67+I67+M67+Q67+U67+Y67+AC67+AG67+AK67+AO67+AS67+AW67+BA67+BE67+BI67+BM67+BQ67+BU67+BY67+CC67 | CH67: =CH66+CG67
B68: 64 | C68: =F68+J68+N68+R68+V68+Z68+AD68+AH68+AL68+AP68+AT68+AX68+BB68+BF68+BJ68+BN68+BR68+BV68+BZ68+CD68 | D68: =G67 | E68: =IF(D68>0.005,D68*Debts!D8/12,0) | F68: 0 | G68: =MAX(0,D68+E68-F68) | H68: =K67 | I68: =IF(H68>0.005,H68*Debts!D9/12,0) | J68: 0 | K68: =MAX(0,H68+I68-J68) | L68: =O67 | M68: =IF(L68>0.005,L68*Debts!D10/12,0) | N68: 0 | O68: =MAX(0,L68+M68-N68) | P68: =S67 | Q68: =IF(P68>0.005,P68*Debts!D11/12,0) | R68: 0 | S68: =MAX(0,P68+Q68-R68) | T68: =W67 | U68: =IF(T68>0.005,T68*Debts!D12/12,0) | V68: 0 | W68: =MAX(0,T68+U68-V68) | X68: =AA67 | Y68: =IF(X68>0.005,X68*Debts!D13/12,0) | Z68: 0 | AA68: =MAX(0,X68+Y68-Z68) | AB68: =AE67 | AC68: =IF(AB68>0.005,AB68*Debts!D14/12,0) | AD68: 0 | AE68: =MAX(0,AB68+AC68-AD68) | AF68: =AI67 | AG68: =IF(AF68>0.005,AF68*Debts!D15/12,0) | AH68: 0 | AI68: =MAX(0,AF68+AG68-AH68) | AJ68: =AM67 | AK68: =IF(AJ68>0.005,AJ68*Debts!D16/12,0) | AL68: 0 | AM68: =MAX(0,AJ68+AK68-AL68) | AN68: =AQ67 | AO68: =IF(AN68>0.005,AN68*Debts!D17/12,0) | AP68: 0 | AQ68: =MAX(0,AN68+AO68-AP68) | AR68: =AU67 | AS68: =IF(AR68>0.005,AR68*Debts!D18/12,0) | AT68: 0 | AU68: =MAX(0,AR68+AS68-AT68) | AV68: =AY67 | AW68: =IF(AV68>0.005,AV68*Debts!D19/12,0) | AX68: 0 | AY68: =MAX(0,AV68+AW68-AX68) | AZ68: =BC67 | BA68: =IF(AZ68>0.005,AZ68*Debts!D20/12,0) | BB68: 0 | BC68: =MAX(0,AZ68+BA68-BB68) | BD68: =BG67 | BE68: =IF(BD68>0.005,BD68*Debts!D21/12,0) | BF68: 0 | BG68: =MAX(0,BD68+BE68-BF68) | BH68: =BK67 | BI68: =IF(BH68>0.005,BH68*Debts!D22/12,0) | BJ68: 0 | BK68: =MAX(0,BH68+BI68-BJ68) | BL68: =BO67 | BM68: =IF(BL68>0.005,BL68*Debts!D23/12,0) | BN68: 0 | BO68: =MAX(0,BL68+BM68-BN68) | BP68: =BS67 | BQ68: =IF(BP68>0.005,BP68*Debts!D24/12,0) | BR68: 0 | BS68: =MAX(0,BP68+BQ68-BR68) | BT68: =BW67 | BU68: =IF(BT68>0.005,BT68*Debts!D25/12,0) | BV68: 0 | BW68: =MAX(0,BT68+BU68-BV68) | BX68: =CA67 | BY68: =IF(BX68>0.005,BX68*Debts!D26/12,0) | BZ68: 0 | CA68: =MAX(0,BX68+BY68-BZ68) | CB68: =CE67 | CC68: =IF(CB68>0.005,CB68*Debts!D27/12,0) | CD68: 0 | CE68: =MAX(0,CB68+CC68-CD68) | CF68: =G68+K68+O68+S68+W68+AA68+AE68+AI68+AM68+AQ68+AU68+AY68+BC68+BG68+BK68+BO68+BS68+BW68+CA68+CE68 | CG68: =E68+I68+M68+Q68+U68+Y68+AC68+AG68+AK68+AO68+AS68+AW68+BA68+BE68+BI68+BM68+BQ68+BU68+BY68+CC68 | CH68: =CH67+CG68
B69: 65 | C69: =F69+J69+N69+R69+V69+Z69+AD69+AH69+AL69+AP69+AT69+AX69+BB69+BF69+BJ69+BN69+BR69+BV69+BZ69+CD69 | D69: =G68 | E69: =IF(D69>0.005,D69*Debts!D8/12,0) | F69: 0 | G69: =MAX(0,D69+E69-F69) | H69: =K68 | I69: =IF(H69>0.005,H69*Debts!D9/12,0) | J69: 0 | K69: =MAX(0,H69+I69-J69) | L69: =O68 | M69: =IF(L69>0.005,L69*Debts!D10/12,0) | N69: 0 | O69: =MAX(0,L69+M69-N69) | P69: =S68 | Q69: =IF(P69>0.005,P69*Debts!D11/12,0) | R69: 0 | S69: =MAX(0,P69+Q69-R69) | T69: =W68 | U69: =IF(T69>0.005,T69*Debts!D12/12,0) | V69: 0 | W69: =MAX(0,T69+U69-V69) | X69: =AA68 | Y69: =IF(X69>0.005,X69*Debts!D13/12,0) | Z69: 0 | AA69: =MAX(0,X69+Y69-Z69) | AB69: =AE68 | AC69: =IF(AB69>0.005,AB69*Debts!D14/12,0) | AD69: 0 | AE69: =MAX(0,AB69+AC69-AD69) | AF69: =AI68 | AG69: =IF(AF69>0.005,AF69*Debts!D15/12,0) | AH69: 0 | AI69: =MAX(0,AF69+AG69-AH69) | AJ69: =AM68 | AK69: =IF(AJ69>0.005,AJ69*Debts!D16/12,0) | AL69: 0 | AM69: =MAX(0,AJ69+AK69-AL69) | AN69: =AQ68 | AO69: =IF(AN69>0.005,AN69*Debts!D17/12,0) | AP69: 0 | AQ69: =MAX(0,AN69+AO69-AP69) | AR69: =AU68 | AS69: =IF(AR69>0.005,AR69*Debts!D18/12,0) | AT69: 0 | AU69: =MAX(0,AR69+AS69-AT69) | AV69: =AY68 | AW69: =IF(AV69>0.005,AV69*Debts!D19/12,0) | AX69: 0 | AY69: =MAX(0,AV69+AW69-AX69) | AZ69: =BC68 | BA69: =IF(AZ69>0.005,AZ69*Debts!D20/12,0) | BB69: 0 | BC69: =MAX(0,AZ69+BA69-BB69) | BD69: =BG68 | BE69: =IF(BD69>0.005,BD69*Debts!D21/12,0) | BF69: 0 | BG69: =MAX(0,BD69+BE69-BF69) | BH69: =BK68 | BI69: =IF(BH69>0.005,BH69*Debts!D22/12,0) | BJ69: 0 | BK69: =MAX(0,BH69+BI69-BJ69) | BL69: =BO68 | BM69: =IF(BL69>0.005,BL69*Debts!D23/12,0) | BN69: 0 | BO69: =MAX(0,BL69+BM69-BN69) | BP69: =BS68 | BQ69: =IF(BP69>0.005,BP69*Debts!D24/12,0) | BR69: 0 | BS69: =MAX(0,BP69+BQ69-BR69) | BT69: =BW68 | BU69: =IF(BT69>0.005,BT69*Debts!D25/12,0) | BV69: 0 | BW69: =MAX(0,BT69+BU69-BV69) | BX69: =CA68 | BY69: =IF(BX69>0.005,BX69*Debts!D26/12,0) | BZ69: 0 | CA69: =MAX(0,BX69+BY69-BZ69) | CB69: =CE68 | CC69: =IF(CB69>0.005,CB69*Debts!D27/12,0) | CD69: 0 | CE69: =MAX(0,CB69+CC69-CD69) | CF69: =G69+K69+O69+S69+W69+AA69+AE69+AI69+AM69+AQ69+AU69+AY69+BC69+BG69+BK69+BO69+BS69+BW69+CA69+CE69 | CG69: =E69+I69+M69+Q69+U69+Y69+AC69+AG69+AK69+AO69+AS69+AW69+BA69+BE69+BI69+BM69+BQ69+BU69+BY69+CC69 | CH69: =CH68+CG69
B70: 66 | C70: =F70+J70+N70+R70+V70+Z70+AD70+AH70+AL70+AP70+AT70+AX70+BB70+BF70+BJ70+BN70+BR70+BV70+BZ70+CD70 | D70: =G69 | E70: =IF(D70>0.005,D70*Debts!D8/12,0) | F70: 0 | G70: =MAX(0,D70+E70-F70) | H70: =K69 | I70: =IF(H70>0.005,H70*Debts!D9/12,0) | J70: 0 | K70: =MAX(0,H70+I70-J70) | L70: =O69 | M70: =IF(L70>0.005,L70*Debts!D10/12,0) | N70: 0 | O70: =MAX(0,L70+M70-N70) | P70: =S69 | Q70: =IF(P70>0.005,P70*Debts!D11/12,0) | R70: 0 | S70: =MAX(0,P70+Q70-R70) | T70: =W69 | U70: =IF(T70>0.005,T70*Debts!D12/12,0) | V70: 0 | W70: =MAX(0,T70+U70-V70) | X70: =AA69 | Y70: =IF(X70>0.005,X70*Debts!D13/12,0) | Z70: 0 | AA70: =MAX(0,X70+Y70-Z70) | AB70: =AE69 | AC70: =IF(AB70>0.005,AB70*Debts!D14/12,0) | AD70: 0 | AE70: =MAX(0,AB70+AC70-AD70) | AF70: =AI69 | AG70: =IF(AF70>0.005,AF70*Debts!D15/12,0) | AH70: 0 | AI70: =MAX(0,AF70+AG70-AH70) | AJ70: =AM69 | AK70: =IF(AJ70>0.005,AJ70*Debts!D16/12,0) | AL70: 0 | AM70: =MAX(0,AJ70+AK70-AL70) | AN70: =AQ69 | AO70: =IF(AN70>0.005,AN70*Debts!D17/12,0) | AP70: 0 | AQ70: =MAX(0,AN70+AO70-AP70) | AR70: =AU69 | AS70: =IF(AR70>0.005,AR70*Debts!D18/12,0) | AT70: 0 | AU70: =MAX(0,AR70+AS70-AT70) | AV70: =AY69 | AW70: =IF(AV70>0.005,AV70*Debts!D19/12,0) | AX70: 0 | AY70: =MAX(0,AV70+AW70-AX70) | AZ70: =BC69 | BA70: =IF(AZ70>0.005,AZ70*Debts!D20/12,0) | BB70: 0 | BC70: =MAX(0,AZ70+BA70-BB70) | BD70: =BG69 | BE70: =IF(BD70>0.005,BD70*Debts!D21/12,0) | BF70: 0 | BG70: =MAX(0,BD70+BE70-BF70) | BH70: =BK69 | BI70: =IF(BH70>0.005,BH70*Debts!D22/12,0) | BJ70: 0 | BK70: =MAX(0,BH70+BI70-BJ70) | BL70: =BO69 | BM70: =IF(BL70>0.005,BL70*Debts!D23/12,0) | BN70: 0 | BO70: =MAX(0,BL70+BM70-BN70) | BP70: =BS69 | BQ70: =IF(BP70>0.005,BP70*Debts!D24/12,0) | BR70: 0 | BS70: =MAX(0,BP70+BQ70-BR70) | BT70: =BW69 | BU70: =IF(BT70>0.005,BT70*Debts!D25/12,0) | BV70: 0 | BW70: =MAX(0,BT70+BU70-BV70) | BX70: =CA69 | BY70: =IF(BX70>0.005,BX70*Debts!D26/12,0) | BZ70: 0 | CA70: =MAX(0,BX70+BY70-BZ70) | CB70: =CE69 | CC70: =IF(CB70>0.005,CB70*Debts!D27/12,0) | CD70: 0 | CE70: =MAX(0,CB70+CC70-CD70) | CF70: =G70+K70+O70+S70+W70+AA70+AE70+AI70+AM70+AQ70+AU70+AY70+BC70+BG70+BK70+BO70+BS70+BW70+CA70+CE70 | CG70: =E70+I70+M70+Q70+U70+Y70+AC70+AG70+AK70+AO70+AS70+AW70+BA70+BE70+BI70+BM70+BQ70+BU70+BY70+CC70 | CH70: =CH69+CG70
B71: 67 | C71: =F71+J71+N71+R71+V71+Z71+AD71+AH71+AL71+AP71+AT71+AX71+BB71+BF71+BJ71+BN71+BR71+BV71+BZ71+CD71 | D71: =G70 | E71: =IF(D71>0.005,D71*Debts!D8/12,0) | F71: 0 | G71: =MAX(0,D71+E71-F71) | H71: =K70 | I71: =IF(H71>0.005,H71*Debts!D9/12,0) | J71: 0 | K71: =MAX(0,H71+I71-J71) | L71: =O70 | M71: =IF(L71>0.005,L71*Debts!D10/12,0) | N71: 0 | O71: =MAX(0,L71+M71-N71) | P71: =S70 | Q71: =IF(P71>0.005,P71*Debts!D11/12,0) | R71: 0 | S71: =MAX(0,P71+Q71-R71) | T71: =W70 | U71: =IF(T71>0.005,T71*Debts!D12/12,0) | V71: 0 | W71: =MAX(0,T71+U71-V71) | X71: =AA70 | Y71: =IF(X71>0.005,X71*Debts!D13/12,0) | Z71: 0 | AA71: =MAX(0,X71+Y71-Z71) | AB71: =AE70 | AC71: =IF(AB71>0.005,AB71*Debts!D14/12,0) | AD71: 0 | AE71: =MAX(0,AB71+AC71-AD71) | AF71: =AI70 | AG71: =IF(AF71>0.005,AF71*Debts!D15/12,0) | AH71: 0 | AI71: =MAX(0,AF71+AG71-AH71) | AJ71: =AM70 | AK71: =IF(AJ71>0.005,AJ71*Debts!D16/12,0) | AL71: 0 | AM71: =MAX(0,AJ71+AK71-AL71) | AN71: =AQ70 | AO71: =IF(AN71>0.005,AN71*Debts!D17/12,0) | AP71: 0 | AQ71: =MAX(0,AN71+AO71-AP71) | AR71: =AU70 | AS71: =IF(AR71>0.005,AR71*Debts!D18/12,0) | AT71: 0 | AU71: =MAX(0,AR71+AS71-AT71) | AV71: =AY70 | AW71: =IF(AV71>0.005,AV71*Debts!D19/12,0) | AX71: 0 | AY71: =MAX(0,AV71+AW71-AX71) | AZ71: =BC70 | BA71: =IF(AZ71>0.005,AZ71*Debts!D20/12,0) | BB71: 0 | BC71: =MAX(0,AZ71+BA71-BB71) | BD71: =BG70 | BE71: =IF(BD71>0.005,BD71*Debts!D21/12,0) | BF71: 0 | BG71: =MAX(0,BD71+BE71-BF71) | BH71: =BK70 | BI71: =IF(BH71>0.005,BH71*Debts!D22/12,0) | BJ71: 0 | BK71: =MAX(0,BH71+BI71-BJ71) | BL71: =BO70 | BM71: =IF(BL71>0.005,BL71*Debts!D23/12,0) | BN71: 0 | BO71: =MAX(0,BL71+BM71-BN71) | BP71: =BS70 | BQ71: =IF(BP71>0.005,BP71*Debts!D24/12,0) | BR71: 0 | BS71: =MAX(0,BP71+BQ71-BR71) | BT71: =BW70 | BU71: =IF(BT71>0.005,BT71*Debts!D25/12,0) | BV71: 0 | BW71: =MAX(0,BT71+BU71-BV71) | BX71: =CA70 | BY71: =IF(BX71>0.005,BX71*Debts!D26/12,0) | BZ71: 0 | CA71: =MAX(0,BX71+BY71-BZ71) | CB71: =CE70 | CC71: =IF(CB71>0.005,CB71*Debts!D27/12,0) | CD71: 0 | CE71: =MAX(0,CB71+CC71-CD71) | CF71: =G71+K71+O71+S71+W71+AA71+AE71+AI71+AM71+AQ71+AU71+AY71+BC71+BG71+BK71+BO71+BS71+BW71+CA71+CE71 | CG71: =E71+I71+M71+Q71+U71+Y71+AC71+AG71+AK71+AO71+AS71+AW71+BA71+BE71+BI71+BM71+BQ71+BU71+BY71+CC71 | CH71: =CH70+CG71
B72: 68 | C72: =F72+J72+N72+R72+V72+Z72+AD72+AH72+AL72+AP72+AT72+AX72+BB72+BF72+BJ72+BN72+BR72+BV72+BZ72+CD72 | D72: =G71 | E72: =IF(D72>0.005,D72*Debts!D8/12,0) | F72: 0 | G72: =MAX(0,D72+E72-F72) | H72: =K71 | I72: =IF(H72>0.005,H72*Debts!D9/12,0) | J72: 0 | K72: =MAX(0,H72+I72-J72) | L72: =O71 | M72: =IF(L72>0.005,L72*Debts!D10/12,0) | N72: 0 | O72: =MAX(0,L72+M72-N72) | P72: =S71 | Q72: =IF(P72>0.005,P72*Debts!D11/12,0) | R72: 0 | S72: =MAX(0,P72+Q72-R72) | T72: =W71 | U72: =IF(T72>0.005,T72*Debts!D12/12,0) | V72: 0 | W72: =MAX(0,T72+U72-V72) | X72: =AA71 | Y72: =IF(X72>0.005,X72*Debts!D13/12,0) | Z72: 0 | AA72: =MAX(0,X72+Y72-Z72) | AB72: =AE71 | AC72: =IF(AB72>0.005,AB72*Debts!D14/12,0) | AD72: 0 | AE72: =MAX(0,AB72+AC72-AD72) | AF72: =AI71 | AG72: =IF(AF72>0.005,AF72*Debts!D15/12,0) | AH72: 0 | AI72: =MAX(0,AF72+AG72-AH72) | AJ72: =AM71 | AK72: =IF(AJ72>0.005,AJ72*Debts!D16/12,0) | AL72: 0 | AM72: =MAX(0,AJ72+AK72-AL72) | AN72: =AQ71 | AO72: =IF(AN72>0.005,AN72*Debts!D17/12,0) | AP72: 0 | AQ72: =MAX(0,AN72+AO72-AP72) | AR72: =AU71 | AS72: =IF(AR72>0.005,AR72*Debts!D18/12,0) | AT72: 0 | AU72: =MAX(0,AR72+AS72-AT72) | AV72: =AY71 | AW72: =IF(AV72>0.005,AV72*Debts!D19/12,0) | AX72: 0 | AY72: =MAX(0,AV72+AW72-AX72) | AZ72: =BC71 | BA72: =IF(AZ72>0.005,AZ72*Debts!D20/12,0) | BB72: 0 | BC72: =MAX(0,AZ72+BA72-BB72) | BD72: =BG71 | BE72: =IF(BD72>0.005,BD72*Debts!D21/12,0) | BF72: 0 | BG72: =MAX(0,BD72+BE72-BF72) | BH72: =BK71 | BI72: =IF(BH72>0.005,BH72*Debts!D22/12,0) | BJ72: 0 | BK72: =MAX(0,BH72+BI72-BJ72) | BL72: =BO71 | BM72: =IF(BL72>0.005,BL72*Debts!D23/12,0) | BN72: 0 | BO72: =MAX(0,BL72+BM72-BN72) | BP72: =BS71 | BQ72: =IF(BP72>0.005,BP72*Debts!D24/12,0) | BR72: 0 | BS72: =MAX(0,BP72+BQ72-BR72) | BT72: =BW71 | BU72: =IF(BT72>0.005,BT72*Debts!D25/12,0) | BV72: 0 | BW72: =MAX(0,BT72+BU72-BV72) | BX72: =CA71 | BY72: =IF(BX72>0.005,BX72*Debts!D26/12,0) | BZ72: 0 | CA72: =MAX(0,BX72+BY72-BZ72) | CB72: =CE71 | CC72: =IF(CB72>0.005,CB72*Debts!D27/12,0) | CD72: 0 | CE72: =MAX(0,CB72+CC72-CD72) | CF72: =G72+K72+O72+S72+W72+AA72+AE72+AI72+AM72+AQ72+AU72+AY72+BC72+BG72+BK72+BO72+BS72+BW72+CA72+CE72 | CG72: =E72+I72+M72+Q72+U72+Y72+AC72+AG72+AK72+AO72+AS72+AW72+BA72+BE72+BI72+BM72+BQ72+BU72+BY72+CC72 | CH72: =CH71+CG72
B73: 69 | C73: =F73+J73+N73+R73+V73+Z73+AD73+AH73+AL73+AP73+AT73+AX73+BB73+BF73+BJ73+BN73+BR73+BV73+BZ73+CD73 | D73: =G72 | E73: =IF(D73>0.005,D73*Debts!D8/12,0) | F73: 0 | G73: =MAX(0,D73+E73-F73) | H73: =K72 | I73: =IF(H73>0.005,H73*Debts!D9/12,0) | J73: 0 | K73: =MAX(0,H73+I73-J73) | L73: =O72 | M73: =IF(L73>0.005,L73*Debts!D10/12,0) | N73: 0 | O73: =MAX(0,L73+M73-N73) | P73: =S72 | Q73: =IF(P73>0.005,P73*Debts!D11/12,0) | R73: 0 | S73: =MAX(0,P73+Q73-R73) | T73: =W72 | U73: =IF(T73>0.005,T73*Debts!D12/12,0) | V73: 0 | W73: =MAX(0,T73+U73-V73) | X73: =AA72 | Y73: =IF(X73>0.005,X73*Debts!D13/12,0) | Z73: 0 | AA73: =MAX(0,X73+Y73-Z73) | AB73: =AE72 | AC73: =IF(AB73>0.005,AB73*Debts!D14/12,0) | AD73: 0 | AE73: =MAX(0,AB73+AC73-AD73) | AF73: =AI72 | AG73: =IF(AF73>0.005,AF73*Debts!D15/12,0) | AH73: 0 | AI73: =MAX(0,AF73+AG73-AH73) | AJ73: =AM72 | AK73: =IF(AJ73>0.005,AJ73*Debts!D16/12,0) | AL73: 0 | AM73: =MAX(0,AJ73+AK73-AL73) | AN73: =AQ72 | AO73: =IF(AN73>0.005,AN73*Debts!D17/12,0) | AP73: 0 | AQ73: =MAX(0,AN73+AO73-AP73) | AR73: =AU72 | AS73: =IF(AR73>0.005,AR73*Debts!D18/12,0) | AT73: 0 | AU73: =MAX(0,AR73+AS73-AT73) | AV73: =AY72 | AW73: =IF(AV73>0.005,AV73*Debts!D19/12,0) | AX73: 0 | AY73: =MAX(0,AV73+AW73-AX73) | AZ73: =BC72 | BA73: =IF(AZ73>0.005,AZ73*Debts!D20/12,0) | BB73: 0 | BC73: =MAX(0,AZ73+BA73-BB73) | BD73: =BG72 | BE73: =IF(BD73>0.005,BD73*Debts!D21/12,0) | BF73: 0 | BG73: =MAX(0,BD73+BE73-BF73) | BH73: =BK72 | BI73: =IF(BH73>0.005,BH73*Debts!D22/12,0) | BJ73: 0 | BK73: =MAX(0,BH73+BI73-BJ73) | BL73: =BO72 | BM73: =IF(BL73>0.005,BL73*Debts!D23/12,0) | BN73: 0 | BO73: =MAX(0,BL73+BM73-BN73) | BP73: =BS72 | BQ73: =IF(BP73>0.005,BP73*Debts!D24/12,0) | BR73: 0 | BS73: =MAX(0,BP73+BQ73-BR73) | BT73: =BW72 | BU73: =IF(BT73>0.005,BT73*Debts!D25/12,0) | BV73: 0 | BW73: =MAX(0,BT73+BU73-BV73) | BX73: =CA72 | BY73: =IF(BX73>0.005,BX73*Debts!D26/12,0) | BZ73: 0 | CA73: =MAX(0,BX73+BY73-BZ73) | CB73: =CE72 | CC73: =IF(CB73>0.005,CB73*Debts!D27/12,0) | CD73: 0 | CE73: =MAX(0,CB73+CC73-CD73) | CF73: =G73+K73+O73+S73+W73+AA73+AE73+AI73+AM73+AQ73+AU73+AY73+BC73+BG73+BK73+BO73+BS73+BW73+CA73+CE73 | CG73: =E73+I73+M73+Q73+U73+Y73+AC73+AG73+AK73+AO73+AS73+AW73+BA73+BE73+BI73+BM73+BQ73+BU73+BY73+CC73 | CH73: =CH72+CG73
B74: 70 | C74: =F74+J74+N74+R74+V74+Z74+AD74+AH74+AL74+AP74+AT74+AX74+BB74+BF74+BJ74+BN74+BR74+BV74+BZ74+CD74 | D74: =G73 | E74: =IF(D74>0.005,D74*Debts!D8/12,0) | F74: 0 | G74: =MAX(0,D74+E74-F74) | H74: =K73 | I74: =IF(H74>0.005,H74*Debts!D9/12,0) | J74: 0 | K74: =MAX(0,H74+I74-J74) | L74: =O73 | M74: =IF(L74>0.005,L74*Debts!D10/12,0) | N74: 0 | O74: =MAX(0,L74+M74-N74) | P74: =S73 | Q74: =IF(P74>0.005,P74*Debts!D11/12,0) | R74: 0 | S74: =MAX(0,P74+Q74-R74) | T74: =W73 | U74: =IF(T74>0.005,T74*Debts!D12/12,0) | V74: 0 | W74: =MAX(0,T74+U74-V74) | X74: =AA73 | Y74: =IF(X74>0.005,X74*Debts!D13/12,0) | Z74: 0 | AA74: =MAX(0,X74+Y74-Z74) | AB74: =AE73 | AC74: =IF(AB74>0.005,AB74*Debts!D14/12,0) | AD74: 0 | AE74: =MAX(0,AB74+AC74-AD74) | AF74: =AI73 | AG74: =IF(AF74>0.005,AF74*Debts!D15/12,0) | AH74: 0 | AI74: =MAX(0,AF74+AG74-AH74) | AJ74: =AM73 | AK74: =IF(AJ74>0.005,AJ74*Debts!D16/12,0) | AL74: 0 | AM74: =MAX(0,AJ74+AK74-AL74) | AN74: =AQ73 | AO74: =IF(AN74>0.005,AN74*Debts!D17/12,0) | AP74: 0 | AQ74: =MAX(0,AN74+AO74-AP74) | AR74: =AU73 | AS74: =IF(AR74>0.005,AR74*Debts!D18/12,0) | AT74: 0 | AU74: =MAX(0,AR74+AS74-AT74) | AV74: =AY73 | AW74: =IF(AV74>0.005,AV74*Debts!D19/12,0) | AX74: 0 | AY74: =MAX(0,AV74+AW74-AX74) | AZ74: =BC73 | BA74: =IF(AZ74>0.005,AZ74*Debts!D20/12,0) | BB74: 0 | BC74: =MAX(0,AZ74+BA74-BB74) | BD74: =BG73 | BE74: =IF(BD74>0.005,BD74*Debts!D21/12,0) | BF74: 0 | BG74: =MAX(0,BD74+BE74-BF74) | BH74: =BK73 | BI74: =IF(BH74>0.005,BH74*Debts!D22/12,0) | BJ74: 0 | BK74: =MAX(0,BH74+BI74-BJ74) | BL74: =BO73 | BM74: =IF(BL74>0.005,BL74*Debts!D23/12,0) | BN74: 0 | BO74: =MAX(0,BL74+BM74-BN74) | BP74: =BS73 | BQ74: =IF(BP74>0.005,BP74*Debts!D24/12,0) | BR74: 0 | BS74: =MAX(0,BP74+BQ74-BR74) | BT74: =BW73 | BU74: =IF(BT74>0.005,BT74*Debts!D25/12,0) | BV74: 0 | BW74: =MAX(0,BT74+BU74-BV74) | BX74: =CA73 | BY74: =IF(BX74>0.005,BX74*Debts!D26/12,0) | BZ74: 0 | CA74: =MAX(0,BX74+BY74-BZ74) | CB74: =CE73 | CC74: =IF(CB74>0.005,CB74*Debts!D27/12,0) | CD74: 0 | CE74: =MAX(0,CB74+CC74-CD74) | CF74: =G74+K74+O74+S74+W74+AA74+AE74+AI74+AM74+AQ74+AU74+AY74+BC74+BG74+BK74+BO74+BS74+BW74+CA74+CE74 | CG74: =E74+I74+M74+Q74+U74+Y74+AC74+AG74+AK74+AO74+AS74+AW74+BA74+BE74+BI74+BM74+BQ74+BU74+BY74+CC74 | CH74: =CH73+CG74
B75: 71 | C75: =F75+J75+N75+R75+V75+Z75+AD75+AH75+AL75+AP75+AT75+AX75+BB75+BF75+BJ75+BN75+BR75+BV75+BZ75+CD75 | D75: =G74 | E75: =IF(D75>0.005,D75*Debts!D8/12,0) | F75: 0 | G75: =MAX(0,D75+E75-F75) | H75: =K74 | I75: =IF(H75>0.005,H75*Debts!D9/12,0) | J75: 0 | K75: =MAX(0,H75+I75-J75) | L75: =O74 | M75: =IF(L75>0.005,L75*Debts!D10/12,0) | N75: 0 | O75: =MAX(0,L75+M75-N75) | P75: =S74 | Q75: =IF(P75>0.005,P75*Debts!D11/12,0) | R75: 0 | S75: =MAX(0,P75+Q75-R75) | T75: =W74 | U75: =IF(T75>0.005,T75*Debts!D12/12,0) | V75: 0 | W75: =MAX(0,T75+U75-V75) | X75: =AA74 | Y75: =IF(X75>0.005,X75*Debts!D13/12,0) | Z75: 0 | AA75: =MAX(0,X75+Y75-Z75) | AB75: =AE74 | AC75: =IF(AB75>0.005,AB75*Debts!D14/12,0) | AD75: 0 | AE75: =MAX(0,AB75+AC75-AD75) | AF75: =AI74 | AG75: =IF(AF75>0.005,AF75*Debts!D15/12,0) | AH75: 0 | AI75: =MAX(0,AF75+AG75-AH75) | AJ75: =AM74 | AK75: =IF(AJ75>0.005,AJ75*Debts!D16/12,0) | AL75: 0 | AM75: =MAX(0,AJ75+AK75-AL75) | AN75: =AQ74 | AO75: =IF(AN75>0.005,AN75*Debts!D17/12,0) | AP75: 0 | AQ75: =MAX(0,AN75+AO75-AP75) | AR75: =AU74 | AS75: =IF(AR75>0.005,AR75*Debts!D18/12,0) | AT75: 0 | AU75: =MAX(0,AR75+AS75-AT75) | AV75: =AY74 | AW75: =IF(AV75>0.005,AV75*Debts!D19/12,0) | AX75: 0 | AY75: =MAX(0,AV75+AW75-AX75) | AZ75: =BC74 | BA75: =IF(AZ75>0.005,AZ75*Debts!D20/12,0) | BB75: 0 | BC75: =MAX(0,AZ75+BA75-BB75) | BD75: =BG74 | BE75: =IF(BD75>0.005,BD75*Debts!D21/12,0) | BF75: 0 | BG75: =MAX(0,BD75+BE75-BF75) | BH75: =BK74 | BI75: =IF(BH75>0.005,BH75*Debts!D22/12,0) | BJ75: 0 | BK75: =MAX(0,BH75+BI75-BJ75) | BL75: =BO74 | BM75: =IF(BL75>0.005,BL75*Debts!D23/12,0) | BN75: 0 | BO75: =MAX(0,BL75+BM75-BN75) | BP75: =BS74 | BQ75: =IF(BP75>0.005,BP75*Debts!D24/12,0) | BR75: 0 | BS75: =MAX(0,BP75+BQ75-BR75) | BT75: =BW74 | BU75: =IF(BT75>0.005,BT75*Debts!D25/12,0) | BV75: 0 | BW75: =MAX(0,BT75+BU75-BV75) | BX75: =CA74 | BY75: =IF(BX75>0.005,BX75*Debts!D26/12,0) | BZ75: 0 | CA75: =MAX(0,BX75+BY75-BZ75) | CB75: =CE74 | CC75: =IF(CB75>0.005,CB75*Debts!D27/12,0) | CD75: 0 | CE75: =MAX(0,CB75+CC75-CD75) | CF75: =G75+K75+O75+S75+W75+AA75+AE75+AI75+AM75+AQ75+AU75+AY75+BC75+BG75+BK75+BO75+BS75+BW75+CA75+CE75 | CG75: =E75+I75+M75+Q75+U75+Y75+AC75+AG75+AK75+AO75+AS75+AW75+BA75+BE75+BI75+BM75+BQ75+BU75+BY75+CC75 | CH75: =CH74+CG75
B76: 72 | C76: =F76+J76+N76+R76+V76+Z76+AD76+AH76+AL76+AP76+AT76+AX76+BB76+BF76+BJ76+BN76+BR76+BV76+BZ76+CD76 | D76: =G75 | E76: =IF(D76>0.005,D76*Debts!D8/12,0) | F76: 0 | G76: =MAX(0,D76+E76-F76) | H76: =K75 | I76: =IF(H76>0.005,H76*Debts!D9/12,0) | J76: 0 | K76: =MAX(0,H76+I76-J76) | L76: =O75 | M76: =IF(L76>0.005,L76*Debts!D10/12,0) | N76: 0 | O76: =MAX(0,L76+M76-N76) | P76: =S75 | Q76: =IF(P76>0.005,P76*Debts!D11/12,0) | R76: 0 | S76: =MAX(0,P76+Q76-R76) | T76: =W75 | U76: =IF(T76>0.005,T76*Debts!D12/12,0) | V76: 0 | W76: =MAX(0,T76+U76-V76) | X76: =AA75 | Y76: =IF(X76>0.005,X76*Debts!D13/12,0) | Z76: 0 | AA76: =MAX(0,X76+Y76-Z76) | AB76: =AE75 | AC76: =IF(AB76>0.005,AB76*Debts!D14/12,0) | AD76: 0 | AE76: =MAX(0,AB76+AC76-AD76) | AF76: =AI75 | AG76: =IF(AF76>0.005,AF76*Debts!D15/12,0) | AH76: 0 | AI76: =MAX(0,AF76+AG76-AH76) | AJ76: =AM75 | AK76: =IF(AJ76>0.005,AJ76*Debts!D16/12,0) | AL76: 0 | AM76: =MAX(0,AJ76+AK76-AL76) | AN76: =AQ75 | AO76: =IF(AN76>0.005,AN76*Debts!D17/12,0) | AP76: 0 | AQ76: =MAX(0,AN76+AO76-AP76) | AR76: =AU75 | AS76: =IF(AR76>0.005,AR76*Debts!D18/12,0) | AT76: 0 | AU76: =MAX(0,AR76+AS76-AT76) | AV76: =AY75 | AW76: =IF(AV76>0.005,AV76*Debts!D19/12,0) | AX76: 0 | AY76: =MAX(0,AV76+AW76-AX76) | AZ76: =BC75 | BA76: =IF(AZ76>0.005,AZ76*Debts!D20/12,0) | BB76: 0 | BC76: =MAX(0,AZ76+BA76-BB76) | BD76: =BG75 | BE76: =IF(BD76>0.005,BD76*Debts!D21/12,0) | BF76: 0 | BG76: =MAX(0,BD76+BE76-BF76) | BH76: =BK75 | BI76: =IF(BH76>0.005,BH76*Debts!D22/12,0) | BJ76: 0 | BK76: =MAX(0,BH76+BI76-BJ76) | BL76: =BO75 | BM76: =IF(BL76>0.005,BL76*Debts!D23/12,0) | BN76: 0 | BO76: =MAX(0,BL76+BM76-BN76) | BP76: =BS75 | BQ76: =IF(BP76>0.005,BP76*Debts!D24/12,0) | BR76: 0 | BS76: =MAX(0,BP76+BQ76-BR76) | BT76: =BW75 | BU76: =IF(BT76>0.005,BT76*Debts!D25/12,0) | BV76: 0 | BW76: =MAX(0,BT76+BU76-BV76) | BX76: =CA75 | BY76: =IF(BX76>0.005,BX76*Debts!D26/12,0) | BZ76: 0 | CA76: =MAX(0,BX76+BY76-BZ76) | CB76: =CE75 | CC76: =IF(CB76>0.005,CB76*Debts!D27/12,0) | CD76: 0 | CE76: =MAX(0,CB76+CC76-CD76) | CF76: =G76+K76+O76+S76+W76+AA76+AE76+AI76+AM76+AQ76+AU76+AY76+BC76+BG76+BK76+BO76+BS76+BW76+CA76+CE76 | CG76: =E76+I76+M76+Q76+U76+Y76+AC76+AG76+AK76+AO76+AS76+AW76+BA76+BE76+BI76+BM76+BQ76+BU76+BY76+CC76 | CH76: =CH75+CG76
B77: 73 | C77: =F77+J77+N77+R77+V77+Z77+AD77+AH77+AL77+AP77+AT77+AX77+BB77+BF77+BJ77+BN77+BR77+BV77+BZ77+CD77 | D77: =G76 | E77: =IF(D77>0.005,D77*Debts!D8/12,0) | F77: 0 | G77: =MAX(0,D77+E77-F77) | H77: =K76 | I77: =IF(H77>0.005,H77*Debts!D9/12,0) | J77: 0 | K77: =MAX(0,H77+I77-J77) | L77: =O76 | M77: =IF(L77>0.005,L77*Debts!D10/12,0) | N77: 0 | O77: =MAX(0,L77+M77-N77) | P77: =S76 | Q77: =IF(P77>0.005,P77*Debts!D11/12,0) | R77: 0 | S77: =MAX(0,P77+Q77-R77) | T77: =W76 | U77: =IF(T77>0.005,T77*Debts!D12/12,0) | V77: 0 | W77: =MAX(0,T77+U77-V77) | X77: =AA76 | Y77: =IF(X77>0.005,X77*Debts!D13/12,0) | Z77: 0 | AA77: =MAX(0,X77+Y77-Z77) | AB77: =AE76 | AC77: =IF(AB77>0.005,AB77*Debts!D14/12,0) | AD77: 0 | AE77: =MAX(0,AB77+AC77-AD77) | AF77: =AI76 | AG77: =IF(AF77>0.005,AF77*Debts!D15/12,0) | AH77: 0 | AI77: =MAX(0,AF77+AG77-AH77) | AJ77: =AM76 | AK77: =IF(AJ77>0.005,AJ77*Debts!D16/12,0) | AL77: 0 | AM77: =MAX(0,AJ77+AK77-AL77) | AN77: =AQ76 | AO77: =IF(AN77>0.005,AN77*Debts!D17/12,0) | AP77: 0 | AQ77: =MAX(0,AN77+AO77-AP77) | AR77: =AU76 | AS77: =IF(AR77>0.005,AR77*Debts!D18/12,0) | AT77: 0 | AU77: =MAX(0,AR77+AS77-AT77) | AV77: =AY76 | AW77: =IF(AV77>0.005,AV77*Debts!D19/12,0) | AX77: 0 | AY77: =MAX(0,AV77+AW77-AX77) | AZ77: =BC76 | BA77: =IF(AZ77>0.005,AZ77*Debts!D20/12,0) | BB77: 0 | BC77: =MAX(0,AZ77+BA77-BB77) | BD77: =BG76 | BE77: =IF(BD77>0.005,BD77*Debts!D21/12,0) | BF77: 0 | BG77: =MAX(0,BD77+BE77-BF77) | BH77: =BK76 | BI77: =IF(BH77>0.005,BH77*Debts!D22/12,0) | BJ77: 0 | BK77: =MAX(0,BH77+BI77-BJ77) | BL77: =BO76 | BM77: =IF(BL77>0.005,BL77*Debts!D23/12,0) | BN77: 0 | BO77: =MAX(0,BL77+BM77-BN77) | BP77: =BS76 | BQ77: =IF(BP77>0.005,BP77*Debts!D24/12,0) | BR77: 0 | BS77: =MAX(0,BP77+BQ77-BR77) | BT77: =BW76 | BU77: =IF(BT77>0.005,BT77*Debts!D25/12,0) | BV77: 0 | BW77: =MAX(0,BT77+BU77-BV77) | BX77: =CA76 | BY77: =IF(BX77>0.005,BX77*Debts!D26/12,0) | BZ77: 0 | CA77: =MAX(0,BX77+BY77-BZ77) | CB77: =CE76 | CC77: =IF(CB77>0.005,CB77*Debts!D27/12,0) | CD77: 0 | CE77: =MAX(0,CB77+CC77-CD77) | CF77: =G77+K77+O77+S77+W77+AA77+AE77+AI77+AM77+AQ77+AU77+AY77+BC77+BG77+BK77+BO77+BS77+BW77+CA77+CE77 | CG77: =E77+I77+M77+Q77+U77+Y77+AC77+AG77+AK77+AO77+AS77+AW77+BA77+BE77+BI77+BM77+BQ77+BU77+BY77+CC77 | CH77: =CH76+CG77
B78: 74 | C78: =F78+J78+N78+R78+V78+Z78+AD78+AH78+AL78+AP78+AT78+AX78+BB78+BF78+BJ78+BN78+BR78+BV78+BZ78+CD78 | D78: =G77 | E78: =IF(D78>0.005,D78*Debts!D8/12,0) | F78: 0 | G78: =MAX(0,D78+E78-F78) | H78: =K77 | I78: =IF(H78>0.005,H78*Debts!D9/12,0) | J78: 0 | K78: =MAX(0,H78+I78-J78) | L78: =O77 | M78: =IF(L78>0.005,L78*Debts!D10/12,0) | N78: 0 | O78: =MAX(0,L78+M78-N78) | P78: =S77 | Q78: =IF(P78>0.005,P78*Debts!D11/12,0) | R78: 0 | S78: =MAX(0,P78+Q78-R78) | T78: =W77 | U78: =IF(T78>0.005,T78*Debts!D12/12,0) | V78: 0 | W78: =MAX(0,T78+U78-V78) | X78: =AA77 | Y78: =IF(X78>0.005,X78*Debts!D13/12,0) | Z78: 0 | AA78: =MAX(0,X78+Y78-Z78) | AB78: =AE77 | AC78: =IF(AB78>0.005,AB78*Debts!D14/12,0) | AD78: 0 | AE78: =MAX(0,AB78+AC78-AD78) | AF78: =AI77 | AG78: =IF(AF78>0.005,AF78*Debts!D15/12,0) | AH78: 0 | AI78: =MAX(0,AF78+AG78-AH78) | AJ78: =AM77 | AK78: =IF(AJ78>0.005,AJ78*Debts!D16/12,0) | AL78: 0 | AM78: =MAX(0,AJ78+AK78-AL78) | AN78: =AQ77 | AO78: =IF(AN78>0.005,AN78*Debts!D17/12,0) | AP78: 0 | AQ78: =MAX(0,AN78+AO78-AP78) | AR78: =AU77 | AS78: =IF(AR78>0.005,AR78*Debts!D18/12,0) | AT78: 0 | AU78: =MAX(0,AR78+AS78-AT78) | AV78: =AY77 | AW78: =IF(AV78>0.005,AV78*Debts!D19/12,0) | AX78: 0 | AY78: =MAX(0,AV78+AW78-AX78) | AZ78: =BC77 | BA78: =IF(AZ78>0.005,AZ78*Debts!D20/12,0) | BB78: 0 | BC78: =MAX(0,AZ78+BA78-BB78) | BD78: =BG77 | BE78: =IF(BD78>0.005,BD78*Debts!D21/12,0) | BF78: 0 | BG78: =MAX(0,BD78+BE78-BF78) | BH78: =BK77 | BI78: =IF(BH78>0.005,BH78*Debts!D22/12,0) | BJ78: 0 | BK78: =MAX(0,BH78+BI78-BJ78) | BL78: =BO77 | BM78: =IF(BL78>0.005,BL78*Debts!D23/12,0) | BN78: 0 | BO78: =MAX(0,BL78+BM78-BN78) | BP78: =BS77 | BQ78: =IF(BP78>0.005,BP78*Debts!D24/12,0) | BR78: 0 | BS78: =MAX(0,BP78+BQ78-BR78) | BT78: =BW77 | BU78: =IF(BT78>0.005,BT78*Debts!D25/12,0) | BV78: 0 | BW78: =MAX(0,BT78+BU78-BV78) | BX78: =CA77 | BY78: =IF(BX78>0.005,BX78*Debts!D26/12,0) | BZ78: 0 | CA78: =MAX(0,BX78+BY78-BZ78) | CB78: =CE77 | CC78: =IF(CB78>0.005,CB78*Debts!D27/12,0) | CD78: 0 | CE78: =MAX(0,CB78+CC78-CD78) | CF78: =G78+K78+O78+S78+W78+AA78+AE78+AI78+AM78+AQ78+AU78+AY78+BC78+BG78+BK78+BO78+BS78+BW78+CA78+CE78 | CG78: =E78+I78+M78+Q78+U78+Y78+AC78+AG78+AK78+AO78+AS78+AW78+BA78+BE78+BI78+BM78+BQ78+BU78+BY78+CC78 | CH78: =CH77+CG78
B79: 75 | C79: =F79+J79+N79+R79+V79+Z79+AD79+AH79+AL79+AP79+AT79+AX79+BB79+BF79+BJ79+BN79+BR79+BV79+BZ79+CD79 | D79: =G78 | E79: =IF(D79>0.005,D79*Debts!D8/12,0) | F79: 0 | G79: =MAX(0,D79+E79-F79) | H79: =K78 | I79: =IF(H79>0.005,H79*Debts!D9/12,0) | J79: 0 | K79: =MAX(0,H79+I79-J79) | L79: =O78 | M79: =IF(L79>0.005,L79*Debts!D10/12,0) | N79: 0 | O79: =MAX(0,L79+M79-N79) | P79: =S78 | Q79: =IF(P79>0.005,P79*Debts!D11/12,0) | R79: 0 | S79: =MAX(0,P79+Q79-R79) | T79: =W78 | U79: =IF(T79>0.005,T79*Debts!D12/12,0) | V79: 0 | W79: =MAX(0,T79+U79-V79) | X79: =AA78 | Y79: =IF(X79>0.005,X79*Debts!D13/12,0) | Z79: 0 | AA79: =MAX(0,X79+Y79-Z79) | AB79: =AE78 | AC79: =IF(AB79>0.005,AB79*Debts!D14/12,0) | AD79: 0 | AE79: =MAX(0,AB79+AC79-AD79) | AF79: =AI78 | AG79: =IF(AF79>0.005,AF79*Debts!D15/12,0) | AH79: 0 | AI79: =MAX(0,AF79+AG79-AH79) | AJ79: =AM78 | AK79: =IF(AJ79>0.005,AJ79*Debts!D16/12,0) | AL79: 0 | AM79: =MAX(0,AJ79+AK79-AL79) | AN79: =AQ78 | AO79: =IF(AN79>0.005,AN79*Debts!D17/12,0) | AP79: 0 | AQ79: =MAX(0,AN79+AO79-AP79) | AR79: =AU78 | AS79: =IF(AR79>0.005,AR79*Debts!D18/12,0) | AT79: 0 | AU79: =MAX(0,AR79+AS79-AT79) | AV79: =AY78 | AW79: =IF(AV79>0.005,AV79*Debts!D19/12,0) | AX79: 0 | AY79: =MAX(0,AV79+AW79-AX79) | AZ79: =BC78 | BA79: =IF(AZ79>0.005,AZ79*Debts!D20/12,0) | BB79: 0 | BC79: =MAX(0,AZ79+BA79-BB79) | BD79: =BG78 | BE79: =IF(BD79>0.005,BD79*Debts!D21/12,0) | BF79: 0 | BG79: =MAX(0,BD79+BE79-BF79) | BH79: =BK78 | BI79: =IF(BH79>0.005,BH79*Debts!D22/12,0) | BJ79: 0 | BK79: =MAX(0,BH79+BI79-BJ79) | BL79: =BO78 | BM79: =IF(BL79>0.005,BL79*Debts!D23/12,0) | BN79: 0 | BO79: =MAX(0,BL79+BM79-BN79) | BP79: =BS78 | BQ79: =IF(BP79>0.005,BP79*Debts!D24/12,0) | BR79: 0 | BS79: =MAX(0,BP79+BQ79-BR79) | BT79: =BW78 | BU79: =IF(BT79>0.005,BT79*Debts!D25/12,0) | BV79: 0 | BW79: =MAX(0,BT79+BU79-BV79) | BX79: =CA78 | BY79: =IF(BX79>0.005,BX79*Debts!D26/12,0) | BZ79: 0 | CA79: =MAX(0,BX79+BY79-BZ79) | CB79: =CE78 | CC79: =IF(CB79>0.005,CB79*Debts!D27/12,0) | CD79: 0 | CE79: =MAX(0,CB79+CC79-CD79) | CF79: =G79+K79+O79+S79+W79+AA79+AE79+AI79+AM79+AQ79+AU79+AY79+BC79+BG79+BK79+BO79+BS79+BW79+CA79+CE79 | CG79: =E79+I79+M79+Q79+U79+Y79+AC79+AG79+AK79+AO79+AS79+AW79+BA79+BE79+BI79+BM79+BQ79+BU79+BY79+CC79 | CH79: =CH78+CG79
B80: 76 | C80: =F80+J80+N80+R80+V80+Z80+AD80+AH80+AL80+AP80+AT80+AX80+BB80+BF80+BJ80+BN80+BR80+BV80+BZ80+CD80 | D80: =G79 | E80: =IF(D80>0.005,D80*Debts!D8/12,0) | F80: 0 | G80: =MAX(0,D80+E80-F80) | H80: =K79 | I80: =IF(H80>0.005,H80*Debts!D9/12,0) | J80: 0 | K80: =MAX(0,H80+I80-J80) | L80: =O79 | M80: =IF(L80>0.005,L80*Debts!D10/12,0) | N80: 0 | O80: =MAX(0,L80+M80-N80) | P80: =S79 | Q80: =IF(P80>0.005,P80*Debts!D11/12,0) | R80: 0 | S80: =MAX(0,P80+Q80-R80) | T80: =W79 | U80: =IF(T80>0.005,T80*Debts!D12/12,0) | V80: 0 | W80: =MAX(0,T80+U80-V80) | X80: =AA79 | Y80: =IF(X80>0.005,X80*Debts!D13/12,0) | Z80: 0 | AA80: =MAX(0,X80+Y80-Z80) | AB80: =AE79 | AC80: =IF(AB80>0.005,AB80*Debts!D14/12,0) | AD80: 0 | AE80: =MAX(0,AB80+AC80-AD80) | AF80: =AI79 | AG80: =IF(AF80>0.005,AF80*Debts!D15/12,0) | AH80: 0 | AI80: =MAX(0,AF80+AG80-AH80) | AJ80: =AM79 | AK80: =IF(AJ80>0.005,AJ80*Debts!D16/12,0) | AL80: 0 | AM80: =MAX(0,AJ80+AK80-AL80) | AN80: =AQ79 | AO80: =IF(AN80>0.005,AN80*Debts!D17/12,0) | AP80: 0 | AQ80: =MAX(0,AN80+AO80-AP80) | AR80: =AU79 | AS80: =IF(AR80>0.005,AR80*Debts!D18/12,0) | AT80: 0 | AU80: =MAX(0,AR80+AS80-AT80) | AV80: =AY79 | AW80: =IF(AV80>0.005,AV80*Debts!D19/12,0) | AX80: 0 | AY80: =MAX(0,AV80+AW80-AX80) | AZ80: =BC79 | BA80: =IF(AZ80>0.005,AZ80*Debts!D20/12,0) | BB80: 0 | BC80: =MAX(0,AZ80+BA80-BB80) | BD80: =BG79 | BE80: =IF(BD80>0.005,BD80*Debts!D21/12,0) | BF80: 0 | BG80: =MAX(0,BD80+BE80-BF80) | BH80: =BK79 | BI80: =IF(BH80>0.005,BH80*Debts!D22/12,0) | BJ80: 0 | BK80: =MAX(0,BH80+BI80-BJ80) | BL80: =BO79 | BM80: =IF(BL80>0.005,BL80*Debts!D23/12,0) | BN80: 0 | BO80: =MAX(0,BL80+BM80-BN80) | BP80: =BS79 | BQ80: =IF(BP80>0.005,BP80*Debts!D24/12,0) | BR80: 0 | BS80: =MAX(0,BP80+BQ80-BR80) | BT80: =BW79 | BU80: =IF(BT80>0.005,BT80*Debts!D25/12,0) | BV80: 0 | BW80: =MAX(0,BT80+BU80-BV80) | BX80: =CA79 | BY80: =IF(BX80>0.005,BX80*Debts!D26/12,0) | BZ80: 0 | CA80: =MAX(0,BX80+BY80-BZ80) | CB80: =CE79 | CC80: =IF(CB80>0.005,CB80*Debts!D27/12,0) | CD80: 0 | CE80: =MAX(0,CB80+CC80-CD80) | CF80: =G80+K80+O80+S80+W80+AA80+AE80+AI80+AM80+AQ80+AU80+AY80+BC80+BG80+BK80+BO80+BS80+BW80+CA80+CE80 | CG80: =E80+I80+M80+Q80+U80+Y80+AC80+AG80+AK80+AO80+AS80+AW80+BA80+BE80+BI80+BM80+BQ80+BU80+BY80+CC80 | CH80: =CH79+CG80
B81: 77 | C81: =F81+J81+N81+R81+V81+Z81+AD81+AH81+AL81+AP81+AT81+AX81+BB81+BF81+BJ81+BN81+BR81+BV81+BZ81+CD81 | D81: =G80 | E81: =IF(D81>0.005,D81*Debts!D8/12,0) | F81: 0 | G81: =MAX(0,D81+E81-F81) | H81: =K80 | I81: =IF(H81>0.005,H81*Debts!D9/12,0) | J81: 0 | K81: =MAX(0,H81+I81-J81) | L81: =O80 | M81: =IF(L81>0.005,L81*Debts!D10/12,0) | N81: 0 | O81: =MAX(0,L81+M81-N81) | P81: =S80 | Q81: =IF(P81>0.005,P81*Debts!D11/12,0) | R81: 0 | S81: =MAX(0,P81+Q81-R81) | T81: =W80 | U81: =IF(T81>0.005,T81*Debts!D12/12,0) | V81: 0 | W81: =MAX(0,T81+U81-V81) | X81: =AA80 | Y81: =IF(X81>0.005,X81*Debts!D13/12,0) | Z81: 0 | AA81: =MAX(0,X81+Y81-Z81) | AB81: =AE80 | AC81: =IF(AB81>0.005,AB81*Debts!D14/12,0) | AD81: 0 | AE81: =MAX(0,AB81+AC81-AD81) | AF81: =AI80 | AG81: =IF(AF81>0.005,AF81*Debts!D15/12,0) | AH81: 0 | AI81: =MAX(0,AF81+AG81-AH81) | AJ81: =AM80 | AK81: =IF(AJ81>0.005,AJ81*Debts!D16/12,0) | AL81: 0 | AM81: =MAX(0,AJ81+AK81-AL81) | AN81: =AQ80 | AO81: =IF(AN81>0.005,AN81*Debts!D17/12,0) | AP81: 0 | AQ81: =MAX(0,AN81+AO81-AP81) | AR81: =AU80 | AS81: =IF(AR81>0.005,AR81*Debts!D18/12,0) | AT81: 0 | AU81: =MAX(0,AR81+AS81-AT81) | AV81: =AY80 | AW81: =IF(AV81>0.005,AV81*Debts!D19/12,0) | AX81: 0 | AY81: =MAX(0,AV81+AW81-AX81) | AZ81: =BC80 | BA81: =IF(AZ81>0.005,AZ81*Debts!D20/12,0) | BB81: 0 | BC81: =MAX(0,AZ81+BA81-BB81) | BD81: =BG80 | BE81: =IF(BD81>0.005,BD81*Debts!D21/12,0) | BF81: 0 | BG81: =MAX(0,BD81+BE81-BF81) | BH81: =BK80 | BI81: =IF(BH81>0.005,BH81*Debts!D22/12,0) | BJ81: 0 | BK81: =MAX(0,BH81+BI81-BJ81) | BL81: =BO80 | BM81: =IF(BL81>0.005,BL81*Debts!D23/12,0) | BN81: 0 | BO81: =MAX(0,BL81+BM81-BN81) | BP81: =BS80 | BQ81: =IF(BP81>0.005,BP81*Debts!D24/12,0) | BR81: 0 | BS81: =MAX(0,BP81+BQ81-BR81) | BT81: =BW80 | BU81: =IF(BT81>0.005,BT81*Debts!D25/12,0) | BV81: 0 | BW81: =MAX(0,BT81+BU81-BV81) | BX81: =CA80 | BY81: =IF(BX81>0.005,BX81*Debts!D26/12,0) | BZ81: 0 | CA81: =MAX(0,BX81+BY81-BZ81) | CB81: =CE80 | CC81: =IF(CB81>0.005,CB81*Debts!D27/12,0) | CD81: 0 | CE81: =MAX(0,CB81+CC81-CD81) | CF81: =G81+K81+O81+S81+W81+AA81+AE81+AI81+AM81+AQ81+AU81+AY81+BC81+BG81+BK81+BO81+BS81+BW81+CA81+CE81 | CG81: =E81+I81+M81+Q81+U81+Y81+AC81+AG81+AK81+AO81+AS81+AW81+BA81+BE81+BI81+BM81+BQ81+BU81+BY81+CC81 | CH81: =CH80+CG81
B82: 78 | C82: =F82+J82+N82+R82+V82+Z82+AD82+AH82+AL82+AP82+AT82+AX82+BB82+BF82+BJ82+BN82+BR82+BV82+BZ82+CD82 | D82: =G81 | E82: =IF(D82>0.005,D82*Debts!D8/12,0) | F82: 0 | G82: =MAX(0,D82+E82-F82) | H82: =K81 | I82: =IF(H82>0.005,H82*Debts!D9/12,0) | J82: 0 | K82: =MAX(0,H82+I82-J82) | L82: =O81 | M82: =IF(L82>0.005,L82*Debts!D10/12,0) | N82: 0 | O82: =MAX(0,L82+M82-N82) | P82: =S81 | Q82: =IF(P82>0.005,P82*Debts!D11/12,0) | R82: 0 | S82: =MAX(0,P82+Q82-R82) | T82: =W81 | U82: =IF(T82>0.005,T82*Debts!D12/12,0) | V82: 0 | W82: =MAX(0,T82+U82-V82) | X82: =AA81 | Y82: =IF(X82>0.005,X82*Debts!D13/12,0) | Z82: 0 | AA82: =MAX(0,X82+Y82-Z82) | AB82: =AE81 | AC82: =IF(AB82>0.005,AB82*Debts!D14/12,0) | AD82: 0 | AE82: =MAX(0,AB82+AC82-AD82) | AF82: =AI81 | AG82: =IF(AF82>0.005,AF82*Debts!D15/12,0) | AH82: 0 | AI82: =MAX(0,AF82+AG82-AH82) | AJ82: =AM81 | AK82: =IF(AJ82>0.005,AJ82*Debts!D16/12,0) | AL82: 0 | AM82: =MAX(0,AJ82+AK82-AL82) | AN82: =AQ81 | AO82: =IF(AN82>0.005,AN82*Debts!D17/12,0) | AP82: 0 | AQ82: =MAX(0,AN82+AO82-AP82) | AR82: =AU81 | AS82: =IF(AR82>0.005,AR82*Debts!D18/12,0) | AT82: 0 | AU82: =MAX(0,AR82+AS82-AT82) | AV82: =AY81 | AW82: =IF(AV82>0.005,AV82*Debts!D19/12,0) | AX82: 0 | AY82: =MAX(0,AV82+AW82-AX82) | AZ82: =BC81 | BA82: =IF(AZ82>0.005,AZ82*Debts!D20/12,0) | BB82: 0 | BC82: =MAX(0,AZ82+BA82-BB82) | BD82: =BG81 | BE82: =IF(BD82>0.005,BD82*Debts!D21/12,0) | BF82: 0 | BG82: =MAX(0,BD82+BE82-BF82) | BH82: =BK81 | BI82: =IF(BH82>0.005,BH82*Debts!D22/12,0) | BJ82: 0 | BK82: =MAX(0,BH82+BI82-BJ82) | BL82: =BO81 | BM82: =IF(BL82>0.005,BL82*Debts!D23/12,0) | BN82: 0 | BO82: =MAX(0,BL82+BM82-BN82) | BP82: =BS81 | BQ82: =IF(BP82>0.005,BP82*Debts!D24/12,0) | BR82: 0 | BS82: =MAX(0,BP82+BQ82-BR82) | BT82: =BW81 | BU82: =IF(BT82>0.005,BT82*Debts!D25/12,0) | BV82: 0 | BW82: =MAX(0,BT82+BU82-BV82) | BX82: =CA81 | BY82: =IF(BX82>0.005,BX82*Debts!D26/12,0) | BZ82: 0 | CA82: =MAX(0,BX82+BY82-BZ82) | CB82: =CE81 | CC82: =IF(CB82>0.005,CB82*Debts!D27/12,0) | CD82: 0 | CE82: =MAX(0,CB82+CC82-CD82) | CF82: =G82+K82+O82+S82+W82+AA82+AE82+AI82+AM82+AQ82+AU82+AY82+BC82+BG82+BK82+BO82+BS82+BW82+CA82+CE82 | CG82: =E82+I82+M82+Q82+U82+Y82+AC82+AG82+AK82+AO82+AS82+AW82+BA82+BE82+BI82+BM82+BQ82+BU82+BY82+CC82 | CH82: =CH81+CG82
B83: 79 | C83: =F83+J83+N83+R83+V83+Z83+AD83+AH83+AL83+AP83+AT83+AX83+BB83+BF83+BJ83+BN83+BR83+BV83+BZ83+CD83 | D83: =G82 | E83: =IF(D83>0.005,D83*Debts!D8/12,0) | F83: 0 | G83: =MAX(0,D83+E83-F83) | H83: =K82 | I83: =IF(H83>0.005,H83*Debts!D9/12,0) | J83: 0 | K83: =MAX(0,H83+I83-J83) | L83: =O82 | M83: =IF(L83>0.005,L83*Debts!D10/12,0) | N83: 0 | O83: =MAX(0,L83+M83-N83) | P83: =S82 | Q83: =IF(P83>0.005,P83*Debts!D11/12,0) | R83: 0 | S83: =MAX(0,P83+Q83-R83) | T83: =W82 | U83: =IF(T83>0.005,T83*Debts!D12/12,0) | V83: 0 | W83: =MAX(0,T83+U83-V83) | X83: =AA82 | Y83: =IF(X83>0.005,X83*Debts!D13/12,0) | Z83: 0 | AA83: =MAX(0,X83+Y83-Z83) | AB83: =AE82 | AC83: =IF(AB83>0.005,AB83*Debts!D14/12,0) | AD83: 0 | AE83: =MAX(0,AB83+AC83-AD83) | AF83: =AI82 | AG83: =IF(AF83>0.005,AF83*Debts!D15/12,0) | AH83: 0 | AI83: =MAX(0,AF83+AG83-AH83) | AJ83: =AM82 | AK83: =IF(AJ83>0.005,AJ83*Debts!D16/12,0) | AL83: 0 | AM83: =MAX(0,AJ83+AK83-AL83) | AN83: =AQ82 | AO83: =IF(AN83>0.005,AN83*Debts!D17/12,0) | AP83: 0 | AQ83: =MAX(0,AN83+AO83-AP83) | AR83: =AU82 | AS83: =IF(AR83>0.005,AR83*Debts!D18/12,0) | AT83: 0 | AU83: =MAX(0,AR83+AS83-AT83) | AV83: =AY82 | AW83: =IF(AV83>0.005,AV83*Debts!D19/12,0) | AX83: 0 | AY83: =MAX(0,AV83+AW83-AX83) | AZ83: =BC82 | BA83: =IF(AZ83>0.005,AZ83*Debts!D20/12,0) | BB83: 0 | BC83: =MAX(0,AZ83+BA83-BB83) | BD83: =BG82 | BE83: =IF(BD83>0.005,BD83*Debts!D21/12,0) | BF83: 0 | BG83: =MAX(0,BD83+BE83-BF83) | BH83: =BK82 | BI83: =IF(BH83>0.005,BH83*Debts!D22/12,0) | BJ83: 0 | BK83: =MAX(0,BH83+BI83-BJ83) | BL83: =BO82 | BM83: =IF(BL83>0.005,BL83*Debts!D23/12,0) | BN83: 0 | BO83: =MAX(0,BL83+BM83-BN83) | BP83: =BS82 | BQ83: =IF(BP83>0.005,BP83*Debts!D24/12,0) | BR83: 0 | BS83: =MAX(0,BP83+BQ83-BR83) | BT83: =BW82 | BU83: =IF(BT83>0.005,BT83*Debts!D25/12,0) | BV83: 0 | BW83: =MAX(0,BT83+BU83-BV83) | BX83: =CA82 | BY83: =IF(BX83>0.005,BX83*Debts!D26/12,0) | BZ83: 0 | CA83: =MAX(0,BX83+BY83-BZ83) | CB83: =CE82 | CC83: =IF(CB83>0.005,CB83*Debts!D27/12,0) | CD83: 0 | CE83: =MAX(0,CB83+CC83-CD83) | CF83: =G83+K83+O83+S83+W83+AA83+AE83+AI83+AM83+AQ83+AU83+AY83+BC83+BG83+BK83+BO83+BS83+BW83+CA83+CE83 | CG83: =E83+I83+M83+Q83+U83+Y83+AC83+AG83+AK83+AO83+AS83+AW83+BA83+BE83+BI83+BM83+BQ83+BU83+BY83+CC83 | CH83: =CH82+CG83
B84: 80 | C84: =F84+J84+N84+R84+V84+Z84+AD84+AH84+AL84+AP84+AT84+AX84+BB84+BF84+BJ84+BN84+BR84+BV84+BZ84+CD84 | D84: =G83 | E84: =IF(D84>0.005,D84*Debts!D8/12,0) | F84: 0 | G84: =MAX(0,D84+E84-F84) | H84: =K83 | I84: =IF(H84>0.005,H84*Debts!D9/12,0) | J84: 0 | K84: =MAX(0,H84+I84-J84) | L84: =O83 | M84: =IF(L84>0.005,L84*Debts!D10/12,0) | N84: 0 | O84: =MAX(0,L84+M84-N84) | P84: =S83 | Q84: =IF(P84>0.005,P84*Debts!D11/12,0) | R84: 0 | S84: =MAX(0,P84+Q84-R84) | T84: =W83 | U84: =IF(T84>0.005,T84*Debts!D12/12,0) | V84: 0 | W84: =MAX(0,T84+U84-V84) | X84: =AA83 | Y84: =IF(X84>0.005,X84*Debts!D13/12,0) | Z84: 0 | AA84: =MAX(0,X84+Y84-Z84) | AB84: =AE83 | AC84: =IF(AB84>0.005,AB84*Debts!D14/12,0) | AD84: 0 | AE84: =MAX(0,AB84+AC84-AD84) | AF84: =AI83 | AG84: =IF(AF84>0.005,AF84*Debts!D15/12,0) | AH84: 0 | AI84: =MAX(0,AF84+AG84-AH84) | AJ84: =AM83 | AK84: =IF(AJ84>0.005,AJ84*Debts!D16/12,0) | AL84: 0 | AM84: =MAX(0,AJ84+AK84-AL84) | AN84: =AQ83 | AO84: =IF(AN84>0.005,AN84*Debts!D17/12,0) | AP84: 0 | AQ84: =MAX(0,AN84+AO84-AP84) | AR84: =AU83 | AS84: =IF(AR84>0.005,AR84*Debts!D18/12,0) | AT84: 0 | AU84: =MAX(0,AR84+AS84-AT84) | AV84: =AY83 | AW84: =IF(AV84>0.005,AV84*Debts!D19/12,0) | AX84: 0 | AY84: =MAX(0,AV84+AW84-AX84) | AZ84: =BC83 | BA84: =IF(AZ84>0.005,AZ84*Debts!D20/12,0) | BB84: 0 | BC84: =MAX(0,AZ84+BA84-BB84) | BD84: =BG83 | BE84: =IF(BD84>0.005,BD84*Debts!D21/12,0) | BF84: 0 | BG84: =MAX(0,BD84+BE84-BF84) | BH84: =BK83 | BI84: =IF(BH84>0.005,BH84*Debts!D22/12,0) | BJ84: 0 | BK84: =MAX(0,BH84+BI84-BJ84) | BL84: =BO83 | BM84: =IF(BL84>0.005,BL84*Debts!D23/12,0) | BN84: 0 | BO84: =MAX(0,BL84+BM84-BN84) | BP84: =BS83 | BQ84: =IF(BP84>0.005,BP84*Debts!D24/12,0) | BR84: 0 | BS84: =MAX(0,BP84+BQ84-BR84) | BT84: =BW83 | BU84: =IF(BT84>0.005,BT84*Debts!D25/12,0) | BV84: 0 | BW84: =MAX(0,BT84+BU84-BV84) | BX84: =CA83 | BY84: =IF(BX84>0.005,BX84*Debts!D26/12,0) | BZ84: 0 | CA84: =MAX(0,BX84+BY84-BZ84) | CB84: =CE83 | CC84: =IF(CB84>0.005,CB84*Debts!D27/12,0) | CD84: 0 | CE84: =MAX(0,CB84+CC84-CD84) | CF84: =G84+K84+O84+S84+W84+AA84+AE84+AI84+AM84+AQ84+AU84+AY84+BC84+BG84+BK84+BO84+BS84+BW84+CA84+CE84 | CG84: =E84+I84+M84+Q84+U84+Y84+AC84+AG84+AK84+AO84+AS84+AW84+BA84+BE84+BI84+BM84+BQ84+BU84+BY84+CC84 | CH84: =CH83+CG84
B85: 81 | C85: =F85+J85+N85+R85+V85+Z85+AD85+AH85+AL85+AP85+AT85+AX85+BB85+BF85+BJ85+BN85+BR85+BV85+BZ85+CD85 | D85: =G84 | E85: =IF(D85>0.005,D85*Debts!D8/12,0) | F85: 0 | G85: =MAX(0,D85+E85-F85) | H85: =K84 | I85: =IF(H85>0.005,H85*Debts!D9/12,0) | J85: 0 | K85: =MAX(0,H85+I85-J85) | L85: =O84 | M85: =IF(L85>0.005,L85*Debts!D10/12,0) | N85: 0 | O85: =MAX(0,L85+M85-N85) | P85: =S84 | Q85: =IF(P85>0.005,P85*Debts!D11/12,0) | R85: 0 | S85: =MAX(0,P85+Q85-R85) | T85: =W84 | U85: =IF(T85>0.005,T85*Debts!D12/12,0) | V85: 0 | W85: =MAX(0,T85+U85-V85) | X85: =AA84 | Y85: =IF(X85>0.005,X85*Debts!D13/12,0) | Z85: 0 | AA85: =MAX(0,X85+Y85-Z85) | AB85: =AE84 | AC85: =IF(AB85>0.005,AB85*Debts!D14/12,0) | AD85: 0 | AE85: =MAX(0,AB85+AC85-AD85) | AF85: =AI84 | AG85: =IF(AF85>0.005,AF85*Debts!D15/12,0) | AH85: 0 | AI85: =MAX(0,AF85+AG85-AH85) | AJ85: =AM84 | AK85: =IF(AJ85>0.005,AJ85*Debts!D16/12,0) | AL85: 0 | AM85: =MAX(0,AJ85+AK85-AL85) | AN85: =AQ84 | AO85: =IF(AN85>0.005,AN85*Debts!D17/12,0) | AP85: 0 | AQ85: =MAX(0,AN85+AO85-AP85) | AR85: =AU84 | AS85: =IF(AR85>0.005,AR85*Debts!D18/12,0) | AT85: 0 | AU85: =MAX(0,AR85+AS85-AT85) | AV85: =AY84 | AW85: =IF(AV85>0.005,AV85*Debts!D19/12,0) | AX85: 0 | AY85: =MAX(0,AV85+AW85-AX85) | AZ85: =BC84 | BA85: =IF(AZ85>0.005,AZ85*Debts!D20/12,0) | BB85: 0 | BC85: =MAX(0,AZ85+BA85-BB85) | BD85: =BG84 | BE85: =IF(BD85>0.005,BD85*Debts!D21/12,0) | BF85: 0 | BG85: =MAX(0,BD85+BE85-BF85) | BH85: =BK84 | BI85: =IF(BH85>0.005,BH85*Debts!D22/12,0) | BJ85: 0 | BK85: =MAX(0,BH85+BI85-BJ85) | BL85: =BO84 | BM85: =IF(BL85>0.005,BL85*Debts!D23/12,0) | BN85: 0 | BO85: =MAX(0,BL85+BM85-BN85) | BP85: =BS84 | BQ85: =IF(BP85>0.005,BP85*Debts!D24/12,0) | BR85: 0 | BS85: =MAX(0,BP85+BQ85-BR85) | BT85: =BW84 | BU85: =IF(BT85>0.005,BT85*Debts!D25/12,0) | BV85: 0 | BW85: =MAX(0,BT85+BU85-BV85) | BX85: =CA84 | BY85: =IF(BX85>0.005,BX85*Debts!D26/12,0) | BZ85: 0 | CA85: =MAX(0,BX85+BY85-BZ85) | CB85: =CE84 | CC85: =IF(CB85>0.005,CB85*Debts!D27/12,0) | CD85: 0 | CE85: =MAX(0,CB85+CC85-CD85) | CF85: =G85+K85+O85+S85+W85+AA85+AE85+AI85+AM85+AQ85+AU85+AY85+BC85+BG85+BK85+BO85+BS85+BW85+CA85+CE85 | CG85: =E85+I85+M85+Q85+U85+Y85+AC85+AG85+AK85+AO85+AS85+AW85+BA85+BE85+BI85+BM85+BQ85+BU85+BY85+CC85 | CH85: =CH84+CG85
B86: 82 | C86: =F86+J86+N86+R86+V86+Z86+AD86+AH86+AL86+AP86+AT86+AX86+BB86+BF86+BJ86+BN86+BR86+BV86+BZ86+CD86 | D86: =G85 | E86: =IF(D86>0.005,D86*Debts!D8/12,0) | F86: 0 | G86: =MAX(0,D86+E86-F86) | H86: =K85 | I86: =IF(H86>0.005,H86*Debts!D9/12,0) | J86: 0 | K86: =MAX(0,H86+I86-J86) | L86: =O85 | M86: =IF(L86>0.005,L86*Debts!D10/12,0) | N86: 0 | O86: =MAX(0,L86+M86-N86) | P86: =S85 | Q86: =IF(P86>0.005,P86*Debts!D11/12,0) | R86: 0 | S86: =MAX(0,P86+Q86-R86) | T86: =W85 | U86: =IF(T86>0.005,T86*Debts!D12/12,0) | V86: 0 | W86: =MAX(0,T86+U86-V86) | X86: =AA85 | Y86: =IF(X86>0.005,X86*Debts!D13/12,0) | Z86: 0 | AA86: =MAX(0,X86+Y86-Z86) | AB86: =AE85 | AC86: =IF(AB86>0.005,AB86*Debts!D14/12,0) | AD86: 0 | AE86: =MAX(0,AB86+AC86-AD86) | AF86: =AI85 | AG86: =IF(AF86>0.005,AF86*Debts!D15/12,0) | AH86: 0 | AI86: =MAX(0,AF86+AG86-AH86) | AJ86: =AM85 | AK86: =IF(AJ86>0.005,AJ86*Debts!D16/12,0) | AL86: 0 | AM86: =MAX(0,AJ86+AK86-AL86) | AN86: =AQ85 | AO86: =IF(AN86>0.005,AN86*Debts!D17/12,0) | AP86: 0 | AQ86: =MAX(0,AN86+AO86-AP86) | AR86: =AU85 | AS86: =IF(AR86>0.005,AR86*Debts!D18/12,0) | AT86: 0 | AU86: =MAX(0,AR86+AS86-AT86) | AV86: =AY85 | AW86: =IF(AV86>0.005,AV86*Debts!D19/12,0) | AX86: 0 | AY86: =MAX(0,AV86+AW86-AX86) | AZ86: =BC85 | BA86: =IF(AZ86>0.005,AZ86*Debts!D20/12,0) | BB86: 0 | BC86: =MAX(0,AZ86+BA86-BB86) | BD86: =BG85 | BE86: =IF(BD86>0.005,BD86*Debts!D21/12,0) | BF86: 0 | BG86: =MAX(0,BD86+BE86-BF86) | BH86: =BK85 | BI86: =IF(BH86>0.005,BH86*Debts!D22/12,0) | BJ86: 0 | BK86: =MAX(0,BH86+BI86-BJ86) | BL86: =BO85 | BM86: =IF(BL86>0.005,BL86*Debts!D23/12,0) | BN86: 0 | BO86: =MAX(0,BL86+BM86-BN86) | BP86: =BS85 | BQ86: =IF(BP86>0.005,BP86*Debts!D24/12,0) | BR86: 0 | BS86: =MAX(0,BP86+BQ86-BR86) | BT86: =BW85 | BU86: =IF(BT86>0.005,BT86*Debts!D25/12,0) | BV86: 0 | BW86: =MAX(0,BT86+BU86-BV86) | BX86: =CA85 | BY86: =IF(BX86>0.005,BX86*Debts!D26/12,0) | BZ86: 0 | CA86: =MAX(0,BX86+BY86-BZ86) | CB86: =CE85 | CC86: =IF(CB86>0.005,CB86*Debts!D27/12,0) | CD86: 0 | CE86: =MAX(0,CB86+CC86-CD86) | CF86: =G86+K86+O86+S86+W86+AA86+AE86+AI86+AM86+AQ86+AU86+AY86+BC86+BG86+BK86+BO86+BS86+BW86+CA86+CE86 | CG86: =E86+I86+M86+Q86+U86+Y86+AC86+AG86+AK86+AO86+AS86+AW86+BA86+BE86+BI86+BM86+BQ86+BU86+BY86+CC86 | CH86: =CH85+CG86
B87: 83 | C87: =F87+J87+N87+R87+V87+Z87+AD87+AH87+AL87+AP87+AT87+AX87+BB87+BF87+BJ87+BN87+BR87+BV87+BZ87+CD87 | D87: =G86 | E87: =IF(D87>0.005,D87*Debts!D8/12,0) | F87: 0 | G87: =MAX(0,D87+E87-F87) | H87: =K86 | I87: =IF(H87>0.005,H87*Debts!D9/12,0) | J87: 0 | K87: =MAX(0,H87+I87-J87) | L87: =O86 | M87: =IF(L87>0.005,L87*Debts!D10/12,0) | N87: 0 | O87: =MAX(0,L87+M87-N87) | P87: =S86 | Q87: =IF(P87>0.005,P87*Debts!D11/12,0) | R87: 0 | S87: =MAX(0,P87+Q87-R87) | T87: =W86 | U87: =IF(T87>0.005,T87*Debts!D12/12,0) | V87: 0 | W87: =MAX(0,T87+U87-V87) | X87: =AA86 | Y87: =IF(X87>0.005,X87*Debts!D13/12,0) | Z87: 0 | AA87: =MAX(0,X87+Y87-Z87) | AB87: =AE86 | AC87: =IF(AB87>0.005,AB87*Debts!D14/12,0) | AD87: 0 | AE87: =MAX(0,AB87+AC87-AD87) | AF87: =AI86 | AG87: =IF(AF87>0.005,AF87*Debts!D15/12,0) | AH87: 0 | AI87: =MAX(0,AF87+AG87-AH87) | AJ87: =AM86 | AK87: =IF(AJ87>0.005,AJ87*Debts!D16/12,0) | AL87: 0 | AM87: =MAX(0,AJ87+AK87-AL87) | AN87: =AQ86 | AO87: =IF(AN87>0.005,AN87*Debts!D17/12,0) | AP87: 0 | AQ87: =MAX(0,AN87+AO87-AP87) | AR87: =AU86 | AS87: =IF(AR87>0.005,AR87*Debts!D18/12,0) | AT87: 0 | AU87: =MAX(0,AR87+AS87-AT87) | AV87: =AY86 | AW87: =IF(AV87>0.005,AV87*Debts!D19/12,0) | AX87: 0 | AY87: =MAX(0,AV87+AW87-AX87) | AZ87: =BC86 | BA87: =IF(AZ87>0.005,AZ87*Debts!D20/12,0) | BB87: 0 | BC87: =MAX(0,AZ87+BA87-BB87) | BD87: =BG86 | BE87: =IF(BD87>0.005,BD87*Debts!D21/12,0) | BF87: 0 | BG87: =MAX(0,BD87+BE87-BF87) | BH87: =BK86 | BI87: =IF(BH87>0.005,BH87*Debts!D22/12,0) | BJ87: 0 | BK87: =MAX(0,BH87+BI87-BJ87) | BL87: =BO86 | BM87: =IF(BL87>0.005,BL87*Debts!D23/12,0) | BN87: 0 | BO87: =MAX(0,BL87+BM87-BN87) | BP87: =BS86 | BQ87: =IF(BP87>0.005,BP87*Debts!D24/12,0) | BR87: 0 | BS87: =MAX(0,BP87+BQ87-BR87) | BT87: =BW86 | BU87: =IF(BT87>0.005,BT87*Debts!D25/12,0) | BV87: 0 | BW87: =MAX(0,BT87+BU87-BV87) | BX87: =CA86 | BY87: =IF(BX87>0.005,BX87*Debts!D26/12,0) | BZ87: 0 | CA87: =MAX(0,BX87+BY87-BZ87) | CB87: =CE86 | CC87: =IF(CB87>0.005,CB87*Debts!D27/12,0) | CD87: 0 | CE87: =MAX(0,CB87+CC87-CD87) | CF87: =G87+K87+O87+S87+W87+AA87+AE87+AI87+AM87+AQ87+AU87+AY87+BC87+BG87+BK87+BO87+BS87+BW87+CA87+CE87 | CG87: =E87+I87+M87+Q87+U87+Y87+AC87+AG87+AK87+AO87+AS87+AW87+BA87+BE87+BI87+BM87+BQ87+BU87+BY87+CC87 | CH87: =CH86+CG87
